Workbook
Name Costco_COGS: 'Raw Data'!$C$29:$M$29
Name Costco_CurrentAssets: 'Raw Data'!$C$31:$M$31
Name Costco_CurrentLiabilities: 'Raw Data'!$C$32:$M$32
Name Costco_Inventory: 'Raw Data'!$C$43:$M$43
Name Costco_LIFOReserve: 'Raw Data'!$C$44:$M$44
Name Costco_MembershipFeeRevenueIncluded_FY2025: 'Raw Data'!$D$110
Name Costco_MembershipFees: 'Raw Data'!$C$46:$M$46
Name Costco_NetIncome: 'Raw Data'!$C$30:$M$30
Name Costco_OperatingIncome: 'Raw Data'!$C$40:$M$40
Name Costco_OperatingLease: 'Raw Data'!$C$41:$M$41
Name Costco_Revenue: 'Raw Data'!$C$28:$M$28
Name Costco_TotalAssets: 'Raw Data'!$C$42:$M$42
Name Costco_TotalDebt: 'Raw Data'!$C$34:$M$34
Name Costco_TotalEquity: 'Raw Data'!$C$33:$M$33
Name Costco_TotalRevenue: 'Raw Data'!$C$45:$M$45
Name CR_Costco: 'Ratio Calculations'!$B$29:$K$29
Name CR_Kroger: 'Ratio Calculations'!$B$30:$K$30
Name CR_SamsClub: 'Ratio Calculations'!$B$31:$K$31
Name CR_Walmart: 'Ratio Calculations'!$B$28:$K$28
Name CR_WholeFoods: 'Ratio Calculations'!$B$32:$K$32
Name DE_Costco: 'Ratio Calculations'!$B$36:$K$36
Name DE_Kroger: 'Ratio Calculations'!$B$37:$K$37
Name DE_SamsClub: 'Ratio Calculations'!$B$38:$K$38
Name DE_Walmart: 'Ratio Calculations'!$B$35:$K$35
Name DE_WholeFoods: 'Ratio Calculations'!$B$39:$K$39
Name DEL_Costco: 'Ratio Calculations'!$B$43:$K$43
Name DEL_Kroger: 'Ratio Calculations'!$B$44:$K$44
Name DEL_SamsClub: 'Ratio Calculations'!$B$45:$K$45
Name DEL_Walmart: 'Ratio Calculations'!$B$42:$K$42
Name DEL_WholeFoods: 'Ratio Calculations'!$B$46:$K$46
Name GM_Costco: 'Ratio Calculations'!$B$8:$K$8
Name GM_Kroger: 'Ratio Calculations'!$B$9:$K$9
Name GM_SamsClub: 'Ratio Calculations'!$B$10:$K$10
Name GM_Walmart: 'Ratio Calculations'!$B$7:$K$7
Name GM_WholeFoods: 'Ratio Calculations'!$B$11:$K$11
Name GR_Costco: 'Ratio Calculations'!$B$50:$K$50
Name GR_Kroger: 'Ratio Calculations'!$B$51:$K$51
Name GR_SamsClub: 'Ratio Calculations'!$B$52:$K$52
Name GR_Walmart: 'Ratio Calculations'!$B$49:$K$49
Name GR_WholeFoods: 'Ratio Calculations'!$B$53:$K$53
Name Kroger_COGS: 'Raw Data'!$C$51:$M$51
Name Kroger_CurrentAssets: 'Raw Data'!$C$53:$M$53
Name Kroger_CurrentLiabilities: 'Raw Data'!$C$54:$M$54
Name Kroger_LIFOReserve: 'Raw Data'!$C$67:$M$67
Name Kroger_LifoReserve_FY2016: 'Raw Data'!$D$108
Name Kroger_LifoReserve_FY2025: 'Raw Data'!$D$107
Name Kroger_NetIncome: 'Raw Data'!$C$52:$M$52
Name Kroger_OperatingIncome: 'Raw Data'!$C$64:$M$64
Name Kroger_OperatingLease: 'Raw Data'!$C$65:$M$65
Name Kroger_ProceedsFromIssuanceOf_FY2024: 'Raw Data'!$D$103
Name Kroger_RestructuringAndAssetImpairment_FY2025: 'Raw Data'!$D$106
Name Kroger_Revenue: 'Raw Data'!$C$50:$M$50
Name Kroger_ShareRepurchases_FY2024: 'Raw Data'!$D$104
Name Kroger_ShareRepurchases_FY2025: 'Raw Data'!$D$105
Name Kroger_TotalAssets: 'Raw Data'!$C$66:$M$66
Name Kroger_TotalDebt: 'Raw Data'!$C$56:$M$56
Name Kroger_TotalEquity: 'Raw Data'!$C$55:$M$55
Name NM_Costco: 'Ratio Calculations'!$B$22:$K$22
Name NM_Kroger: 'Ratio Calculations'!$B$23:$K$23
Name NM_SamsClub: 'Ratio Calculations'!$B$24:$K$24

Sheet Cover
B2: LOGO
C3: 01 — COVER · COMPETITOR SCORECARD · FY2016–FY2025 · SEC 10-K DATA
B7: Competitor Scorecard:
B8: Walmart, Costco, Kroger & Sam's Club
B9: with Whole Foods Market on a best-effort basis
B11: Ten-year financial comparison (FY2016–FY2025) built from SEC 10-K filings: capital structure, resilience through 2020–2023, and margin pressure — every ratio a live formula traceable to its XBRL fact.
B13: Prepared by | C13: Ryan Barry
B14: Date | C14: September 18, 2026
B15: Data source | C15: SEC EDGAR – 10-K XBRL filings (companyfacts API and instance documents)
B16: Coverage | C16: Walmart Inc. · Costco Wholesale Corp. · The Kroger Co. – full 10-K coverage FY2016–FY2025
C17: Sam's Club – Walmart reportable segment (ASC 280): sales, operating income, assets; cost of sales FY2022+
C18: Whole Foods Market – standalone 10-Ks FY2016–FY2017; Amazon 'Physical stores' net sales thereafter
B19: Units | C19: USD millions unless stated; fiscal years labelled by SEC frame convention (see Methodology)
B20: Status | C20: All formulas live; recalculated in Excel with zero formula errors
B22: Contents
B23: Executive Summary | C23: Findings against the three key questions, trend shifts, data caveats
B24: Raw Data | C24: As-reported inputs by company and year, named ranges, SEC citations, debt build
B25: Ratio Calculations | C25: Gross margin, operating margin, net margin, current ratio, debt-to-equity, revenue growth
B26: Scorecard | C26: Latest-year ranking per metric with conditional formatting and takeaways
B27: Trend | C27: Native line charts FY2016–FY2025 with the FY2020–FY2023 shock window shaded
B28: Methodology & Tools | C28: Sources, techniques, accounting-policy comparability, assumptions
B29: Data Lineage | C29: Every input value with XBRL tag, accession number, filing date and restatement flag
B31: Personal portfolio project built from public filings only. Not an H-E-B work product; no non-public information used.

Sheet Executive Summary
B1: COMPETITOR SCORECARD · FY2016–FY2025 · SEC 10-K DATA
B2: Executive Summary
B3: Findings are stated against the three key questions. Every figure quoted below is a live formula into the Ratio Calculations and Raw Data tabs; cited transactions (debt issued, buybacks, charges) are on Raw Data under 'Supporting facts'.
B4: 1. Capital structure & financing strategy — who is financed most conservatively, and has that changed?
B5: BOTTOM LINE: Costco is the most conservatively financed of the group and has become more so every year since FY2021. Walmart's leverage is unchanged over the decade. Kroger has nearly tripled its debt-to-equity since FY2023 to fund share repurchases after the Albertsons merger collapsed – a deliberate capital-return decision, but the one red flag in the set.
B6: ="• Costco is financed most conservatively and is still de-levering: debt-to-equity fell from "&TEXT(_xlfn.XLOOKUP(2016,RatioYears,DE_Costco),"0.00")&"x"&" in FY2016 to "&TEXT(_xlfn.XLOOKUP(2025,RatioYears,DE_Costco),"0.00")&"x"&" in FY2025. Total debt has stayed near "&"$"&TEXT(_xlfn.XLOOKUP(2025,Years,Costco_TotalDebt)/1000,"0.0")&"B"&" while equity compounded from "&"$"&TEXT(_xlfn.XLOOKUP(2016,Years,Costco_TotalEquity)/1000,"0.0")&"B"&" to "&"$"&TEXT(_xlfn.XLOOKUP(2025,Years,Costco_TotalEquity)/1000,"0.0")&"B"&" – growth and buybacks are funded from operating cash flow, not borrowing." -> • Costco is financed most conservatively and is still de-levering: debt-to-equity fell from 0.45x in FY2016 to 0.25x in FY2025. Total debt has stayed near $7.3B while equity compounded from $12.3B to $29.2B – growth and buybacks are funded from operating cash flow, not borrowing.
B7: ="• Walmart is stable by design: debt-to-equity has held in a "&TEXT(MIN(DE_Walmart),"0.00")&"x"&"–"&TEXT(MAX(DE_Walmart),"0.00")&"x"&" band for the whole decade. Total debt in FY2025 ("&"$"&TEXT(_xlfn.XLOOKUP(2025,Years,Walmart_TotalDebt)/1000,"0.0")&"B"&") is only "&TEXT(_xlfn.XLOOKUP(2025,Years,Walmart_TotalDebt)/_xlfn.XLOOKUP(2016,Years,Walmart_TotalDebt)-1,"0.0%")&" above FY2016 ("&"$"&TEXT(_xlfn.XLOOKUP(2016,Years,Walmart_TotalDebt)/1000,"0.0")&"B"&") on revenue that is "&TEXT(_xlfn.XLOOKUP(2025,Years,Walmart_Revenue)/_xlfn.XLOOKUP(2016,Years,Walmart_Revenue)-1,"0.0%")&" larger, so leverage has fallen relative to the size of the business." -> • Walmart is stable by design: debt-to-equity has held in a 0.47x–0.73x band for the whole decade. Total debt in FY2025 ($51.5B) is only 12.2% above FY2016 ($45.9B) on revenue that is 46.8% larger, so leverage has fallen relative to the size of the business.
B8: ="• Kroger is the outlier and the one genuine red flag. It de-levered from "&TEXT(_xlfn.XLOOKUP(2016,RatioYears,DE_Kroger),"0.00")&"x"&" (FY2016) to "&TEXT(_xlfn.XLOOKUP(2023,RatioYears,DE_Kroger),"0.00")&"x"&" (FY2023), then re-levered to "&TEXT(_xlfn.XLOOKUP(2024,RatioYears,DE_Kroger),"0.00")&"x"&" in FY2024 and "&TEXT(_xlfn.XLOOKUP(2025,RatioYears,DE_Kroger),"0.00")&"x"&" in FY2025. The FY2024 10-K shows "&"$"&TEXT(Kroger_ProceedsFromIssuanceOf_FY2024/1000,"0.0")&"B"&" of long-term debt issued for the Albertsons merger (terminated December 2024) and "&"$"&TEXT(Kroger_ShareRepurchases_FY2024/1000,"0.0")&"B"&" of share repurchases, followed by a further "&"$"&TEXT(Kroger_ShareRepurchases_FY2025/1000,"0.0")&"B"&" of repurchases in FY2025; equity fell from "&"$"&TEXT(_xlfn.XLOOKUP(2023,Years,Kroger_TotalEquity)/1000,"0.0")&"B"&" to "&"$"&TEXT(_xlfn.XLOOKUP(2025,Years,Kroger_TotalEquity)/1000,"0.0")&"B"&" in two years." -> • Kroger is the outlier and the one genuine red flag. It de-levered from 2.10x (FY2016) to 1.05x (FY2023), then re-levered to 2.16x in FY2024 and 2.96x in FY2025. The FY2024 10-K shows $10.5B of long-term debt issued for the Albertsons merger (terminated December 2024) and $4.2B of share repurchases, followed by a further $2.7B of repurchases in FY2025; equity fell from $11.6B to $5.9B in two years.
B9: =_xlfn._LONGTEXT("• Reading: Kroger's leverage is funding buybacks, not growth – revenue has been flat since FY2022 – and it is doing so on an equity base shrunk by charges. That is a deliberate capital-return choice, but it leaves the least financial flexibility in the gr","oup and would be the first balance sheet to strain if margins slip further.") -> • Reading: Kroger's leverage is funding buybacks, not growth – revenue has been flat since FY2022 – and it is doing so on an equity base shrunk by charges. That is a deliberate capital-return choice, but it leaves the least financial flexibility in the group and would be the first balance sheet to strain if margins slip further.
B10: ="• Lease-adjusted view (ASC 842): including operating lease liabilities lifts every ratio but changes no ranking – FY2025 debt-to-equity incl. leases is "&TEXT(_xlfn.XLOOKUP(2025,RatioYears,DEL_Costco),"0.00")&"x"&" Costco, "&TEXT(_xlfn.XLOOKUP(2025,RatioYears,DEL_Walmart),"0.00")&"x"&" Walmart, "&TEXT(_xlfn.XLOOKUP(2025,RatioYears,DEL_Kroger),"0.00")&"x"&" Kroger." -> • Lease-adjusted view (ASC 842): including operating lease liabilities lifts every ratio but changes no ranking – FY2025 debt-to-equity incl. leases is 0.34x Costco, 0.63x Walmart, 4.16x Kroger.
B12: 2. Resilience through 2020–2023 — who absorbed COVID and the inflation spike best, and who took the biggest hit?
B13: BOTTOM LINE: Costco absorbed the shock best – revenue, net margin and liquidity all rose through the window. Walmart took the biggest hit, with FY2022 gross and operating margins the lowest of the decade, but recovered within two years. Kroger's margin swings were fuel-mix effects, not financial stress.
B14: ="• Costco absorbed the shock best. Revenue grew "&TEXT(_xlfn.XLOOKUP(2020,RatioYears,GR_Costco),"0.0%")&", "&TEXT(_xlfn.XLOOKUP(2021,RatioYears,GR_Costco),"0.0%")&" and "&TEXT(_xlfn.XLOOKUP(2022,RatioYears,GR_Costco),"0.0%")&" in FY2020–FY2022; net margin rose from "&TEXT(_xlfn.XLOOKUP(2019,RatioYears,NM_Costco),"0.0%")&" (FY2019) to "&TEXT(_xlfn.XLOOKUP(2023,RatioYears,NM_Costco),"0.0%")&" (FY2023); the current ratio peaked at "&TEXT(_xlfn.XLOOKUP(2020,RatioYears,CR_Costco),"0.00")&"x"&" in FY2020 and never fell below "&TEXT(MIN(CR_Costco),"0.00")&"x"&". Gross margin dipped to "&TEXT(_xlfn.XLOOKUP(2022,RatioYears,GM_Costco),"0.0%")&" in FY2022 – inflation absorbed on members' behalf – and has since recovered to "&TEXT(_xlfn.XLOOKUP(2025,RatioYears,GM_Costco),"0.0%")&"." -> • Costco absorbed the shock best. Revenue grew 9.3%, 17.7% and 16.0% in FY2020–FY2022; net margin rose from 2.4% (FY2019) to 2.6% (FY2023); the current ratio peaked at 1.13x in FY2020 and never fell below 0.97x. Gross margin dipped to 10.5% in FY2022 – inflation absorbed on members' behalf – and has since recovered to 11.1%.
B15: ="• Walmart took the biggest single-year hit, in FY2022 (year ended January 2023): gross margin fell to "&TEXT(_xlfn.XLOOKUP(2022,RatioYears,GM_Walmart),"0.0%")&" and operating margin to "&TEXT(_xlfn.XLOOKUP(2022,RatioYears,OM_Walmart),"0.0%")&", the lowest of the decade, as inventory built and was marked down; the current ratio fell from "&TEXT(_xlfn.XLOOKUP(2020,RatioYears,CR_Walmart),"0.00")&"x"&" (FY2020) to "&TEXT(_xlfn.XLOOKUP(2022,RatioYears,CR_Walmart),"0.00")&"x"&". Recovery was quick – operating margin was back to "&TEXT(_xlfn.XLOOKUP(2024,RatioYears,OM_Walmart),"0.0%")&" by FY2024 and net margin to "&TEXT(_xlfn.XLOOKUP(2025,RatioYears,NM_Walmart),"0.0%")&" in FY2025." -> • Walmart took the biggest single-year hit, in FY2022 (year ended January 2023): gross margin fell to 23.5% and operating margin to 3.4%, the lowest of the decade, as inventory built and was marked down; the current ratio fell from 0.97x (FY2020) to 0.82x. Recovery was quick – operating margin was back to 4.4% by FY2024 and net margin to 3.1% in FY2025.
B16: ="• Kroger's margins moved most but for a mix reason: gross margin jumped to "&TEXT(_xlfn.XLOOKUP(2020,RatioYears,GM_Kroger),"0.0%")&" in FY2020 when low-margin fuel sales collapsed, then fell to "&TEXT(_xlfn.XLOOKUP(2022,RatioYears,GM_Kroger),"0.0%")&" in FY2022 as fuel prices spiked. Through FY2020–FY2023 net margin stayed between "&TEXT(MIN(INDEX(NM_Kroger,1,5):INDEX(NM_Kroger,1,8)),"0.0%")&" and "&TEXT(MAX(INDEX(NM_Kroger,1,5):INDEX(NM_Kroger,1,8)),"0.0%")&", and the current ratio ("&TEXT(MIN(INDEX(CR_Kroger,1,5):INDEX(CR_Kroger,1,8)),"0.00")&"x"&"–"&TEXT(MAX(INDEX(CR_Kroger,1,5):INDEX(CR_Kroger,1,8)),"0.00")&"x"&") is structurally the lowest of the three – a feature of its working-capital model, not a shock effect." -> • Kroger's margins moved most but for a mix reason: gross margin jumped to 23.3% in FY2020 when low-margin fuel sales collapsed, then fell to 21.4% in FY2022 as fuel prices spiked. Through FY2020–FY2023 net margin stayed between 1.2% and 2.0%, and the current ratio (0.74x–0.81x) is structurally the lowest of the three – a feature of its working-capital model, not a shock effect.
B17: ="• Sam's Club (segment) grew net sales "&TEXT(_xlfn.XLOOKUP(2020,RatioYears,GR_SamsClub),"0.0%")&", "&TEXT(_xlfn.XLOOKUP(2021,RatioYears,GR_SamsClub),"0.0%")&" and "&TEXT(_xlfn.XLOOKUP(2022,RatioYears,GR_SamsClub),"0.0%")&" over FY2020–FY2022 with operating margin between "&TEXT(MIN(INDEX(OM_SamsClub,1,5):INDEX(OM_SamsClub,1,8)),"0.0%")&" and "&TEXT(MAX(INDEX(OM_SamsClub,1,5):INDEX(OM_SamsClub,1,8)),"0.0%")&" through FY2020–FY2023 – the club format was the clear beneficiary of pandemic-era bulk buying and inflation trade-down." -> • Sam's Club (segment) grew net sales 8.7%, 15.1% and 14.7% over FY2020–FY2022 with operating margin between 2.3% and 3.1% through FY2020–FY2023 – the club format was the clear beneficiary of pandemic-era bulk buying and inflation trade-down.
B19: 3. Margin pressure since 2016 — who has felt it most, and is it cost, pricing, or mix?
B20: BOTTOM LINE: Walmart has felt the most persistent pressure, and it is pricing and mix – gross margin gave up ground while SG&A held. Kroger's decline is the steepest in operating terms but sits below gross profit: cost growth and FY2025 one-off charges, not pricing. Costco shows no pressure at all; Sam's Club's margin is improving.
B21: ="• Walmart shows the most persistent pressure among the full filers: gross margin "&TEXT(_xlfn.XLOOKUP(2016,RatioYears,GM_Walmart),"0.0%")&" (FY2016) → "&TEXT(_xlfn.XLOOKUP(2022,RatioYears,GM_Walmart),"0.0%")&" (FY2022 low) → "&TEXT(_xlfn.XLOOKUP(2025,RatioYears,GM_Walmart),"0.0%")&" (FY2025), and operating margin "&TEXT(_xlfn.XLOOKUP(2016,RatioYears,OM_Walmart),"0.0%")&" → "&TEXT(_xlfn.XLOOKUP(2025,RatioYears,OM_Walmart),"0.0%")&". The driver is pricing and mix, not cost: the gross-margin give-up tracks Walmart's stated price investment and the shift toward lower-margin e-commerce and grocery, while the operating-margin gap to gross margin has not widened – SG&A is under control." -> • Walmart shows the most persistent pressure among the full filers: gross margin 24.9% (FY2016) → 23.5% (FY2022 low) → 24.2% (FY2025), and operating margin 4.7% → 4.2%. The driver is pricing and mix, not cost: the gross-margin give-up tracks Walmart's stated price investment and the shift toward lower-margin e-commerce and grocery, while the operating-margin gap to gross margin has not widened – SG&A is under control.
B22: ="• Kroger's decline is the largest in operating terms – "&TEXT(_xlfn.XLOOKUP(2016,RatioYears,OM_Kroger),"0.0%")&" in FY2016 to "&TEXT(_xlfn.XLOOKUP(2025,RatioYears,OM_Kroger),"0.0%")&" in FY2025 – but the FY2025 figure includes "&"$"&TEXT(Kroger_RestructuringAndAssetImpairment_FY2025/1000,"0.0")&"B"&" of restructuring and asset-impairment charges; excluding them, operating margin would be about "&TEXT((_xlfn.XLOOKUP(2025,Years,Kroger_OperatingIncome)+Kroger_RestructuringAndAssetImpairment_FY2025)/_xlfn.XLOOKUP(2025,Years,Kroger_Revenue),"0.0%")&". Its gross margin is essentially unchanged ("&TEXT(_xlfn.XLOOKUP(2016,RatioYears,GM_Kroger),"0.0%")&" → "&TEXT(_xlfn.XLOOKUP(2025,RatioYears,GM_Kroger),"0.0%")&"), so the pressure is below gross profit: cost (labour, D&A) and one-off charges rather than pricing." -> • Kroger's decline is the largest in operating terms – 3.0% in FY2016 to 1.3% in FY2025 – but the FY2025 figure includes $2.7B of restructuring and asset-impairment charges; excluding them, operating margin would be about 3.1%. Its gross margin is essentially unchanged (22.4% → 23.3%), so the pressure is below gross profit: cost (labour, D&A) and one-off charges rather than pricing.
B23: ="• Costco shows no pressure: gross margin is flat by design ("&TEXT(_xlfn.XLOOKUP(2016,RatioYears,GM_Costco),"0.0%")&" → "&TEXT(_xlfn.XLOOKUP(2025,RatioYears,GM_Costco),"0.0%")&") while net margin expanded from "&TEXT(_xlfn.XLOOKUP(2016,RatioYears,NM_Costco),"0.0%")&" to "&TEXT(_xlfn.XLOOKUP(2025,RatioYears,NM_Costco),"0.0%")&" – membership fees ("&"$"&TEXT(Costco_MembershipFeeRevenueIncluded_FY2025/1000,"0.0")&"B"&" in FY2025, equal to "&TEXT(Costco_MembershipFeeRevenueIncluded_FY2025/_xlfn.XLOOKUP(2025,Years,Costco_Revenue),"0.0%")&" of net sales, excluded from net sales here and carrying no cost of sales) and operating leverage on "&TEXT(_xlfn.XLOOKUP(2025,Years,Costco_Revenue)/_xlfn.XLOOKUP(2016,Years,Costco_Revenue)-1,"0.0%")&" cumulative revenue growth." -> • Costco shows no pressure: gross margin is flat by design (11.3% → 11.1%) while net margin expanded from 2.0% to 3.0% – membership fees ($5.3B in FY2025, equal to 2.0% of net sales, excluded from net sales here and carrying no cost of sales) and operating leverage on 132.5% cumulative revenue growth.
B24: ="• Sam's Club is improving: segment gross margin rose from "&TEXT(_xlfn.XLOOKUP(2022,RatioYears,GM_SamsClub),"0.0%")&" (FY2022) to "&TEXT(_xlfn.XLOOKUP(2025,RatioYears,GM_SamsClub),"0.0%")&" (FY2025) – a mix shift toward members-only pricing and away from fuel. Whole Foods was already under pricing pressure before the Amazon deal: gross margin "&TEXT(_xlfn.XLOOKUP(2016,RatioYears,GM_WholeFoods),"0.0%")&" → "&TEXT(_xlfn.XLOOKUP(2017,RatioYears,GM_WholeFoods),"0.0%")&" and operating margin "&TEXT(_xlfn.XLOOKUP(2016,RatioYears,OM_WholeFoods),"0.0%")&" → "&TEXT(_xlfn.XLOOKUP(2017,RatioYears,OM_WholeFoods),"0.0%")&" in its last two standalone years." -> • Sam's Club is improving: segment gross margin rose from 10.4% (FY2022) to 11.3% (FY2025) – a mix shift toward members-only pricing and away from fuel. Whole Foods was already under pricing pressure before the Amazon deal: gross margin 34.4% → 33.7% and operating margin 5.5% → 2.9% in its last two standalone years.
B26: Notable trend shifts since FY2016
B27: ="• Costco's step-change: revenue growth of "&TEXT(_xlfn.XLOOKUP(2021,RatioYears,GR_Costco),"0.0%")&" and "&TEXT(_xlfn.XLOOKUP(2022,RatioYears,GR_Costco),"0.0%")&" in FY2021–FY2022 lifted it from "&"$"&TEXT(_xlfn.XLOOKUP(2016,Years,Costco_Revenue)/1000,"0.0")&"B"&" to "&"$"&TEXT(_xlfn.XLOOKUP(2025,Years,Costco_Revenue)/1000,"0.0")&"B"&" – it is now "&TEXT(_xlfn.XLOOKUP(2025,Years,Costco_Revenue)/_xlfn.XLOOKUP(2025,Years,Kroger_Revenue),"0.0")&"x Kroger's size, versus "&TEXT(_xlfn.XLOOKUP(2016,Years,Costco_Revenue)/_xlfn.XLOOKUP(2016,Years,Kroger_Revenue),"0.0")&"x in FY2016." -> • Costco's step-change: revenue growth of 17.7% and 16.0% in FY2021–FY2022 lifted it from $116.1B to $269.9B – it is now 1.8x Kroger's size, versus 1.0x in FY2016.
B28: ="• Kroger's reversal: five years of de-leveraging (FY2018–FY2023) undone in two. Debt-to-equity "&TEXT(_xlfn.XLOOKUP(2023,RatioYears,DE_Kroger),"0.00")&"x"&" → "&TEXT(_xlfn.XLOOKUP(2025,RatioYears,DE_Kroger),"0.00")&"x"&"; revenue "&TEXT(_xlfn.XLOOKUP(2024,RatioYears,GR_Kroger),"0.0%")&" and "&TEXT(_xlfn.XLOOKUP(2025,RatioYears,GR_Kroger),"0.0%")&" in FY2024–FY2025." -> • Kroger's reversal: five years of de-leveraging (FY2018–FY2023) undone in two. Debt-to-equity 1.05x → 2.96x; revenue -1.9% and 0.4% in FY2024–FY2025.
B29: ="• ASC 842 (FY2019; Costco FY2020) put operating leases on every balance sheet. Total debt in this model excludes them so FY2016–FY2018 remain comparable; the supplementary lease-inclusive ratio shows the effect." -> • ASC 842 (FY2019; Costco FY2020) put operating leases on every balance sheet. Total debt in this model excludes them so FY2016–FY2018 remain comparable; the supplementary lease-inclusive ratio shows the effect.
B31: Data caveats
B32: • Sam's Club is a reportable segment of Walmart (ASC 280), not a filer: net sales, operating income and total assets are available FY2016–FY2025; cost of revenue only from FY2022 (ASU 2023-07 comparatives); no net income, current ratio or debt is reported at segment level.
B33: • Whole Foods Market filed its last 10-K for FY2017 (acquired by Amazon.com 2017-08-28). FY2018 onward the only public figure is Amazon's 'Physical stores' net sales, which also includes Amazon Fresh and Amazon Go. Whole Foods' cost line included occupancy costs, so its ~34% gross margin is not like-for-like with peers.
B34: ="• Inventory method: Walmart (U.S.), Costco (U.S.) and Kroger (~91% of inventory) use LIFO; Whole Foods used LIFO; Costco Canada / Walmart International use FIFO. Kroger discloses its LIFO reserve – "&"$"&TEXT(Kroger_LifoReserve_FY2025/1000,"0.0")&"B"&" at FY2025 versus "&"$"&TEXT(Kroger_LifoReserve_FY2016/1000,"0.0")&"B"&_xlfn._LONGTEXT(" at FY2016 – so its reported inventory and cost of sales understate FIFO-basis values. Walmart disclosed that LIFO approximated FIFO through January 2022 and gives only sensitivity language since; Costco discloses no reserve but took a LIFO charge worth 1","9 bp of gross margin in FY2022. Gross margins are therefore compared as reported; a full FIFO restatement is outside this workbook's scope and is discussed on the Methodology tab.") -> • Inventory method: Walmart (U.S.), Costco (U.S.) and Kroger (~91% of inventory) use LIFO; Whole Foods used LIFO; Costco Canada / Walmart International use FIFO. Kroger discloses its LIFO reserve – $2.6B at FY2025 versus $1.3B at FY2016 – so its reported inventory and cost of sales understate FIFO-basis values. Walmart disclosed that LIFO approximated FIFO through January 2022 and gives only sensitivity language since; Costco discloses no reserve but took a LIFO charge worth 19 bp of gross margin in FY2022. Gross margins are therefore compared as reported; a full FIFO restatement is outside this workbook's scope and is discussed on the Methodology tab.
B35: ="• Total equity includes noncontrolling interests (Walmart: "&"$"&TEXT(Walmart_NoncontrollingInterestInTotal_FY2025/1000,"0.0")&"B"&" at FY2025) while net income is the amount attributable to the parent – the standard presentation, but it slightly lowers Walmart's debt-to-equity relative to a parent-only basis." -> • Total equity includes noncontrolling interests (Walmart: $6.3B at FY2025) while net income is the amount attributable to the parent – the standard presentation, but it slightly lowers Walmart's debt-to-equity relative to a parent-only basis.
B36: • 53-week fiscal years: Costco and Kroger FY2017 and FY2023 each contain 53 weeks (371 days), which flatters growth in those years and depresses it the year after by roughly 2 percentage points. Fiscal years are aligned by the SEC frame convention (calendar year holding most of the period), so Walmart's 'fiscal 2026' (ended January 2026) is FY2025 here.
B37: • Every input carries its XBRL tag, accession number and filing date on the Data Lineage tab; seven values the SEC API could not return were taken from the filing's XBRL instance or derived from two tagged facts and are shaded yellow on Raw Data.

Sheet Raw Data
A1: 03 — RAW DATA | N1: COMPETITOR SCORECARD · FY2016–FY2025 · SEC 10-K DATA
A2: Raw Data
A3: As reported in SEC 10-K filings. USD millions. Blue = hard-coded input from EDGAR XBRL (one citation per value on the Data Lineage tab); black = formula; 'n/a' = not reported – flagged, never estimated. Fiscal years labelled by SEC frame convention (FY2025 = Walmart fiscal 2026, Kroger 2025, Costco 2025).
A4: Line item | B4: XBRL tag(s) / basis | C4: 2015 | D4: 2016 | E4: 2017 | F4: 2018 | G4: 2019 | H4: 2020 | I4: 2021 | J4: 2022 | K4: 2023 | L4: 2024 | M4: 2025 | N4: Source / notes
A6: Walmart — Walmart Inc., CIK 104169
A7: Fiscal year end | B7: January 31 | C7: 42400 | D7: 42766 | E7: 43131 | F7: 43496 | G7: 43861 | H7: 44227 | I7: 44592 | J7: 44957 | K7: 45322 | L7: 45688 | M7: 46053
A8: Revenue (net sales) | B8: RevenueFromContractWithCustomerExcludingAssessedTax; SalesRevenueNet | C8: 478614 | D8: 481317 | E8: 495761 | F8: 510329 | G8: 519926 | H8: 555233 | I8: 567762 | J8: 605881 | K8: 642637 | L8: 674538 | M8: 706413 | N8: 10-K XBRL via SEC companyfacts API; latest-filed (restated) value.
A9: Cost of sales | B9: CostOfRevenue | C9: 360984 | D9: 361256 | E9: 373396 | F9: 385301 | G9: 394605 | H9: 420315 | I9: 429000 | J9: 463721 | K9: 490142 | L9: 511753 | M9: 535395 | N9: 10-K XBRL via SEC companyfacts API; latest-filed (restated) value.
A10: Net income | B10: NetIncomeLoss | C10: 14694 | D10: 13643 | E10: 9862 | F10: 6670 | G10: 14881 | H10: 13510 | I10: 13673 | J10: 11680 | K10: 15511 | L10: 19436 | M10: 21893 | N10: 10-K XBRL via SEC companyfacts API; latest-filed (restated) value. Attributable to the parent (NetIncomeLoss).
A11: Current assets | B11: AssetsCurrent | C11: 60239 | D11: 57689 | E11: 59664 | F11: 61897 | G11: 61806 | H11: 90067 | I11: 81070 | J11: 75655 | K11: 76877 | L11: 79458 | M11: 84874 | N11: 10-K XBRL via SEC companyfacts API; latest-filed (restated) value.
A12: Current liabilities | B12: LiabilitiesCurrent | C12: 64619 | D12: 66928 | E12: 78521 | F12: 77477 | G12: 77790 | H12: 92645 | I12: 87379 | J12: 92198 | K12: 92415 | L12: 96584 | M12: 107469 | N12: 10-K XBRL via SEC companyfacts API; latest-filed (restated) value.
A13: Total equity (incl. noncontrolling interest) | B13: StockholdersEquityIncludingPortionAttributableToNoncontrollingInterest | C13: 83611 | D13: 80535 | E13: 80822 | F13: 79634 | G13: 81552 | H13: 87531 | I13: 91891 | J13: 83754 | K13: 90349 | L13: 97421 | M13: 105887 | N13: 10-K XBRL via SEC companyfacts API; latest-filed (restated) value. Includes noncontrolling interest (Walmart FY2025: $6.3B).
A14: Total debt (formula – see debt build below) | B14: Policy: config/debt_policy.yaml (ASC 842) | C14: =SUM(C15,C16,C17)+IF(COUNT(C18,C19)>0,SUM(C18,C19),IF(ISNUMBER(C20),C20,0)) -> 50034 | D14: =SUM(D15,D16,D17)+IF(COUNT(D18,D19)>0,SUM(D18,D19),IF(ISNUMBER(D20),D20,0)) -> 45938 | E14: =SUM(E15,E16,E17)+IF(COUNT(E18,E19)>0,SUM(E18,E19),IF(ISNUMBER(E20),E20,0)) -> 46487 | F14: =SUM(F15,F16,F17)+IF(COUNT(F18,F19)>0,SUM(F18,F19),IF(ISNUMBER(F20),F20,0)) -> 58033 | G14: =SUM(G15,G16,G17)+IF(COUNT(G18,G19)>0,SUM(G18,G19),IF(ISNUMBER(G20),G20,0)) -> 54469 | H14: =SUM(H15,H16,H17)+IF(COUNT(H18,H19)>0,SUM(H18,H19),IF(ISNUMBER(H20),H20,0)) -> 48871 | I14: =SUM(I15,I16,I17)+IF(COUNT(I18,I19)>0,SUM(I18,I19),IF(ISNUMBER(I20),I20,0)) -> 42831 | J14: =SUM(J15,J16,J17)+IF(COUNT(J18,J19)>0,SUM(J18,J19),IF(ISNUMBER(J20),J20,0)) -> 44622 | ... M14: =SUM(M15,M16,M17)+IF(COUNT(M18,M19)>0,SUM(M18,M19),IF(ISNUMBER(M20),M20,0)) -> 51523 | N14: Walmart reports short-term borrowings, LTD due within one year, LTD, and finance (pre-2019: capital) lease obligations as separate balance-sheet lines.
A15: Short-term borrowings | B15: ShortTermBorrowings | C15: 2708 | D15: 1099 | E15: 5257 | F15: 5225 | G15: 575 | H15: 224 | I15: 410 | J15: 372 | K15: 878 | L15: 3068 | M15: 6596 | N15: Debt component.
A16: Long-term debt – due within one year | B16: LongTermDebtCurrent | C16: 2745 | D16: 2256 | E16: 3738 | F16: 1876 | G16: 5362 | H16: 3115 | I16: 2803 | J16: 4191 | K16: 3447 | L16: 2598 | M16: 3542 | N16: Debt component.
A17: Long-term debt – non-current | B17: LongTermDebtNoncurrent | C17: 38214 | D17: 36015 | E17: 30045 | F17: 43520 | G17: 43714 | H17: 41194 | I17: 34864 | J17: 34649 | K17: 36132 | L17: 33401 | M17: 34624 | N17: Debt component.
A18: Finance / capital lease liability – current | B18: CapitalLeaseObligationsCurrent; FinanceLeaseLiabilityCurrent | C18: 551 | D18: 565 | E18: 667 | F18: 729 | G18: 511 | H18: 491 | I18: 511 | J18: 567 | K18: 725 | L18: 800 | M18: 856 | N18: Debt component.
A19: Finance / capital lease liability – non-current | B19: CapitalLeaseObligationsNoncurrent; FinanceLeaseLiabilityNoncurrent | C19: 5816 | D19: 6003 | E19: 6780 | F19: 6683 | G19: 4307 | H19: 3847 | I19: 4243 | J19: 4843 | K19: 5709 | L19: 5923 | M19: 5905 | N19: Debt component.
A20: Finance lease liability – total (years not split on the balance sheet) | B20: CapitalLeaseObligations; FinanceLeaseLiability | C20: 6367 | D20: 6568 | E20: 7447 | F20: 7412 | G20: 4818 | H20: 4338 | I20: 4754 | J20: 5410 | K20: 6434 | L20: 6723 | M20: 6761 | N20: Debt component.
A21: Operating income (memo) | B21: OperatingIncomeLoss | C21: 24105 | D21: 22764 | E21: 20437 | F21: 21957 | G21: 20568 | H21: 22548 | I21: 25942 | J21: 20428 | K21: 27012 | L21: 29348 | M21: 29825 | N21: Memo item – not used in the five core ratios except where stated.
A22: Operating lease liability (ASC 842; excluded from Total debt) (memo) | B22: OperatingLeaseLiability; OperatingLeaseLiabilityNoncurrent | C22: n/a | D22: n/a | E22: n/a | F22: n/a | G22: 17964 | H22: 14375 | I22: 14492 | J22: 14301 | K22: 14430 | L22: 14324 | M22: 15572 | N22: Memo item – not used in the five core ratios except where stated.
A23: Total assets (memo) | B23: Assets | C23: 199581 | D23: 198825 | E23: 204522 | F23: 219295 | G23: 236495 | H23: 252496 | I23: 244860 | J23: 243197 | K23: 252399 | L23: 260823 | M23: 284668 | N23: Memo item – not used in the five core ratios except where stated.
A24: Inventory (memo) | B24: InventoryNet | C24: 44469 | D24: 43046 | E24: 43783 | F24: 44269 | G24: 44435 | H24: 44949 | I24: 56511 | J24: 56576 | K24: 54892 | L24: 56435 | M24: 58851 | N24: Memo item – not used in the five core ratios except where stated.
A26: Costco — Costco Wholesale Corporation, CIK 909832
A27: Fiscal year end | B27: Sunday nearest August 31 | C27: 42246 | D27: 42610 | E27: 42981 | F27: 43345 | G27: 43709 | H27: 44073 | I27: 44437 | J27: 44801 | K27: 45172 | L27: 45536 | M27: 45900
A28: Revenue (net sales) | B28: us-gaap:RevenueFromContractWithCustomerExcludingAssessedTax; us-gaap:SalesRevenueNet | C28: 113666 | D28: 116073 | E28: 126172 | F28: 138434 | G28: 149351 | H28: 163220 | I28: 192052 | J28: 222730 | K28: 237710 | L28: 249625 | M28: 269912 | N28: 10-K XBRL via SEC companyfacts API; latest-filed (restated) value. NET SALES (merchandise), excluding membership fees - ProductOrServiceAxis = ProductMember from FY2018 (parsed from the XBRL instance), SalesRevenueNet before ASC 606. Total revenue is shown as a memo row.
A29: Cost of sales | B29: CostOfGoodsAndServicesSold; CostOfGoodsSold | C29: 101065 | D29: 102901 | E29: 111882 | F29: 123152 | G29: 132886 | H29: 144939 | I29: 170684 | J29: 199382 | K29: 212586 | L29: 222358 | M29: 239886 | N29: 10-K XBRL via SEC companyfacts API; latest-filed (restated) value.
A30: Net income | B30: NetIncomeLoss | C30: 2377 | D30: 2350 | E30: 2679 | F30: 3134 | G30: 3659 | H30: 4002 | I30: 5007 | J30: 5844 | K30: 6292 | L30: 7367 | M30: 8099 | N30: 10-K XBRL via SEC companyfacts API; latest-filed (restated) value. Attributable to the parent (NetIncomeLoss).
A31: Current assets | B31: AssetsCurrent | C31: 16779 | D31: 15218 | E31: 17317 | F31: 20289 | G31: 23485 | H31: 28120 | I31: 29505 | J31: 32696 | K31: 35879 | L31: 34246 | M31: 38380 | N31: 10-K XBRL via SEC companyfacts API; latest-filed (restated) value.
A32: Current liabilities | B32: LiabilitiesCurrent | C32: 16539 | D32: 15575 | E32: 17495 | F32: 19926 | G32: 23237 | H32: 24844 | I32: 29441 | J32: 31998 | K32: 33583 | L32: 35464 | M32: 37108 | N32: 10-K XBRL via SEC companyfacts API; latest-filed (restated) value.
A33: Total equity (incl. noncontrolling interest) | B33: StockholdersEquityIncludingPortionAttributableToNoncontrollingInterest | C33: 10843 | D33: 12332 | E33: 11079 | F33: 13103 | G33: 15584 | H33: 18705 | I33: 18078 | J33: 20647 | K33: 25058 | L33: 23622 | M33: 29164 | N33: 10-K XBRL via SEC companyfacts API; latest-filed (restated) value.
A34: Total debt (formula – see debt build below) | B34: Policy: config/debt_policy.yaml (ASC 842) | C34: =SUM(C35,C36)+IF(COUNT(C37,C38)>0,SUM(C37,C38),IF(ISNUMBER(C39),C39,0)) -> 6431 | D34: =SUM(D35,D36)+IF(COUNT(D37,D38)>0,SUM(D37,D38),IF(ISNUMBER(D39),D39,0)) -> 5535 | E34: =SUM(E35,E36)+IF(COUNT(E37,E38)>0,SUM(E37,E38),IF(ISNUMBER(E39),E39,0)) -> 7039 | F34: =SUM(F35,F36)+IF(COUNT(F37,F38)>0,SUM(F37,F38),IF(ISNUMBER(F39),F39,0)) -> 6974 | G34: =SUM(G35,G36)+IF(COUNT(G37,G38)>0,SUM(G37,G38),IF(ISNUMBER(G39),G39,0)) -> 7244 | H34: =SUM(H35,H36)+IF(COUNT(H37,H38)>0,SUM(H37,H38),IF(ISNUMBER(H39),H39,0)) -> 8297 | I34: =SUM(I35,I36)+IF(COUNT(I37,I38)>0,SUM(I37,I38),IF(ISNUMBER(I39),I39,0)) -> 8543 | J34: =SUM(J35,J36)+IF(COUNT(J37,J38)>0,SUM(J37,J38),IF(ISNUMBER(J39),J39,0)) -> 8185 | ... M34: =SUM(M35,M36)+IF(COUNT(M37,M38)>0,SUM(M37,M38),IF(ISNUMBER(M39),M39,0)) -> 7267 | N34: Costco has no short-term borrowings line. Finance leases sit inside 'other current' / 'other long-term liabilities' and are disclosed in the Leases note. finance_lease_total is used only in years where current/non-current are not separately tagged (FY2021-FY2023); the workbook formula takes current+non-current if present, else total.
A35: Long-term debt – due within one year | B35: LongTermDebtCurrent | C35: 1283 | D35: 1100 | E35: 86 | F35: 90 | G35: 1699 | H35: 95 | I35: 799 | J35: 73 | K35: 1081 | L35: 103 | M35: 75 | N35: Debt component.
A36: Long-term debt – non-current | B36: LongTermDebtNoncurrent | C36: 4852 | D36: 4061 | E36: 6573 | F36: 6487 | G36: 5124 | H36: 7514 | I36: 6692 | J36: 6484 | K36: 5377 | L36: 5794 | M36: 5713 | N36: Debt component.
A37: Finance / capital lease liability – current | B37: CapitalLeaseObligationsCurrent; FinanceLeaseLiabilityCurrent | C37: 10 | D37: 10 | E37: 7 | F37: 7 | G37: 26 | H37: 31 | I37: n/a | J37: n/a | K37: n/a | L37: 147 | M37: 78 | N37: Debt component. FY2019: instance – Tagged in the FY2019 10-K XBRL instance (cost-20190901.xml, context FI2019Q4) but absent from the companyfacts API; ASC 840 capital lease, pre-842 adoption.
A38: Finance / capital lease liability – non-current | B38: CapitalLeaseObligationsNoncurrent; FinanceLeaseLiabilityNoncurrent | C38: 286 | D38: 364 | E38: 373 | F38: 390 | G38: 395 | H38: 657 | I38: n/a | J38: n/a | K38: n/a | L38: 1351 | M38: 1401 | N38: Debt component. FY2019: instance – Tagged in the FY2019 10-K XBRL instance (cost-20190901.xml, context FI2019Q4) but absent from the companyfacts API; ties to CapitalLeasesFutureMinimumPaymentsPresentValueOfNetMinimumPayments 421M.
A39: Finance lease liability – total (years not split on the balance sheet) | B39: FinanceLeaseLiability; FinanceLeaseLiabilityPaymentsDue - FinanceLeaseLiabilityUndiscountedExcessAmount | C39: n/a | D39: n/a | E39: n/a | F39: n/a | G39: n/a | H39: 688 | I39: 1052 | J39: 1628 | K39: 1432 | L39: n/a | M39: 1479 | N39: Debt component. FY2022: derived – Finance lease liability not tagged as a balance; derived as undiscounted payments less imputed interest (both us-gaap tagged, Leases note). Costco carries finance leases inside other current / other long-term liabilities. FY2023: derived – Same derivation as FY2022; ties to cost:OperatingLeaseandFinanceLeaseLiabilities 4078M less OperatingLeaseLiability 2646M = 1432M in the same filing.
A40: Operating income (memo) | B40: OperatingIncomeLoss | C40: 3624 | D40: 3672 | E40: 4111 | F40: 4480 | G40: 4737 | H40: 5435 | I40: 6708 | J40: 7793 | K40: 8114 | L40: 9285 | M40: 10383 | N40: Memo item – not used in the five core ratios except where stated.
A41: Operating lease liability (ASC 842; excluded from Total debt) (memo) | B41: OperatingLeaseLiability; OperatingLeaseLiabilityNoncurrent | C41: n/a | D41: n/a | E41: n/a | F41: n/a | G41: n/a | H41: 2789 | I41: 2864 | J41: 2721 | K41: 2646 | L41: 2554 | M41: 2668 | N41: Memo item – not used in the five core ratios except where stated.
A42: Total assets (memo) | B42: Assets | C42: 33017 | D42: 33163 | E42: 36347 | F42: 40830 | G42: 45400 | H42: 55556 | I42: 59268 | J42: 64166 | K42: 68994 | L42: 69831 | M42: 77099 | N42: Memo item – not used in the five core ratios except where stated.
A43: Inventory (memo) | B43: InventoryNet | C43: 8908 | D43: 8969 | E43: 9834 | F43: 11040 | G43: 11395 | H43: 12242 | I43: 14215 | J43: 17907 | K43: 16651 | L43: 18647 | M43: 18116 | N43: Memo item – not used in the five core ratios except where stated.
A44: LIFO reserve (where disclosed) (memo) | B44: InventoryLIFOReserve | C44: 82 | D44: n/a | E44: 0 | F44: n/a | G44: n/a | H44: n/a | I44: n/a | J44: n/a | K44: n/a | L44: n/a | M44: n/a | N44: Memo item – not used in the five core ratios except where stated.
A45: Total revenue incl. membership fees (memo) | B45: RevenueFromContractWithCustomerExcludingAssessedTax; Revenues | C45: 116199 | D45: 118719 | E45: 129025 | F45: 141576 | G45: 152703 | H45: 166761 | I45: 195929 | J45: 226954 | K45: 242290 | L45: 254453 | M45: 275235 | N45: Costco's income-statement total ('Total revenue'). Net sales above exclude membership fees so the revenue basis matches Walmart and Sam's Club.
A46: Membership fee revenue = total revenue - net sales (memo, formula) | B46: Formula | C46: =IFERROR(C45-C28,"n/a") -> 2533 | D46: =IFERROR(D45-D28,"n/a") -> 2646 | E46: =IFERROR(E45-E28,"n/a") -> 2853 | F46: =IFERROR(F45-F28,"n/a") -> 3142 | G46: =IFERROR(G45-G28,"n/a") -> 3352 | H46: =IFERROR(H45-H28,"n/a") -> 3541 | I46: =IFERROR(I45-I28,"n/a") -> 3877 | J46: =IFERROR(J45-J28,"n/a") -> 4224 | ... M46: =IFERROR(M45-M28,"n/a") -> 5323 | N46: Ties to the MembershipMember disaggregated-revenue fact (FY2025: $5,323M, see Supporting facts). Carries no cost of sales; falls straight to operating income.
A48: Kroger — The Kroger Co., CIK 56873
A49: Fiscal year end | B49: Saturday nearest January 31 | C49: 42399 | D49: 42763 | E49: 43134 | F49: 43498 | G49: 43862 | H49: 44226 | I49: 44590 | J49: 44954 | K49: 45325 | L49: 45689 | M49: 46053
A50: Revenue (net sales) | B50: RevenueFromContractWithCustomerExcludingAssessedTax; SalesRevenueGoodsNet | C50: 109830 | D50: 115337 | E50: 123280 | F50: 121852 | G50: 122286 | H50: 132498 | I50: 137888 | J50: 148258 | K50: 150039 | L50: 147123 | M50: 147642 | N50: 10-K XBRL via SEC companyfacts API; latest-filed (restated) value.
A51: Cost of sales | B51: CostOfGoodsAndServiceExcludingDepreciationDepletionAndAmortization; CostOfGoodsSold; CostOfGoodsSoldExcludingDepreciationDepletionAndAmortization | C51: 85496 | D51: 89502 | E51: 95811 | F51: 95103 | G51: 95294 | H51: 101597 | I51: 107539 | J51: 116480 | K51: 116675 | L51: 113720 | M51: 113240 | N51: 10-K XBRL via SEC companyfacts API; latest-filed (restated) value.
A52: Net income | B52: NetIncomeLoss | C52: 2039 | D52: 1975 | E52: 1907 | F52: 3110 | G52: 1659 | H52: 2585 | I52: 1655 | J52: 2244 | K52: 2164 | L52: 2665 | M52: 1016 | N52: 10-K XBRL via SEC companyfacts API; latest-filed (restated) value. Attributable to the parent (NetIncomeLoss).
A53: Current assets | B53: AssetsCurrent | C53: 9892 | D53: 10340 | E53: 11117 | F53: 10803 | G53: 10890 | H53: 12503 | I53: 12174 | J53: 12670 | K53: 12948 | L53: 15273 | M53: 14505 | N53: 10-K XBRL via SEC companyfacts API; latest-filed (restated) value.
A54: Current liabilities | B54: LiabilitiesCurrent | C54: 12971 | D54: 12860 | E54: 14197 | F54: 14274 | G54: 14243 | H54: 15366 | I54: 16323 | J54: 17238 | K54: 16058 | L54: 15940 | M54: 18108 | N54: 10-K XBRL via SEC companyfacts API; latest-filed (restated) value.
A55: Total equity (incl. noncontrolling interest) | B55: StockholdersEquityIncludingPortionAttributableToNoncontrollingInterest | C55: 6798 | D55: 6710 | E55: 6905 | F55: 7835 | G55: 8573 | H55: 9550 | I55: 9429 | J55: 10014 | K55: 11601 | L55: 8281 | M55: 5936 | N55: 10-K XBRL via SEC companyfacts API; latest-filed (restated) value.
A56: Total debt (formula – see debt build below) | B56: Policy: config/debt_policy.yaml (ASC 842) | C56: =IF(ISNUMBER(C62),SUM(C62,C63),SUM(C57,C58)+IF(COUNT(C59,C60)>0,SUM(C59,C60),IF(ISNUMBER(C61),C61,0))) -> 12079 | D56: =IF(ISNUMBER(D62),SUM(D62,D63),SUM(D57,D58)+IF(COUNT(D59,D60)>0,SUM(D59,D60),IF(ISNUMBER(D61),D61,0))) -> 14077 | E56: =IF(ISNUMBER(E62),SUM(E62,E63),SUM(E57,E58)+IF(COUNT(E59,E60)>0,SUM(E59,E60),IF(ISNUMBER(E61),E61,0))) -> 15589 | F56: =IF(ISNUMBER(F62),SUM(F62,F63),SUM(F57,F58)+IF(COUNT(F59,F60)>0,SUM(F59,F60),IF(ISNUMBER(F61),F61,0))) -> 15229 | G56: =IF(ISNUMBER(G62),SUM(G62,G63),SUM(G57,G58)+IF(COUNT(G59,G60)>0,SUM(G59,G60),IF(ISNUMBER(G61),G61,0))) -> 14076 | H56: =IF(ISNUMBER(H62),SUM(H62,H63),SUM(H57,H58)+IF(COUNT(H59,H60)>0,SUM(H59,H60),IF(ISNUMBER(H61),H61,0))) -> 13413 | I56: =IF(ISNUMBER(I62),SUM(I62,I63),SUM(I57,I58)+IF(COUNT(I59,I60)>0,SUM(I59,I60),IF(ISNUMBER(I61),I61,0))) -> 13364 | J56: =IF(ISNUMBER(J62),SUM(J62,J63),SUM(J57,J58)+IF(COUNT(J59,J60)>0,SUM(J59,J60),IF(ISNUMBER(J61),J61,0))) -> 13378 | ... M56: =IF(ISNUMBER(M62),SUM(M62,M63),SUM(M57,M58)+IF(COUNT(M59,M60)>0,SUM(M59,M60),IF(ISNUMBER(M61),M61,0))) -> 17566 | N56: Kroger has no short-term borrowings line; commercial paper is inside current LTD. FY2016-FY2018: the combined 'long-term debt including obligations under capital leases' lines are used (they tie to LTD + capital leases exactly). FY2019+: LTD lines plus finance lease lines.
A57: Long-term debt – due within one year | B57: LongTermDebtCurrent | C57: 2318 | D57: 2197 | E57: 3509 | F57: 3103 | G57: 1926 | H57: 844 | I57: 451 | J57: 1153 | K57: 25 | L57: 104 | M57: 1366 | N57: Debt component.
A58: Long-term debt – non-current | B58: LongTermDebtNoncurrent | C58: 9078 | D58: 11118 | E58: 11278 | F58: 11248 | G58: 11330 | H58: 11566 | I58: 11294 | J58: 10139 | K58: 10162 | L58: 15805 | M58: 14509 | N58: Debt component.
A59: Finance / capital lease liability – current | B59: FinanceLeaseLiabilityCurrent | C59: n/a | D59: n/a | E59: n/a | F59: 54 | G59: 39 | H59: 67 | I59: 104 | J59: 157 | K59: 173 | L59: 168 | M59: 436 | N59: Debt component.
A60: Finance / capital lease liability – non-current | B60: FinanceLeaseLiabilityNoncurrent | C60: n/a | D60: n/a | E60: n/a | F60: 824 | G60: 781 | H60: 936 | I60: 1515 | J60: 1929 | K60: 1866 | L60: 1828 | M60: 1255 | N60: Debt component.
A61: Finance lease liability – total (years not split on the balance sheet) | B61: FinanceLeaseLiability | C61: n/a | D61: n/a | E61: n/a | F61: n/a | G61: 820 | H61: 1003 | I61: 1619 | J61: 2086 | K61: 2039 | L61: 1996 | M61: 1691 | N61: Debt component.
A62: Long-term debt incl. finance leases – current (combined line) | B62: LongTermDebtAndCapitalLeaseObligationsCurrent | C62: 2370 | D62: 2252 | E62: 3560 | F62: 3157 | G62: n/a | H62: n/a | I62: n/a | J62: n/a | K62: n/a | L62: n/a | M62: n/a | N62: Debt component.
A63: Long-term debt incl. finance leases – non-current (combined line) | B63: LongTermDebtAndCapitalLeaseObligations | C63: 9709 | D63: 11825 | E63: 12029 | F63: 12072 | G63: n/a | H63: n/a | I63: n/a | J63: n/a | K63: n/a | L63: n/a | M63: n/a | N63: Debt component.
A64: Operating income (memo) | B64: OperatingIncomeLoss | C64: 3576 | D64: 3452 | E64: 2612 | F64: 2614 | G64: 2251 | H64: 2780 | I64: 3477 | J64: 4126 | K64: 3096 | L64: 3849 | M64: 1890 | N64: Memo item – not used in the five core ratios except where stated.
A65: Operating lease liability (ASC 842; excluded from Total debt) (memo) | B65: OperatingLeaseLiability | C65: n/a | D65: n/a | E65: n/a | F65: n/a | G65: 7102 | H65: 7174 | I65: 7076 | J65: 7034 | K65: 7021 | L65: 7177 | M65: 7126 | N65: Memo item – not used in the five core ratios except where stated.
A66: Total assets (memo) | B66: Assets | C66: 33897 | D66: 36505 | E66: 37197 | F66: 38118 | G66: 45256 | H66: 48662 | I66: 49086 | J66: 49623 | K66: 50505 | L66: 52616 | M66: 49953 | N66: Memo item – not used in the five core ratios except where stated.
A67: LIFO reserve (where disclosed) (memo) | B67: InventoryLIFOReserve | C67: 1272 | D67: 1291 | E67: 1248 | F67: 1277 | G67: 1380 | H67: 1373 | I67: 1570 | J67: 2196 | K67: 2309 | L67: 2404 | M67: 2553 | N67: Memo item – not used in the five core ratios except where stated.
A69: Sam's Club — Walmart reportable segment (ASC 280); no balance sheet or net income at segment level
A70: Fiscal year end | B70: per Walmart | C70: 42400 | D70: 42766 | E70: 43131 | F70: 43496 | G70: 43861 | H70: 44227 | I70: 44592 | J70: 44957 | K70: 45322 | L70: 45688 | M70: 46053
A71: Revenue (net sales) | B71: us-gaap:RevenueFromContractWithCustomerExcludingAssessedTax; us-gaap:SalesRevenueNet | C71: 56828 | D71: 57365 | E71: 59216 | F71: 57839 | G71: 58792 | H71: 63910 | I71: 73556 | J71: 84345 | K71: 86179 | L71: 90238 | M71: 93015 | N71: Walmart 10-K segment note (ASC 280), StatementBusinessSegmentsAxis = SamsClubUSMember; parsed from the XBRL instance.
A72: Cost of sales | B72: us-gaap:CostOfRevenue | C72: n/a | D72: n/a | E72: n/a | F72: n/a | G72: n/a | H72: n/a | I72: n/a | J72: 75584 | K72: 76748 | L72: 80035 | M72: 82459 | N72: Walmart 10-K segment note (ASC 280), StatementBusinessSegmentsAxis = SamsClubUSMember; parsed from the XBRL instance. Segment cost of revenue first disclosed in the FY2024 10-K under ASU 2023-07 (three comparative years).
A73: Net income | B73: — | C73: n/a | D73: n/a | E73: n/a | F73: n/a | G73: n/a | H73: n/a | I73: n/a | J73: n/a | K73: n/a | L73: n/a | M73: n/a | N73: Walmart 10-K segment note (ASC 280), StatementBusinessSegmentsAxis = SamsClubUSMember; parsed from the XBRL instance. Not reported at segment level under ASC 280.Attributable to the parent (NetIncomeLoss).
A74: Current assets | B74: — | C74: n/a | D74: n/a | E74: n/a | F74: n/a | G74: n/a | H74: n/a | I74: n/a | J74: n/a | K74: n/a | L74: n/a | M74: n/a | N74: Walmart 10-K segment note (ASC 280), StatementBusinessSegmentsAxis = SamsClubUSMember; parsed from the XBRL instance. Not reported at segment level under ASC 280.
A75: Current liabilities | B75: — | C75: n/a | D75: n/a | E75: n/a | F75: n/a | G75: n/a | H75: n/a | I75: n/a | J75: n/a | K75: n/a | L75: n/a | M75: n/a | N75: Walmart 10-K segment note (ASC 280), StatementBusinessSegmentsAxis = SamsClubUSMember; parsed from the XBRL instance. Not reported at segment level under ASC 280.
A76: Total equity (incl. noncontrolling interest) | B76: — | C76: n/a | D76: n/a | E76: n/a | F76: n/a | G76: n/a | H76: n/a | I76: n/a | J76: n/a | K76: n/a | L76: n/a | M76: n/a | N76: Walmart 10-K segment note (ASC 280), StatementBusinessSegmentsAxis = SamsClubUSMember; parsed from the XBRL instance. Not reported at segment level under ASC 280.
A77: Total debt (formula – see debt build below) | B77: Policy: config/debt_policy.yaml (ASC 842) | C77: n/a | D77: n/a | E77: n/a | F77: n/a | G77: n/a | H77: n/a | I77: n/a | J77: n/a | K77: n/a | L77: n/a | M77: n/a | N77: Segment (ASC 280) - no balance sheet is reported for Sam's Club; debt ratios not computable.
A78: Operating income (memo) | B78: us-gaap:OperatingIncomeLoss | C78: 1820 | D78: 1628 | E78: 915 | F78: 1520 | G78: 1642 | H78: 1906 | I78: 2259 | J78: 1964 | K78: 2192 | L78: 2404 | M78: 2442 | N78: Memo item – not used in the five core ratios except where stated.
A79: Total assets (memo) | B79: us-gaap:Assets | C79: 13998 | D79: 14125 | E79: 13418 | F79: 12893 | G79: 13494 | H79: 13415 | I79: 14678 | J79: 15490 | K79: 15682 | L79: 16862 | M79: 17186 | N79: Memo item – not used in the five core ratios except where stated.
A81: Whole Foods — standalone 10-Ks through FY2017; acquired by Amazon.com 2017-08-28
A82: Fiscal year end | B82: Last Sunday in September | C82: 42274 | D82: 42638 | E82: 43002
A83: Revenue (net sales) | B83: SalesRevenueNet | C83: 15389 | D83: 15724 | E83: 16030 | F83: n/a | G83: n/a | H83: n/a | I83: n/a | J83: n/a | K83: n/a | L83: n/a | M83: n/a | N83: Whole Foods 10-K XBRL (CIK 865436). No filings after FY2017.
A84: Cost of sales | B84: SalesRevenueNet - GrossProfit | C84: 9973 | D84: 10313 | E84: 10633 | F84: n/a | G84: n/a | H84: n/a | I84: n/a | J84: n/a | K84: n/a | L84: n/a | M84: n/a | N84: Whole Foods 10-K XBRL (CIK 865436). No filings after FY2017. Whole Foods' line is 'Cost of goods sold and occupancy costs' – includes rent; gross margin not directly comparable. FY2015: derived – COGS = 15,389 - 5,416 = 9,973. Includes occupancy costs (see Methodology). Base year only. FY2016: derived – Whole Foods tagged Sales and Gross Profit but not its 'Cost of goods sold and occupancy costs' line; COGS = 15,724 - 5,411 = 10,313. Includes occupancy costs (see Methodology). FY2017: derived – COGS = 16,030 - 5,397 = 10,633. NOTE: Whole Foods' cost line includes occupancy costs, which depresses gross margin vs peers; flagged on Methodology tab.
A85: Net income | B85: NetIncomeLoss | C85: 536 | D85: 507 | E85: 245 | F85: n/a | G85: n/a | H85: n/a | I85: n/a | J85: n/a | K85: n/a | L85: n/a | M85: n/a | N85: Whole Foods 10-K XBRL (CIK 865436). No filings after FY2017. Attributable to the parent (NetIncomeLoss).
A86: Current assets | B86: AssetsCurrent | C86: 1544 | D86: 1975 | E86: 2145 | F86: n/a | G86: n/a | H86: n/a | I86: n/a | J86: n/a | K86: n/a | L86: n/a | M86: n/a | N86: Whole Foods 10-K XBRL (CIK 865436). No filings after FY2017.
A87: Current liabilities | B87: LiabilitiesCurrent | C87: 1252 | D87: 1341 | E87: 1355 | F87: n/a | G87: n/a | H87: n/a | I87: n/a | J87: n/a | K87: n/a | L87: n/a | M87: n/a | N87: Whole Foods 10-K XBRL (CIK 865436). No filings after FY2017.
A88: Total equity (incl. noncontrolling interest) | B88: StockholdersEquity | C88: 3769 | D88: 3224 | E88: 3430 | F88: n/a | G88: n/a | H88: n/a | I88: n/a | J88: n/a | K88: n/a | L88: n/a | M88: n/a | N88: Whole Foods 10-K XBRL (CIK 865436). No filings after FY2017.
A89: Total debt (formula – see debt build below) | B89: Policy: config/debt_policy.yaml (ASC 842) | C89: =IF(ISNUMBER(C93),SUM(C93,C94),0+IF(COUNT(C90,C91)>0,SUM(C90,C91),IF(ISNUMBER(C92),C92,0))) -> 65 | D89: =IF(ISNUMBER(D93),SUM(D93,D94),0+IF(COUNT(D90,D91)>0,SUM(D90,D91),IF(ISNUMBER(D92),D92,0))) -> 1051 | E89: =IF(ISNUMBER(E93),SUM(E93,E94),0+IF(COUNT(E90,E91)>0,SUM(E90,E91),IF(ISNUMBER(E92),E92,0))) -> 1083 | F89: n/a | G89: n/a | H89: n/a | I89: n/a | J89: n/a | K89: n/a | L89: n/a | M89: n/a | N89: Whole Foods reported 'long-term debt and capital lease obligations' as combined lines; FY2016-FY2017 only.
A90: Finance / capital lease liability – current | B90: CapitalLeaseObligationsCurrent | C90: 3 | D90: 3 | E90: n/a | F90: n/a | G90: n/a | H90: n/a | I90: n/a | J90: n/a | K90: n/a | L90: n/a | M90: n/a | N90: Debt component.
A91: Finance / capital lease liability – non-current | B91: CapitalLeaseObligationsNoncurrent | C91: 62 | D91: 1048 | E91: n/a | F91: n/a | G91: n/a | H91: n/a | I91: n/a | J91: n/a | K91: n/a | L91: n/a | M91: n/a | N91: Debt component.
A92: Finance lease liability – total (years not split on the balance sheet) | B92: CapitalLeaseObligations | C92: 65 | D92: 58 | E92: 90 | F92: n/a | G92: n/a | H92: n/a | I92: n/a | J92: n/a | K92: n/a | L92: n/a | M92: n/a | N92: Debt component.
A93: Long-term debt incl. finance leases – current (combined line) | B93: LongTermDebtAndCapitalLeaseObligationsCurrent | C93: 3 | D93: 3 | E93: 2 | F93: n/a | G93: n/a | H93: n/a | I93: n/a | J93: n/a | K93: n/a | L93: n/a | M93: n/a | N93: Debt component.
A94: Long-term debt incl. finance leases – non-current (combined line) | B94: LongTermDebtAndCapitalLeaseObligations | C94: 62 | D94: 1048 | E94: 1081 | F94: n/a | G94: n/a | H94: n/a | I94: n/a | J94: n/a | K94: n/a | L94: n/a | M94: n/a | N94: Debt component.
A95: Operating income (memo) | B95: OperatingIncomeLoss | C95: 861 | D95: 857 | E95: 459 | F95: n/a | G95: n/a | H95: n/a | I95: n/a | J95: n/a | K95: n/a | L95: n/a | M95: n/a | N95: Memo item – not used in the five core ratios except where stated.
A96: Total assets (memo) | B96: Assets | C96: 5741 | D96: 6341 | E96: 6676 | F96: n/a | G96: n/a | H96: n/a | I96: n/a | J96: n/a | K96: n/a | L96: n/a | M96: n/a | N96: Memo item – not used in the five core ratios except where stated.
A97: Inventory (memo) | B97: InventoryNet | C97: 500 | D97: 517 | E97: 471 | F97: n/a | G97: n/a | H97: n/a | I97: n/a | J97: n/a | K97: n/a | L97: n/a | M97: n/a | N97: Memo item – not used in the five core ratios except where stated.
A98: LIFO reserve (where disclosed) (memo) | B98: InventoryLIFOReserve | C98: 49 | D98: 42 | E98: 47 | F98: n/a | G98: n/a | H98: n/a | I98: n/a | J98: n/a | K98: n/a | L98: n/a | M98: n/a | N98: Memo item – not used in the five core ratios except where stated.
A99: Successor: Amazon.com 'Physical stores' net sales (memo) | B99: RevenueFromContractWithCustomerExcludingAssessedTax [ProductOrServiceAxis = PhysicalStoresMember] | C99: n/a | D99: n/a | E99: n/a | F99: 17224 | G99: 17192 | H99: 16227 | I99: 17075 | J99: 18963 | K99: 20030 | L99: 21215 | M99: 22561 | N99: Amazon 10-K, Note – Segment Information / disaggregated revenue (ASC 606). Mostly Whole Foods Market; also Amazon Fresh and Amazon Go. Revenue only – no cost or balance-sheet data exists for Whole Foods after FY2017.
A101: Supporting facts cited in the Executive Summary (USD millions unless stated)
A102: Fact | B102: XBRL tag | C102: Fiscal year | D102: Value | E102: Accession no. | F102: Filed
A103: Kroger – Proceeds from issuance of long-term debt | B103: ProceedsFromIssuanceOfLongTermDebt | C103: 2024 | D103: 10502 | E103: 0001104659-26-037723 | F103: 2026-03-31
A104: Kroger – Share repurchases | B104: PaymentsForRepurchaseOfCommonStock | C104: 2024 | D104: 4156 | E104: 0001104659-26-037723 | F104: 2026-03-31
A105: Kroger – Share repurchases | B105: PaymentsForRepurchaseOfCommonStock | C105: 2025 | D105: 2699 | E105: 0001104659-26-037723 | F105: 2026-03-31
A106: Kroger – Restructuring and asset impairment charges | B106: RestructuringCostsAndAssetImpairmentCharges | C106: 2025 | D106: 2684 | E106: 0001104659-26-037723 | F106: 2026-03-31
...

Sheet Ratio Calculations
A1: 04 — RATIO CALCULATIONS | M1: COMPETITOR SCORECARD · FY2016–FY2025 · SEC 10-K DATA
A2: Ratio Calculations
A3: Live formulas over named ranges: every cell is =IFERROR( … XLOOKUP(year, Years, Company_Metric) … , "n/a"). Nothing is typed in. Δ columns are percentage-point (margins, growth) or turns (ratios) changes.
A4: Company | B4: 2016 | C4: 2017 | D4: 2018 | E4: 2019 | F4: 2020 | G4: 2021 | H4: 2022 | I4: 2023 | J4: 2024 | K4: 2025 | L4: Δ FY16→FY25 | M4: Δ FY19→FY23 | N4: Formula (FY2025 cell shown)
A6: Gross profit margin — (Revenue − Cost of sales) / Revenue
A7: Walmart | B7: =IFERROR((_xlfn.XLOOKUP(B$4,Years,Walmart_Revenue)-_xlfn.XLOOKUP(B$4,Years,Walmart_COGS))/_xlfn.XLOOKUP(B$4,Years,Walmart_Revenue),"n/a") -> 0.24944267 | C7: =IFERROR((_xlfn.XLOOKUP(C$4,Years,Walmart_Revenue)-_xlfn.XLOOKUP(C$4,Years,Walmart_COGS))/_xlfn.XLOOKUP(C$4,Years,Walmart_Revenue),"n/a") -> 0.24682256 | D7: =IFERROR((_xlfn.XLOOKUP(D$4,Years,Walmart_Revenue)-_xlfn.XLOOKUP(D$4,Years,Walmart_COGS))/_xlfn.XLOOKUP(D$4,Years,Walmart_Revenue),"n/a") -> 0.2449949 | E7: =IFERROR((_xlfn.XLOOKUP(E$4,Years,Walmart_Revenue)-_xlfn.XLOOKUP(E$4,Years,Walmart_COGS))/_xlfn.XLOOKUP(E$4,Years,Walmart_Revenue),"n/a") -> 0.24103622 | F7: =IFERROR((_xlfn.XLOOKUP(F$4,Years,Walmart_Revenue)-_xlfn.XLOOKUP(F$4,Years,Walmart_COGS))/_xlfn.XLOOKUP(F$4,Years,Walmart_Revenue),"n/a") -> 0.24299348 | G7: =IFERROR((_xlfn.XLOOKUP(G$4,Years,Walmart_Revenue)-_xlfn.XLOOKUP(G$4,Years,Walmart_COGS))/_xlfn.XLOOKUP(G$4,Years,Walmart_Revenue),"n/a") -> 0.2444017 | H7: =IFERROR((_xlfn.XLOOKUP(H$4,Years,Walmart_Revenue)-_xlfn.XLOOKUP(H$4,Years,Walmart_COGS))/_xlfn.XLOOKUP(H$4,Years,Walmart_Revenue),"n/a") -> 0.23463353 | I7: =IFERROR((_xlfn.XLOOKUP(I$4,Years,Walmart_Revenue)-_xlfn.XLOOKUP(I$4,Years,Walmart_COGS))/_xlfn.XLOOKUP(I$4,Years,Walmart_Revenue),"n/a") -> 0.23729571 | ... K7: =IFERROR((_xlfn.XLOOKUP(K$4,Years,Walmart_Revenue)-_xlfn.XLOOKUP(K$4,Years,Walmart_COGS))/_xlfn.XLOOKUP(K$4,Years,Walmart_Revenue),"n/a") -> 0.24209351 | L7: =IFERROR(K7-B7,"n/a") -> -0.0073491688 | M7: =IFERROR(I7-E7,"n/a") -> -0.0037405193 | N7: =IFERROR((_xludf.XLOOKUP(K$4,Years,Walmart_Revenue)-_xludf.XLOOKUP(K$4,Years,Walmart_COGS))/_xludf.XLOOKUP(K$4,Years,Walmart_Revenue),"n/a") -> n/a
A8: Costco | B8: =IFERROR((_xlfn.XLOOKUP(B$4,Years,Costco_Revenue)-_xlfn.XLOOKUP(B$4,Years,Costco_COGS))/_xlfn.XLOOKUP(B$4,Years,Costco_Revenue),"n/a") -> 0.11348031 | C8: =IFERROR((_xlfn.XLOOKUP(C$4,Years,Costco_Revenue)-_xlfn.XLOOKUP(C$4,Years,Costco_COGS))/_xlfn.XLOOKUP(C$4,Years,Costco_Revenue),"n/a") -> 0.11325809 | D8: =IFERROR((_xlfn.XLOOKUP(D$4,Years,Costco_Revenue)-_xlfn.XLOOKUP(D$4,Years,Costco_COGS))/_xlfn.XLOOKUP(D$4,Years,Costco_Revenue),"n/a") -> 0.11039196 | E8: =IFERROR((_xlfn.XLOOKUP(E$4,Years,Costco_Revenue)-_xlfn.XLOOKUP(E$4,Years,Costco_COGS))/_xlfn.XLOOKUP(E$4,Years,Costco_Revenue),"n/a") -> 0.11024365 | F8: =IFERROR((_xlfn.XLOOKUP(F$4,Years,Costco_Revenue)-_xlfn.XLOOKUP(F$4,Years,Costco_COGS))/_xlfn.XLOOKUP(F$4,Years,Costco_Revenue),"n/a") -> 0.11200221 | G8: =IFERROR((_xlfn.XLOOKUP(G$4,Years,Costco_Revenue)-_xlfn.XLOOKUP(G$4,Years,Costco_COGS))/_xlfn.XLOOKUP(G$4,Years,Costco_Revenue),"n/a") -> 0.11126153 | H8: =IFERROR((_xlfn.XLOOKUP(H$4,Years,Costco_Revenue)-_xlfn.XLOOKUP(H$4,Years,Costco_COGS))/_xlfn.XLOOKUP(H$4,Years,Costco_Revenue),"n/a") -> 0.10482647 | I8: =IFERROR((_xlfn.XLOOKUP(I$4,Years,Costco_Revenue)-_xlfn.XLOOKUP(I$4,Years,Costco_COGS))/_xlfn.XLOOKUP(I$4,Years,Costco_Revenue),"n/a") -> 0.10569181 | ... K8: =IFERROR((_xlfn.XLOOKUP(K$4,Years,Costco_Revenue)-_xlfn.XLOOKUP(K$4,Years,Costco_COGS))/_xlfn.XLOOKUP(K$4,Years,Costco_Revenue),"n/a") -> 0.11124366 | L8: =IFERROR(K8-B8,"n/a") -> -0.0022366452 | M8: =IFERROR(I8-E8,"n/a") -> -0.0045518449 | N8: =IFERROR((_xludf.XLOOKUP(K$4,Years,Costco_Revenue)-_xludf.XLOOKUP(K$4,Years,Costco_COGS))/_xludf.XLOOKUP(K$4,Years,Costco_Revenue),"n/a") -> n/a
A9: Kroger | B9: =IFERROR((_xlfn.XLOOKUP(B$4,Years,Kroger_Revenue)-_xlfn.XLOOKUP(B$4,Years,Kroger_COGS))/_xlfn.XLOOKUP(B$4,Years,Kroger_Revenue),"n/a") -> 0.22399577 | C9: =IFERROR((_xlfn.XLOOKUP(C$4,Years,Kroger_Revenue)-_xlfn.XLOOKUP(C$4,Years,Kroger_COGS))/_xlfn.XLOOKUP(C$4,Years,Kroger_Revenue),"n/a") -> 0.22281798 | D9: =IFERROR((_xlfn.XLOOKUP(D$4,Years,Kroger_Revenue)-_xlfn.XLOOKUP(D$4,Years,Kroger_COGS))/_xlfn.XLOOKUP(D$4,Years,Kroger_Revenue),"n/a") -> 0.2195204 | E9: =IFERROR((_xlfn.XLOOKUP(E$4,Years,Kroger_Revenue)-_xlfn.XLOOKUP(E$4,Years,Kroger_COGS))/_xlfn.XLOOKUP(E$4,Years,Kroger_Revenue),"n/a") -> 0.22072846 | F9: =IFERROR((_xlfn.XLOOKUP(F$4,Years,Kroger_Revenue)-_xlfn.XLOOKUP(F$4,Years,Kroger_COGS))/_xlfn.XLOOKUP(F$4,Years,Kroger_Revenue),"n/a") -> 0.23321861 | G9: =IFERROR((_xlfn.XLOOKUP(G$4,Years,Kroger_Revenue)-_xlfn.XLOOKUP(G$4,Years,Kroger_COGS))/_xlfn.XLOOKUP(G$4,Years,Kroger_Revenue),"n/a") -> 0.22009892 | H9: =IFERROR((_xlfn.XLOOKUP(H$4,Years,Kroger_Revenue)-_xlfn.XLOOKUP(H$4,Years,Kroger_COGS))/_xlfn.XLOOKUP(H$4,Years,Kroger_Revenue),"n/a") -> 0.21434256 | I9: =IFERROR((_xlfn.XLOOKUP(I$4,Years,Kroger_Revenue)-_xlfn.XLOOKUP(I$4,Years,Kroger_COGS))/_xlfn.XLOOKUP(I$4,Years,Kroger_Revenue),"n/a") -> 0.22236885 | ... K9: =IFERROR((_xlfn.XLOOKUP(K$4,Years,Kroger_Revenue)-_xlfn.XLOOKUP(K$4,Years,Kroger_COGS))/_xlfn.XLOOKUP(K$4,Years,Kroger_Revenue),"n/a") -> 0.23300958 | L9: =IFERROR(K9-B9,"n/a") -> 0.0090138083 | M9: =IFERROR(I9-E9,"n/a") -> 0.0016403945 | N9: =IFERROR((_xludf.XLOOKUP(K$4,Years,Kroger_Revenue)-_xludf.XLOOKUP(K$4,Years,Kroger_COGS))/_xludf.XLOOKUP(K$4,Years,Kroger_Revenue),"n/a") -> n/a
A10: Sam's Club | B10: =IFERROR((_xlfn.XLOOKUP(B$4,Years,SamsClub_Revenue)-_xlfn.XLOOKUP(B$4,Years,SamsClub_COGS))/_xlfn.XLOOKUP(B$4,Years,SamsClub_Revenue),"n/a") -> n/a | C10: =IFERROR((_xlfn.XLOOKUP(C$4,Years,SamsClub_Revenue)-_xlfn.XLOOKUP(C$4,Years,SamsClub_COGS))/_xlfn.XLOOKUP(C$4,Years,SamsClub_Revenue),"n/a") -> n/a | D10: =IFERROR((_xlfn.XLOOKUP(D$4,Years,SamsClub_Revenue)-_xlfn.XLOOKUP(D$4,Years,SamsClub_COGS))/_xlfn.XLOOKUP(D$4,Years,SamsClub_Revenue),"n/a") -> n/a | E10: =IFERROR((_xlfn.XLOOKUP(E$4,Years,SamsClub_Revenue)-_xlfn.XLOOKUP(E$4,Years,SamsClub_COGS))/_xlfn.XLOOKUP(E$4,Years,SamsClub_Revenue),"n/a") -> n/a | F10: =IFERROR((_xlfn.XLOOKUP(F$4,Years,SamsClub_Revenue)-_xlfn.XLOOKUP(F$4,Years,SamsClub_COGS))/_xlfn.XLOOKUP(F$4,Years,SamsClub_Revenue),"n/a") -> n/a | G10: =IFERROR((_xlfn.XLOOKUP(G$4,Years,SamsClub_Revenue)-_xlfn.XLOOKUP(G$4,Years,SamsClub_COGS))/_xlfn.XLOOKUP(G$4,Years,SamsClub_Revenue),"n/a") -> n/a | H10: =IFERROR((_xlfn.XLOOKUP(H$4,Years,SamsClub_Revenue)-_xlfn.XLOOKUP(H$4,Years,SamsClub_COGS))/_xlfn.XLOOKUP(H$4,Years,SamsClub_Revenue),"n/a") -> 0.10387101 | I10: =IFERROR((_xlfn.XLOOKUP(I$4,Years,SamsClub_Revenue)-_xlfn.XLOOKUP(I$4,Years,SamsClub_COGS))/_xlfn.XLOOKUP(I$4,Years,SamsClub_Revenue),"n/a") -> 0.10943501 | ... K10: =IFERROR((_xlfn.XLOOKUP(K$4,Years,SamsClub_Revenue)-_xlfn.XLOOKUP(K$4,Years,SamsClub_COGS))/_xlfn.XLOOKUP(K$4,Years,SamsClub_Revenue),"n/a") -> 0.11348707 | L10: =IFERROR(K10-B10,"n/a") -> n/a | M10: =IFERROR(I10-E10,"n/a") -> n/a | N10: =IFERROR((_xludf.XLOOKUP(K$4,Years,SamsClub_Revenue)-_xludf.XLOOKUP(K$4,Years,SamsClub_COGS))/_xludf.XLOOKUP(K$4,Years,SamsClub_Revenue),"n/a") -> n/a
A11: Whole Foods | B11: =IFERROR((_xlfn.XLOOKUP(B$4,Years,WholeFoods_Revenue)-_xlfn.XLOOKUP(B$4,Years,WholeFoods_COGS))/_xlfn.XLOOKUP(B$4,Years,WholeFoods_Revenue),"n/a") -> 0.34412363 | C11: =IFERROR((_xlfn.XLOOKUP(C$4,Years,WholeFoods_Revenue)-_xlfn.XLOOKUP(C$4,Years,WholeFoods_COGS))/_xlfn.XLOOKUP(C$4,Years,WholeFoods_Revenue),"n/a") -> 0.33668122 | D11: =IFERROR((_xlfn.XLOOKUP(D$4,Years,WholeFoods_Revenue)-_xlfn.XLOOKUP(D$4,Years,WholeFoods_COGS))/_xlfn.XLOOKUP(D$4,Years,WholeFoods_Revenue),"n/a") -> n/a | E11: =IFERROR((_xlfn.XLOOKUP(E$4,Years,WholeFoods_Revenue)-_xlfn.XLOOKUP(E$4,Years,WholeFoods_COGS))/_xlfn.XLOOKUP(E$4,Years,WholeFoods_Revenue),"n/a") -> n/a | F11: =IFERROR((_xlfn.XLOOKUP(F$4,Years,WholeFoods_Revenue)-_xlfn.XLOOKUP(F$4,Years,WholeFoods_COGS))/_xlfn.XLOOKUP(F$4,Years,WholeFoods_Revenue),"n/a") -> n/a | G11: =IFERROR((_xlfn.XLOOKUP(G$4,Years,WholeFoods_Revenue)-_xlfn.XLOOKUP(G$4,Years,WholeFoods_COGS))/_xlfn.XLOOKUP(G$4,Years,WholeFoods_Revenue),"n/a") -> n/a | H11: =IFERROR((_xlfn.XLOOKUP(H$4,Years,WholeFoods_Revenue)-_xlfn.XLOOKUP(H$4,Years,WholeFoods_COGS))/_xlfn.XLOOKUP(H$4,Years,WholeFoods_Revenue),"n/a") -> n/a | I11: =IFERROR((_xlfn.XLOOKUP(I$4,Years,WholeFoods_Revenue)-_xlfn.XLOOKUP(I$4,Years,WholeFoods_COGS))/_xlfn.XLOOKUP(I$4,Years,WholeFoods_Revenue),"n/a") -> n/a | ... K11: =IFERROR((_xlfn.XLOOKUP(K$4,Years,WholeFoods_Revenue)-_xlfn.XLOOKUP(K$4,Years,WholeFoods_COGS))/_xlfn.XLOOKUP(K$4,Years,WholeFoods_Revenue),"n/a") -> n/a | L11: =IFERROR(K11-B11,"n/a") -> n/a | M11: =IFERROR(I11-E11,"n/a") -> n/a | N11: =IFERROR((_xludf.XLOOKUP(K$4,Years,WholeFoods_Revenue)-_xludf.XLOOKUP(K$4,Years,WholeFoods_COGS))/_xludf.XLOOKUP(K$4,Years,WholeFoods_Revenue),"n/a") -> n/a
A13: Operating margin (supplementary) — Operating income / Revenue – separates gross-margin pressure from SG&A
A14: Walmart | B14: =IFERROR(_xlfn.XLOOKUP(B$4,Years,Walmart_OperatingIncome)/_xlfn.XLOOKUP(B$4,Years,Walmart_Revenue),"n/a") -> 0.047295234 | C14: =IFERROR(_xlfn.XLOOKUP(C$4,Years,Walmart_OperatingIncome)/_xlfn.XLOOKUP(C$4,Years,Walmart_Revenue),"n/a") -> 0.041223493 | D14: =IFERROR(_xlfn.XLOOKUP(D$4,Years,Walmart_OperatingIncome)/_xlfn.XLOOKUP(D$4,Years,Walmart_Revenue),"n/a") -> 0.043025186 | E14: =IFERROR(_xlfn.XLOOKUP(E$4,Years,Walmart_OperatingIncome)/_xlfn.XLOOKUP(E$4,Years,Walmart_Revenue),"n/a") -> 0.039559476 | F14: =IFERROR(_xlfn.XLOOKUP(F$4,Years,Walmart_OperatingIncome)/_xlfn.XLOOKUP(F$4,Years,Walmart_Revenue),"n/a") -> 0.040609978 | G14: =IFERROR(_xlfn.XLOOKUP(G$4,Years,Walmart_OperatingIncome)/_xlfn.XLOOKUP(G$4,Years,Walmart_Revenue),"n/a") -> 0.045691681 | H14: =IFERROR(_xlfn.XLOOKUP(H$4,Years,Walmart_OperatingIncome)/_xlfn.XLOOKUP(H$4,Years,Walmart_Revenue),"n/a") -> 0.033716192 | I14: =IFERROR(_xlfn.XLOOKUP(I$4,Years,Walmart_OperatingIncome)/_xlfn.XLOOKUP(I$4,Years,Walmart_Revenue),"n/a") -> 0.042033061 | ... K14: =IFERROR(_xlfn.XLOOKUP(K$4,Years,Walmart_OperatingIncome)/_xlfn.XLOOKUP(K$4,Years,Walmart_Revenue),"n/a") -> 0.042220344 | L14: =IFERROR(K14-B14,"n/a") -> -0.0050748895 | M14: =IFERROR(I14-E14,"n/a") -> 0.0024735849 | N14: =IFERROR(_xludf.XLOOKUP(K$4,Years,Walmart_OperatingIncome)/_xludf.XLOOKUP(K$4,Years,Walmart_Revenue),"n/a") -> n/a
A15: Costco | B15: =IFERROR(_xlfn.XLOOKUP(B$4,Years,Costco_OperatingIncome)/_xlfn.XLOOKUP(B$4,Years,Costco_Revenue),"n/a") -> 0.031635264 | C15: =IFERROR(_xlfn.XLOOKUP(C$4,Years,Costco_OperatingIncome)/_xlfn.XLOOKUP(C$4,Years,Costco_Revenue),"n/a") -> 0.032582506 | D15: =IFERROR(_xlfn.XLOOKUP(D$4,Years,Costco_OperatingIncome)/_xlfn.XLOOKUP(D$4,Years,Costco_Revenue),"n/a") -> 0.032361992 | E15: =IFERROR(_xlfn.XLOOKUP(E$4,Years,Costco_OperatingIncome)/_xlfn.XLOOKUP(E$4,Years,Costco_Revenue),"n/a") -> 0.03171723 | F15: =IFERROR(_xlfn.XLOOKUP(F$4,Years,Costco_OperatingIncome)/_xlfn.XLOOKUP(F$4,Years,Costco_Revenue),"n/a") -> 0.033298615 | G15: =IFERROR(_xlfn.XLOOKUP(G$4,Years,Costco_OperatingIncome)/_xlfn.XLOOKUP(G$4,Years,Costco_Revenue),"n/a") -> 0.03492804 | H15: =IFERROR(_xlfn.XLOOKUP(H$4,Years,Costco_OperatingIncome)/_xlfn.XLOOKUP(H$4,Years,Costco_Revenue),"n/a") -> 0.034988551 | I15: =IFERROR(_xlfn.XLOOKUP(I$4,Years,Costco_OperatingIncome)/_xlfn.XLOOKUP(I$4,Years,Costco_Revenue),"n/a") -> 0.034134029 | ... K15: =IFERROR(_xlfn.XLOOKUP(K$4,Years,Costco_OperatingIncome)/_xlfn.XLOOKUP(K$4,Years,Costco_Revenue),"n/a") -> 0.038468093 | L15: =IFERROR(K15-B15,"n/a") -> 0.0068328293 | M15: =IFERROR(I15-E15,"n/a") -> 0.002416799 | N15: =IFERROR(_xludf.XLOOKUP(K$4,Years,Costco_OperatingIncome)/_xludf.XLOOKUP(K$4,Years,Costco_Revenue),"n/a") -> n/a
A16: Kroger | B16: =IFERROR(_xlfn.XLOOKUP(B$4,Years,Kroger_OperatingIncome)/_xlfn.XLOOKUP(B$4,Years,Kroger_Revenue),"n/a") -> 0.029929684 | C16: =IFERROR(_xlfn.XLOOKUP(C$4,Years,Kroger_OperatingIncome)/_xlfn.XLOOKUP(C$4,Years,Kroger_Revenue),"n/a") -> 0.021187541 | D16: =IFERROR(_xlfn.XLOOKUP(D$4,Years,Kroger_OperatingIncome)/_xlfn.XLOOKUP(D$4,Years,Kroger_Revenue),"n/a") -> 0.021452254 | E16: =IFERROR(_xlfn.XLOOKUP(E$4,Years,Kroger_OperatingIncome)/_xlfn.XLOOKUP(E$4,Years,Kroger_Revenue),"n/a") -> 0.018407667 | F16: =IFERROR(_xlfn.XLOOKUP(F$4,Years,Kroger_OperatingIncome)/_xlfn.XLOOKUP(F$4,Years,Kroger_Revenue),"n/a") -> 0.020981449 | G16: =IFERROR(_xlfn.XLOOKUP(G$4,Years,Kroger_OperatingIncome)/_xlfn.XLOOKUP(G$4,Years,Kroger_Revenue),"n/a") -> 0.025216117 | H16: =IFERROR(_xlfn.XLOOKUP(H$4,Years,Kroger_OperatingIncome)/_xlfn.XLOOKUP(H$4,Years,Kroger_Revenue),"n/a") -> 0.027829864 | I16: =IFERROR(_xlfn.XLOOKUP(I$4,Years,Kroger_OperatingIncome)/_xlfn.XLOOKUP(I$4,Years,Kroger_Revenue),"n/a") -> 0.020634635 | ... K16: =IFERROR(_xlfn.XLOOKUP(K$4,Years,Kroger_OperatingIncome)/_xlfn.XLOOKUP(K$4,Years,Kroger_Revenue),"n/a") -> 0.012801235 | L16: =IFERROR(K16-B16,"n/a") -> -0.017128449 | M16: =IFERROR(I16-E16,"n/a") -> 0.0022269677 | N16: =IFERROR(_xludf.XLOOKUP(K$4,Years,Kroger_OperatingIncome)/_xludf.XLOOKUP(K$4,Years,Kroger_Revenue),"n/a") -> n/a
A17: Sam's Club | B17: =IFERROR(_xlfn.XLOOKUP(B$4,Years,SamsClub_OperatingIncome)/_xlfn.XLOOKUP(B$4,Years,SamsClub_Revenue),"n/a") -> 0.028379674 | C17: =IFERROR(_xlfn.XLOOKUP(C$4,Years,SamsClub_OperatingIncome)/_xlfn.XLOOKUP(C$4,Years,SamsClub_Revenue),"n/a") -> 0.015451905 | D17: =IFERROR(_xlfn.XLOOKUP(D$4,Years,SamsClub_OperatingIncome)/_xlfn.XLOOKUP(D$4,Years,SamsClub_Revenue),"n/a") -> 0.026279846 | E17: =IFERROR(_xlfn.XLOOKUP(E$4,Years,SamsClub_OperatingIncome)/_xlfn.XLOOKUP(E$4,Years,SamsClub_Revenue),"n/a") -> 0.02792897 | F17: =IFERROR(_xlfn.XLOOKUP(F$4,Years,SamsClub_OperatingIncome)/_xlfn.XLOOKUP(F$4,Years,SamsClub_Revenue),"n/a") -> 0.029823189 | G17: =IFERROR(_xlfn.XLOOKUP(G$4,Years,SamsClub_OperatingIncome)/_xlfn.XLOOKUP(G$4,Years,SamsClub_Revenue),"n/a") -> 0.030711295 | H17: =IFERROR(_xlfn.XLOOKUP(H$4,Years,SamsClub_OperatingIncome)/_xlfn.XLOOKUP(H$4,Years,SamsClub_Revenue),"n/a") -> 0.023285316 | I17: =IFERROR(_xlfn.XLOOKUP(I$4,Years,SamsClub_OperatingIncome)/_xlfn.XLOOKUP(I$4,Years,SamsClub_Revenue),"n/a") -> 0.025435431 | ... K17: =IFERROR(_xlfn.XLOOKUP(K$4,Years,SamsClub_OperatingIncome)/_xlfn.XLOOKUP(K$4,Years,SamsClub_Revenue),"n/a") -> 0.02625383 | L17: =IFERROR(K17-B17,"n/a") -> -0.002125844 | M17: =IFERROR(I17-E17,"n/a") -> -0.002493539 | N17: =IFERROR(_xludf.XLOOKUP(K$4,Years,SamsClub_OperatingIncome)/_xludf.XLOOKUP(K$4,Years,SamsClub_Revenue),"n/a") -> n/a
A18: Whole Foods | B18: =IFERROR(_xlfn.XLOOKUP(B$4,Years,WholeFoods_OperatingIncome)/_xlfn.XLOOKUP(B$4,Years,WholeFoods_Revenue),"n/a") -> 0.054502671 | C18: =IFERROR(_xlfn.XLOOKUP(C$4,Years,WholeFoods_OperatingIncome)/_xlfn.XLOOKUP(C$4,Years,WholeFoods_Revenue),"n/a") -> 0.028633812 | D18: =IFERROR(_xlfn.XLOOKUP(D$4,Years,WholeFoods_OperatingIncome)/_xlfn.XLOOKUP(D$4,Years,WholeFoods_Revenue),"n/a") -> n/a | E18: =IFERROR(_xlfn.XLOOKUP(E$4,Years,WholeFoods_OperatingIncome)/_xlfn.XLOOKUP(E$4,Years,WholeFoods_Revenue),"n/a") -> n/a | F18: =IFERROR(_xlfn.XLOOKUP(F$4,Years,WholeFoods_OperatingIncome)/_xlfn.XLOOKUP(F$4,Years,WholeFoods_Revenue),"n/a") -> n/a | G18: =IFERROR(_xlfn.XLOOKUP(G$4,Years,WholeFoods_OperatingIncome)/_xlfn.XLOOKUP(G$4,Years,WholeFoods_Revenue),"n/a") -> n/a | H18: =IFERROR(_xlfn.XLOOKUP(H$4,Years,WholeFoods_OperatingIncome)/_xlfn.XLOOKUP(H$4,Years,WholeFoods_Revenue),"n/a") -> n/a | I18: =IFERROR(_xlfn.XLOOKUP(I$4,Years,WholeFoods_OperatingIncome)/_xlfn.XLOOKUP(I$4,Years,WholeFoods_Revenue),"n/a") -> n/a | ... K18: =IFERROR(_xlfn.XLOOKUP(K$4,Years,WholeFoods_OperatingIncome)/_xlfn.XLOOKUP(K$4,Years,WholeFoods_Revenue),"n/a") -> n/a | L18: =IFERROR(K18-B18,"n/a") -> n/a | M18: =IFERROR(I18-E18,"n/a") -> n/a | N18: =IFERROR(_xludf.XLOOKUP(K$4,Years,WholeFoods_OperatingIncome)/_xludf.XLOOKUP(K$4,Years,WholeFoods_Revenue),"n/a") -> n/a
A20: Net profit margin — Net income / Revenue
A21: Walmart | B21: =IFERROR(_xlfn.XLOOKUP(B$4,Years,Walmart_NetIncome)/_xlfn.XLOOKUP(B$4,Years,Walmart_Revenue),"n/a") -> 0.028345145 | C21: =IFERROR(_xlfn.XLOOKUP(C$4,Years,Walmart_NetIncome)/_xlfn.XLOOKUP(C$4,Years,Walmart_Revenue),"n/a") -> 0.01989265 | D21: =IFERROR(_xlfn.XLOOKUP(D$4,Years,Walmart_NetIncome)/_xlfn.XLOOKUP(D$4,Years,Walmart_Revenue),"n/a") -> 0.01307 | E21: =IFERROR(_xlfn.XLOOKUP(E$4,Years,Walmart_NetIncome)/_xlfn.XLOOKUP(E$4,Years,Walmart_Revenue),"n/a") -> 0.028621381 | F21: =IFERROR(_xlfn.XLOOKUP(F$4,Years,Walmart_NetIncome)/_xlfn.XLOOKUP(F$4,Years,Walmart_Revenue),"n/a") -> 0.024332127 | G21: =IFERROR(_xlfn.XLOOKUP(G$4,Years,Walmart_NetIncome)/_xlfn.XLOOKUP(G$4,Years,Walmart_Revenue),"n/a") -> 0.024082274 | H21: =IFERROR(_xlfn.XLOOKUP(H$4,Years,Walmart_NetIncome)/_xlfn.XLOOKUP(H$4,Years,Walmart_Revenue),"n/a") -> 0.019277713 | I21: =IFERROR(_xlfn.XLOOKUP(I$4,Years,Walmart_NetIncome)/_xlfn.XLOOKUP(I$4,Years,Walmart_Revenue),"n/a") -> 0.024136488 | ... K21: =IFERROR(_xlfn.XLOOKUP(K$4,Years,Walmart_NetIncome)/_xlfn.XLOOKUP(K$4,Years,Walmart_Revenue),"n/a") -> 0.030991785 | L21: =IFERROR(K21-B21,"n/a") -> 0.0026466406 | M21: =IFERROR(I21-E21,"n/a") -> -0.0044848931 | N21: =IFERROR(_xludf.XLOOKUP(K$4,Years,Walmart_NetIncome)/_xludf.XLOOKUP(K$4,Years,Walmart_Revenue),"n/a") -> n/a
A22: Costco | B22: =IFERROR(_xlfn.XLOOKUP(B$4,Years,Costco_NetIncome)/_xlfn.XLOOKUP(B$4,Years,Costco_Revenue),"n/a") -> 0.02024588 | C22: =IFERROR(_xlfn.XLOOKUP(C$4,Years,Costco_NetIncome)/_xlfn.XLOOKUP(C$4,Years,Costco_Revenue),"n/a") -> 0.02123292 | D22: =IFERROR(_xlfn.XLOOKUP(D$4,Years,Costco_NetIncome)/_xlfn.XLOOKUP(D$4,Years,Costco_Revenue),"n/a") -> 0.022638947 | E22: =IFERROR(_xlfn.XLOOKUP(E$4,Years,Costco_NetIncome)/_xlfn.XLOOKUP(E$4,Years,Costco_Revenue),"n/a") -> 0.024499334 | F22: =IFERROR(_xlfn.XLOOKUP(F$4,Years,Costco_NetIncome)/_xlfn.XLOOKUP(F$4,Years,Costco_Revenue),"n/a") -> 0.024519054 | G22: =IFERROR(_xlfn.XLOOKUP(G$4,Years,Costco_NetIncome)/_xlfn.XLOOKUP(G$4,Years,Costco_Revenue),"n/a") -> 0.026071064 | H22: =IFERROR(_xlfn.XLOOKUP(H$4,Years,Costco_NetIncome)/_xlfn.XLOOKUP(H$4,Years,Costco_Revenue),"n/a") -> 0.026238046 | I22: =IFERROR(_xlfn.XLOOKUP(I$4,Years,Costco_NetIncome)/_xlfn.XLOOKUP(I$4,Years,Costco_Revenue),"n/a") -> 0.026469227 | ... K22: =IFERROR(_xlfn.XLOOKUP(K$4,Years,Costco_NetIncome)/_xlfn.XLOOKUP(K$4,Years,Costco_Revenue),"n/a") -> 0.030006076 | L22: =IFERROR(K22-B22,"n/a") -> 0.0097601963 | M22: =IFERROR(I22-E22,"n/a") -> 0.0019698934 | N22: =IFERROR(_xludf.XLOOKUP(K$4,Years,Costco_NetIncome)/_xludf.XLOOKUP(K$4,Years,Costco_Revenue),"n/a") -> n/a
A23: Kroger | B23: =IFERROR(_xlfn.XLOOKUP(B$4,Years,Kroger_NetIncome)/_xlfn.XLOOKUP(B$4,Years,Kroger_Revenue),"n/a") -> 0.017123733 | C23: =IFERROR(_xlfn.XLOOKUP(C$4,Years,Kroger_NetIncome)/_xlfn.XLOOKUP(C$4,Years,Kroger_Revenue),"n/a") -> 0.015468851 | D23: =IFERROR(_xlfn.XLOOKUP(D$4,Years,Kroger_NetIncome)/_xlfn.XLOOKUP(D$4,Years,Kroger_Revenue),"n/a") -> 0.025522765 | E23: =IFERROR(_xlfn.XLOOKUP(E$4,Years,Kroger_NetIncome)/_xlfn.XLOOKUP(E$4,Years,Kroger_Revenue),"n/a") -> 0.013566557 | F23: =IFERROR(_xlfn.XLOOKUP(F$4,Years,Kroger_NetIncome)/_xlfn.XLOOKUP(F$4,Years,Kroger_Revenue),"n/a") -> 0.019509728 | G23: =IFERROR(_xlfn.XLOOKUP(G$4,Years,Kroger_NetIncome)/_xlfn.XLOOKUP(G$4,Years,Kroger_Revenue),"n/a") -> 0.012002495 | H23: =IFERROR(_xlfn.XLOOKUP(H$4,Years,Kroger_NetIncome)/_xlfn.XLOOKUP(H$4,Years,Kroger_Revenue),"n/a") -> 0.015135777 | I23: =IFERROR(_xlfn.XLOOKUP(I$4,Years,Kroger_NetIncome)/_xlfn.XLOOKUP(I$4,Years,Kroger_Revenue),"n/a") -> 0.014422917 | ... K23: =IFERROR(_xlfn.XLOOKUP(K$4,Years,Kroger_NetIncome)/_xlfn.XLOOKUP(K$4,Years,Kroger_Revenue),"n/a") -> 0.0068815107 | L23: =IFERROR(K23-B23,"n/a") -> -0.010242222 | M23: =IFERROR(I23-E23,"n/a") -> 0.00085635962 | N23: =IFERROR(_xludf.XLOOKUP(K$4,Years,Kroger_NetIncome)/_xludf.XLOOKUP(K$4,Years,Kroger_Revenue),"n/a") -> n/a
A24: Sam's Club | B24: =IFERROR(_xlfn.XLOOKUP(B$4,Years,SamsClub_NetIncome)/_xlfn.XLOOKUP(B$4,Years,SamsClub_Revenue),"n/a") -> n/a | C24: =IFERROR(_xlfn.XLOOKUP(C$4,Years,SamsClub_NetIncome)/_xlfn.XLOOKUP(C$4,Years,SamsClub_Revenue),"n/a") -> n/a | D24: =IFERROR(_xlfn.XLOOKUP(D$4,Years,SamsClub_NetIncome)/_xlfn.XLOOKUP(D$4,Years,SamsClub_Revenue),"n/a") -> n/a | E24: =IFERROR(_xlfn.XLOOKUP(E$4,Years,SamsClub_NetIncome)/_xlfn.XLOOKUP(E$4,Years,SamsClub_Revenue),"n/a") -> n/a | F24: =IFERROR(_xlfn.XLOOKUP(F$4,Years,SamsClub_NetIncome)/_xlfn.XLOOKUP(F$4,Years,SamsClub_Revenue),"n/a") -> n/a | G24: =IFERROR(_xlfn.XLOOKUP(G$4,Years,SamsClub_NetIncome)/_xlfn.XLOOKUP(G$4,Years,SamsClub_Revenue),"n/a") -> n/a | H24: =IFERROR(_xlfn.XLOOKUP(H$4,Years,SamsClub_NetIncome)/_xlfn.XLOOKUP(H$4,Years,SamsClub_Revenue),"n/a") -> n/a | I24: =IFERROR(_xlfn.XLOOKUP(I$4,Years,SamsClub_NetIncome)/_xlfn.XLOOKUP(I$4,Years,SamsClub_Revenue),"n/a") -> n/a | ... K24: =IFERROR(_xlfn.XLOOKUP(K$4,Years,SamsClub_NetIncome)/_xlfn.XLOOKUP(K$4,Years,SamsClub_Revenue),"n/a") -> n/a | L24: =IFERROR(K24-B24,"n/a") -> n/a | M24: =IFERROR(I24-E24,"n/a") -> n/a | N24: =IFERROR(_xludf.XLOOKUP(K$4,Years,SamsClub_NetIncome)/_xludf.XLOOKUP(K$4,Years,SamsClub_Revenue),"n/a") -> n/a
A25: Whole Foods | B25: =IFERROR(_xlfn.XLOOKUP(B$4,Years,WholeFoods_NetIncome)/_xlfn.XLOOKUP(B$4,Years,WholeFoods_Revenue),"n/a") -> 0.032243704 | C25: =IFERROR(_xlfn.XLOOKUP(C$4,Years,WholeFoods_NetIncome)/_xlfn.XLOOKUP(C$4,Years,WholeFoods_Revenue),"n/a") -> 0.015283843 | D25: =IFERROR(_xlfn.XLOOKUP(D$4,Years,WholeFoods_NetIncome)/_xlfn.XLOOKUP(D$4,Years,WholeFoods_Revenue),"n/a") -> n/a | E25: =IFERROR(_xlfn.XLOOKUP(E$4,Years,WholeFoods_NetIncome)/_xlfn.XLOOKUP(E$4,Years,WholeFoods_Revenue),"n/a") -> n/a | F25: =IFERROR(_xlfn.XLOOKUP(F$4,Years,WholeFoods_NetIncome)/_xlfn.XLOOKUP(F$4,Years,WholeFoods_Revenue),"n/a") -> n/a | G25: =IFERROR(_xlfn.XLOOKUP(G$4,Years,WholeFoods_NetIncome)/_xlfn.XLOOKUP(G$4,Years,WholeFoods_Revenue),"n/a") -> n/a | H25: =IFERROR(_xlfn.XLOOKUP(H$4,Years,WholeFoods_NetIncome)/_xlfn.XLOOKUP(H$4,Years,WholeFoods_Revenue),"n/a") -> n/a | I25: =IFERROR(_xlfn.XLOOKUP(I$4,Years,WholeFoods_NetIncome)/_xlfn.XLOOKUP(I$4,Years,WholeFoods_Revenue),"n/a") -> n/a | ... K25: =IFERROR(_xlfn.XLOOKUP(K$4,Years,WholeFoods_NetIncome)/_xlfn.XLOOKUP(K$4,Years,WholeFoods_Revenue),"n/a") -> n/a | L25: =IFERROR(K25-B25,"n/a") -> n/a | M25: =IFERROR(I25-E25,"n/a") -> n/a | N25: =IFERROR(_xludf.XLOOKUP(K$4,Years,WholeFoods_NetIncome)/_xludf.XLOOKUP(K$4,Years,WholeFoods_Revenue),"n/a") -> n/a
A27: Current ratio — Current assets / Current liabilities
A28: Walmart | B28: =IFERROR(_xlfn.XLOOKUP(B$4,Years,Walmart_CurrentAssets)/_xlfn.XLOOKUP(B$4,Years,Walmart_CurrentLiabilities),"n/a") -> 0.86195613 | C28: =IFERROR(_xlfn.XLOOKUP(C$4,Years,Walmart_CurrentAssets)/_xlfn.XLOOKUP(C$4,Years,Walmart_CurrentLiabilities),"n/a") -> 0.75984768 | D28: =IFERROR(_xlfn.XLOOKUP(D$4,Years,Walmart_CurrentAssets)/_xlfn.XLOOKUP(D$4,Years,Walmart_CurrentLiabilities),"n/a") -> 0.79890806 | E28: =IFERROR(_xlfn.XLOOKUP(E$4,Years,Walmart_CurrentAssets)/_xlfn.XLOOKUP(E$4,Years,Walmart_CurrentLiabilities),"n/a") -> 0.79452372 | F28: =IFERROR(_xlfn.XLOOKUP(F$4,Years,Walmart_CurrentAssets)/_xlfn.XLOOKUP(F$4,Years,Walmart_CurrentLiabilities),"n/a") -> 0.97217335 | G28: =IFERROR(_xlfn.XLOOKUP(G$4,Years,Walmart_CurrentAssets)/_xlfn.XLOOKUP(G$4,Years,Walmart_CurrentLiabilities),"n/a") -> 0.9277973 | H28: =IFERROR(_xlfn.XLOOKUP(H$4,Years,Walmart_CurrentAssets)/_xlfn.XLOOKUP(H$4,Years,Walmart_CurrentLiabilities),"n/a") -> 0.82057095 | I28: =IFERROR(_xlfn.XLOOKUP(I$4,Years,Walmart_CurrentAssets)/_xlfn.XLOOKUP(I$4,Years,Walmart_CurrentLiabilities),"n/a") -> 0.83186712 | ... K28: =IFERROR(_xlfn.XLOOKUP(K$4,Years,Walmart_CurrentAssets)/_xlfn.XLOOKUP(K$4,Years,Walmart_CurrentLiabilities),"n/a") -> 0.78975332 | L28: =IFERROR(K28-B28,"n/a") -> -0.072202808 | M28: =IFERROR(I28-E28,"n/a") -> 0.037343403 | N28: =IFERROR(_xludf.XLOOKUP(K$4,Years,Walmart_CurrentAssets)/_xludf.XLOOKUP(K$4,Years,Walmart_CurrentLiabilities),"n/a") -> n/a
A29: Costco | B29: =IFERROR(_xlfn.XLOOKUP(B$4,Years,Costco_CurrentAssets)/_xlfn.XLOOKUP(B$4,Years,Costco_CurrentLiabilities),"n/a") -> 0.97707865 | C29: =IFERROR(_xlfn.XLOOKUP(C$4,Years,Costco_CurrentAssets)/_xlfn.XLOOKUP(C$4,Years,Costco_CurrentLiabilities),"n/a") -> 0.98982566 | D29: =IFERROR(_xlfn.XLOOKUP(D$4,Years,Costco_CurrentAssets)/_xlfn.XLOOKUP(D$4,Years,Costco_CurrentLiabilities),"n/a") -> 1.0182174 | E29: =IFERROR(_xlfn.XLOOKUP(E$4,Years,Costco_CurrentAssets)/_xlfn.XLOOKUP(E$4,Years,Costco_CurrentLiabilities),"n/a") -> 1.0106726 | F29: =IFERROR(_xlfn.XLOOKUP(F$4,Years,Costco_CurrentAssets)/_xlfn.XLOOKUP(F$4,Years,Costco_CurrentLiabilities),"n/a") -> 1.1318628 | G29: =IFERROR(_xlfn.XLOOKUP(G$4,Years,Costco_CurrentAssets)/_xlfn.XLOOKUP(G$4,Years,Costco_CurrentLiabilities),"n/a") -> 1.0021738 | H29: =IFERROR(_xlfn.XLOOKUP(H$4,Years,Costco_CurrentAssets)/_xlfn.XLOOKUP(H$4,Years,Costco_CurrentLiabilities),"n/a") -> 1.0218139 | I29: =IFERROR(_xlfn.XLOOKUP(I$4,Years,Costco_CurrentAssets)/_xlfn.XLOOKUP(I$4,Years,Costco_CurrentLiabilities),"n/a") -> 1.0683679 | ... K29: =IFERROR(_xlfn.XLOOKUP(K$4,Years,Costco_CurrentAssets)/_xlfn.XLOOKUP(K$4,Years,Costco_CurrentLiabilities),"n/a") -> 1.0342783 | L29: =IFERROR(K29-B29,"n/a") -> 0.057199671 | M29: =IFERROR(I29-E29,"n/a") -> 0.05769529 | N29: =IFERROR(_xludf.XLOOKUP(K$4,Years,Costco_CurrentAssets)/_xludf.XLOOKUP(K$4,Years,Costco_CurrentLiabilities),"n/a") -> n/a
A30: Kroger | B30: =IFERROR(_xlfn.XLOOKUP(B$4,Years,Kroger_CurrentAssets)/_xlfn.XLOOKUP(B$4,Years,Kroger_CurrentLiabilities),"n/a") -> 0.80404355 | C30: =IFERROR(_xlfn.XLOOKUP(C$4,Years,Kroger_CurrentAssets)/_xlfn.XLOOKUP(C$4,Years,Kroger_CurrentLiabilities),"n/a") -> 0.78305276 | D30: =IFERROR(_xlfn.XLOOKUP(D$4,Years,Kroger_CurrentAssets)/_xlfn.XLOOKUP(D$4,Years,Kroger_CurrentLiabilities),"n/a") -> 0.7568306 | E30: =IFERROR(_xlfn.XLOOKUP(E$4,Years,Kroger_CurrentAssets)/_xlfn.XLOOKUP(E$4,Years,Kroger_CurrentLiabilities),"n/a") -> 0.76458611 | F30: =IFERROR(_xlfn.XLOOKUP(F$4,Years,Kroger_CurrentAssets)/_xlfn.XLOOKUP(F$4,Years,Kroger_CurrentLiabilities),"n/a") -> 0.81367955 | G30: =IFERROR(_xlfn.XLOOKUP(G$4,Years,Kroger_CurrentAssets)/_xlfn.XLOOKUP(G$4,Years,Kroger_CurrentLiabilities),"n/a") -> 0.74581878 | H30: =IFERROR(_xlfn.XLOOKUP(H$4,Years,Kroger_CurrentAssets)/_xlfn.XLOOKUP(H$4,Years,Kroger_CurrentLiabilities),"n/a") -> 0.73500406 | I30: =IFERROR(_xlfn.XLOOKUP(I$4,Years,Kroger_CurrentAssets)/_xlfn.XLOOKUP(I$4,Years,Kroger_CurrentLiabilities),"n/a") -> 0.80632706 | ... K30: =IFERROR(_xlfn.XLOOKUP(K$4,Years,Kroger_CurrentAssets)/_xlfn.XLOOKUP(K$4,Years,Kroger_CurrentLiabilities),"n/a") -> 0.80102717 | L30: =IFERROR(K30-B30,"n/a") -> -0.0030163756 | M30: =IFERROR(I30-E30,"n/a") -> 0.041740952 | N30: =IFERROR(_xludf.XLOOKUP(K$4,Years,Kroger_CurrentAssets)/_xludf.XLOOKUP(K$4,Years,Kroger_CurrentLiabilities),"n/a") -> n/a
A31: Sam's Club | B31: =IFERROR(_xlfn.XLOOKUP(B$4,Years,SamsClub_CurrentAssets)/_xlfn.XLOOKUP(B$4,Years,SamsClub_CurrentLiabilities),"n/a") -> n/a | C31: =IFERROR(_xlfn.XLOOKUP(C$4,Years,SamsClub_CurrentAssets)/_xlfn.XLOOKUP(C$4,Years,SamsClub_CurrentLiabilities),"n/a") -> n/a | D31: =IFERROR(_xlfn.XLOOKUP(D$4,Years,SamsClub_CurrentAssets)/_xlfn.XLOOKUP(D$4,Years,SamsClub_CurrentLiabilities),"n/a") -> n/a | E31: =IFERROR(_xlfn.XLOOKUP(E$4,Years,SamsClub_CurrentAssets)/_xlfn.XLOOKUP(E$4,Years,SamsClub_CurrentLiabilities),"n/a") -> n/a | F31: =IFERROR(_xlfn.XLOOKUP(F$4,Years,SamsClub_CurrentAssets)/_xlfn.XLOOKUP(F$4,Years,SamsClub_CurrentLiabilities),"n/a") -> n/a | G31: =IFERROR(_xlfn.XLOOKUP(G$4,Years,SamsClub_CurrentAssets)/_xlfn.XLOOKUP(G$4,Years,SamsClub_CurrentLiabilities),"n/a") -> n/a | H31: =IFERROR(_xlfn.XLOOKUP(H$4,Years,SamsClub_CurrentAssets)/_xlfn.XLOOKUP(H$4,Years,SamsClub_CurrentLiabilities),"n/a") -> n/a | I31: =IFERROR(_xlfn.XLOOKUP(I$4,Years,SamsClub_CurrentAssets)/_xlfn.XLOOKUP(I$4,Years,SamsClub_CurrentLiabilities),"n/a") -> n/a | ... K31: =IFERROR(_xlfn.XLOOKUP(K$4,Years,SamsClub_CurrentAssets)/_xlfn.XLOOKUP(K$4,Years,SamsClub_CurrentLiabilities),"n/a") -> n/a | L31: =IFERROR(K31-B31,"n/a") -> n/a | M31: =IFERROR(I31-E31,"n/a") -> n/a | N31: =IFERROR(_xludf.XLOOKUP(K$4,Years,SamsClub_CurrentAssets)/_xludf.XLOOKUP(K$4,Years,SamsClub_CurrentLiabilities),"n/a") -> n/a
A32: Whole Foods | B32: =IFERROR(_xlfn.XLOOKUP(B$4,Years,WholeFoods_CurrentAssets)/_xlfn.XLOOKUP(B$4,Years,WholeFoods_CurrentLiabilities),"n/a") -> 1.4727815 | C32: =IFERROR(_xlfn.XLOOKUP(C$4,Years,WholeFoods_CurrentAssets)/_xlfn.XLOOKUP(C$4,Years,WholeFoods_CurrentLiabilities),"n/a") -> 1.5830258 | D32: =IFERROR(_xlfn.XLOOKUP(D$4,Years,WholeFoods_CurrentAssets)/_xlfn.XLOOKUP(D$4,Years,WholeFoods_CurrentLiabilities),"n/a") -> n/a | E32: =IFERROR(_xlfn.XLOOKUP(E$4,Years,WholeFoods_CurrentAssets)/_xlfn.XLOOKUP(E$4,Years,WholeFoods_CurrentLiabilities),"n/a") -> n/a | F32: =IFERROR(_xlfn.XLOOKUP(F$4,Years,WholeFoods_CurrentAssets)/_xlfn.XLOOKUP(F$4,Years,WholeFoods_CurrentLiabilities),"n/a") -> n/a | G32: =IFERROR(_xlfn.XLOOKUP(G$4,Years,WholeFoods_CurrentAssets)/_xlfn.XLOOKUP(G$4,Years,WholeFoods_CurrentLiabilities),"n/a") -> n/a | H32: =IFERROR(_xlfn.XLOOKUP(H$4,Years,WholeFoods_CurrentAssets)/_xlfn.XLOOKUP(H$4,Years,WholeFoods_CurrentLiabilities),"n/a") -> n/a | I32: =IFERROR(_xlfn.XLOOKUP(I$4,Years,WholeFoods_CurrentAssets)/_xlfn.XLOOKUP(I$4,Years,WholeFoods_CurrentLiabilities),"n/a") -> n/a | ... K32: =IFERROR(_xlfn.XLOOKUP(K$4,Years,WholeFoods_CurrentAssets)/_xlfn.XLOOKUP(K$4,Years,WholeFoods_CurrentLiabilities),"n/a") -> n/a | L32: =IFERROR(K32-B32,"n/a") -> n/a | M32: =IFERROR(I32-E32,"n/a") -> n/a | N32: =IFERROR(_xludf.XLOOKUP(K$4,Years,WholeFoods_CurrentAssets)/_xludf.XLOOKUP(K$4,Years,WholeFoods_CurrentLiabilities),"n/a") -> n/a
A34: Debt-to-equity — Total debt / Total equity (finance leases in, operating leases out – ASC 842 policy)
A35: Walmart | B35: =IFERROR(_xlfn.XLOOKUP(B$4,Years,Walmart_TotalDebt)/_xlfn.XLOOKUP(B$4,Years,Walmart_TotalEquity),"n/a") -> 0.57041038 | C35: =IFERROR(_xlfn.XLOOKUP(C$4,Years,Walmart_TotalDebt)/_xlfn.XLOOKUP(C$4,Years,Walmart_TotalEquity),"n/a") -> 0.57517755 | D35: =IFERROR(_xlfn.XLOOKUP(D$4,Years,Walmart_TotalDebt)/_xlfn.XLOOKUP(D$4,Years,Walmart_TotalEquity),"n/a") -> 0.72874652 | E35: =IFERROR(_xlfn.XLOOKUP(E$4,Years,Walmart_TotalDebt)/_xlfn.XLOOKUP(E$4,Years,Walmart_TotalEquity),"n/a") -> 0.66790514 | F35: =IFERROR(_xlfn.XLOOKUP(F$4,Years,Walmart_TotalDebt)/_xlfn.XLOOKUP(F$4,Years,Walmart_TotalEquity),"n/a") -> 0.55832791 | G35: =IFERROR(_xlfn.XLOOKUP(G$4,Years,Walmart_TotalDebt)/_xlfn.XLOOKUP(G$4,Years,Walmart_TotalEquity),"n/a") -> 0.46610658 | H35: =IFERROR(_xlfn.XLOOKUP(H$4,Years,Walmart_TotalDebt)/_xlfn.XLOOKUP(H$4,Years,Walmart_TotalEquity),"n/a") -> 0.53277455 | I35: =IFERROR(_xlfn.XLOOKUP(I$4,Years,Walmart_TotalDebt)/_xlfn.XLOOKUP(I$4,Years,Walmart_TotalEquity),"n/a") -> 0.51899855 | ... K35: =IFERROR(_xlfn.XLOOKUP(K$4,Years,Walmart_TotalDebt)/_xlfn.XLOOKUP(K$4,Years,Walmart_TotalEquity),"n/a") -> 0.48658476 | L35: =IFERROR(K35-B35,"n/a") -> -0.083825625 | M35: =IFERROR(I35-E35,"n/a") -> -0.14890659 | N35: =IFERROR(_xludf.XLOOKUP(K$4,Years,Walmart_TotalDebt)/_xludf.XLOOKUP(K$4,Years,Walmart_TotalEquity),"n/a") -> n/a
A36: Costco | B36: =IFERROR(_xlfn.XLOOKUP(B$4,Years,Costco_TotalDebt)/_xlfn.XLOOKUP(B$4,Years,Costco_TotalEquity),"n/a") -> 0.44883231 | C36: =IFERROR(_xlfn.XLOOKUP(C$4,Years,Costco_TotalDebt)/_xlfn.XLOOKUP(C$4,Years,Costco_TotalEquity),"n/a") -> 0.63534615 | D36: =IFERROR(_xlfn.XLOOKUP(D$4,Years,Costco_TotalDebt)/_xlfn.XLOOKUP(D$4,Years,Costco_TotalEquity),"n/a") -> 0.53224452 | E36: =IFERROR(_xlfn.XLOOKUP(E$4,Years,Costco_TotalDebt)/_xlfn.XLOOKUP(E$4,Years,Costco_TotalEquity),"n/a") -> 0.46483573 | F36: =IFERROR(_xlfn.XLOOKUP(F$4,Years,Costco_TotalDebt)/_xlfn.XLOOKUP(F$4,Years,Costco_TotalEquity),"n/a") -> 0.44357124 | G36: =IFERROR(_xlfn.XLOOKUP(G$4,Years,Costco_TotalDebt)/_xlfn.XLOOKUP(G$4,Years,Costco_TotalEquity),"n/a") -> 0.47256334 | H36: =IFERROR(_xlfn.XLOOKUP(H$4,Years,Costco_TotalDebt)/_xlfn.XLOOKUP(H$4,Years,Costco_TotalEquity),"n/a") -> 0.39642563 | I36: =IFERROR(_xlfn.XLOOKUP(I$4,Years,Costco_TotalDebt)/_xlfn.XLOOKUP(I$4,Years,Costco_TotalEquity),"n/a") -> 0.3148695 | ... K36: =IFERROR(_xlfn.XLOOKUP(K$4,Years,Costco_TotalDebt)/_xlfn.XLOOKUP(K$4,Years,Costco_TotalEquity),"n/a") -> 0.24917707 | L36: =IFERROR(K36-B36,"n/a") -> -0.19965524 | M36: =IFERROR(I36-E36,"n/a") -> -0.14996623 | N36: =IFERROR(_xludf.XLOOKUP(K$4,Years,Costco_TotalDebt)/_xludf.XLOOKUP(K$4,Years,Costco_TotalEquity),"n/a") -> n/a
A37: Kroger | B37: =IFERROR(_xlfn.XLOOKUP(B$4,Years,Kroger_TotalDebt)/_xlfn.XLOOKUP(B$4,Years,Kroger_TotalEquity),"n/a") -> 2.0979136 | C37: =IFERROR(_xlfn.XLOOKUP(C$4,Years,Kroger_TotalDebt)/_xlfn.XLOOKUP(C$4,Years,Kroger_TotalEquity),"n/a") -> 2.2576394 | D37: =IFERROR(_xlfn.XLOOKUP(D$4,Years,Kroger_TotalDebt)/_xlfn.XLOOKUP(D$4,Years,Kroger_TotalEquity),"n/a") -> 1.9437141 | E37: =IFERROR(_xlfn.XLOOKUP(E$4,Years,Kroger_TotalDebt)/_xlfn.XLOOKUP(E$4,Years,Kroger_TotalEquity),"n/a") -> 1.641899 | F37: =IFERROR(_xlfn.XLOOKUP(F$4,Years,Kroger_TotalDebt)/_xlfn.XLOOKUP(F$4,Years,Kroger_TotalEquity),"n/a") -> 1.4045026 | G37: =IFERROR(_xlfn.XLOOKUP(G$4,Years,Kroger_TotalDebt)/_xlfn.XLOOKUP(G$4,Years,Kroger_TotalEquity),"n/a") -> 1.4173295 | H37: =IFERROR(_xlfn.XLOOKUP(H$4,Years,Kroger_TotalDebt)/_xlfn.XLOOKUP(H$4,Years,Kroger_TotalEquity),"n/a") -> 1.3359297 | I37: =IFERROR(_xlfn.XLOOKUP(I$4,Years,Kroger_TotalDebt)/_xlfn.XLOOKUP(I$4,Years,Kroger_TotalEquity),"n/a") -> 1.0538747 | ... K37: =IFERROR(_xlfn.XLOOKUP(K$4,Years,Kroger_TotalDebt)/_xlfn.XLOOKUP(K$4,Years,Kroger_TotalEquity),"n/a") -> 2.9592318 | L37: =IFERROR(K37-B37,"n/a") -> 0.86131824 | M37: =IFERROR(I37-E37,"n/a") -> -0.58802432 | N37: =IFERROR(_xludf.XLOOKUP(K$4,Years,Kroger_TotalDebt)/_xludf.XLOOKUP(K$4,Years,Kroger_TotalEquity),"n/a") -> n/a
A38: Sam's Club | B38: =IFERROR(_xlfn.XLOOKUP(B$4,Years,SamsClub_TotalDebt)/_xlfn.XLOOKUP(B$4,Years,SamsClub_TotalEquity),"n/a") -> n/a | C38: =IFERROR(_xlfn.XLOOKUP(C$4,Years,SamsClub_TotalDebt)/_xlfn.XLOOKUP(C$4,Years,SamsClub_TotalEquity),"n/a") -> n/a | D38: =IFERROR(_xlfn.XLOOKUP(D$4,Years,SamsClub_TotalDebt)/_xlfn.XLOOKUP(D$4,Years,SamsClub_TotalEquity),"n/a") -> n/a | E38: =IFERROR(_xlfn.XLOOKUP(E$4,Years,SamsClub_TotalDebt)/_xlfn.XLOOKUP(E$4,Years,SamsClub_TotalEquity),"n/a") -> n/a | F38: =IFERROR(_xlfn.XLOOKUP(F$4,Years,SamsClub_TotalDebt)/_xlfn.XLOOKUP(F$4,Years,SamsClub_TotalEquity),"n/a") -> n/a | G38: =IFERROR(_xlfn.XLOOKUP(G$4,Years,SamsClub_TotalDebt)/_xlfn.XLOOKUP(G$4,Years,SamsClub_TotalEquity),"n/a") -> n/a | H38: =IFERROR(_xlfn.XLOOKUP(H$4,Years,SamsClub_TotalDebt)/_xlfn.XLOOKUP(H$4,Years,SamsClub_TotalEquity),"n/a") -> n/a | I38: =IFERROR(_xlfn.XLOOKUP(I$4,Years,SamsClub_TotalDebt)/_xlfn.XLOOKUP(I$4,Years,SamsClub_TotalEquity),"n/a") -> n/a | ... K38: =IFERROR(_xlfn.XLOOKUP(K$4,Years,SamsClub_TotalDebt)/_xlfn.XLOOKUP(K$4,Years,SamsClub_TotalEquity),"n/a") -> n/a | L38: =IFERROR(K38-B38,"n/a") -> n/a | M38: =IFERROR(I38-E38,"n/a") -> n/a | N38: =IFERROR(_xludf.XLOOKUP(K$4,Years,SamsClub_TotalDebt)/_xludf.XLOOKUP(K$4,Years,SamsClub_TotalEquity),"n/a") -> n/a
A39: Whole Foods | B39: =IFERROR(_xlfn.XLOOKUP(B$4,Years,WholeFoods_TotalDebt)/_xlfn.XLOOKUP(B$4,Years,WholeFoods_TotalEquity),"n/a") -> 0.32599256 | C39: =IFERROR(_xlfn.XLOOKUP(C$4,Years,WholeFoods_TotalDebt)/_xlfn.XLOOKUP(C$4,Years,WholeFoods_TotalEquity),"n/a") -> 0.31574344 | D39: =IFERROR(_xlfn.XLOOKUP(D$4,Years,WholeFoods_TotalDebt)/_xlfn.XLOOKUP(D$4,Years,WholeFoods_TotalEquity),"n/a") -> n/a | E39: =IFERROR(_xlfn.XLOOKUP(E$4,Years,WholeFoods_TotalDebt)/_xlfn.XLOOKUP(E$4,Years,WholeFoods_TotalEquity),"n/a") -> n/a | F39: =IFERROR(_xlfn.XLOOKUP(F$4,Years,WholeFoods_TotalDebt)/_xlfn.XLOOKUP(F$4,Years,WholeFoods_TotalEquity),"n/a") -> n/a | G39: =IFERROR(_xlfn.XLOOKUP(G$4,Years,WholeFoods_TotalDebt)/_xlfn.XLOOKUP(G$4,Years,WholeFoods_TotalEquity),"n/a") -> n/a | H39: =IFERROR(_xlfn.XLOOKUP(H$4,Years,WholeFoods_TotalDebt)/_xlfn.XLOOKUP(H$4,Years,WholeFoods_TotalEquity),"n/a") -> n/a | I39: =IFERROR(_xlfn.XLOOKUP(I$4,Years,WholeFoods_TotalDebt)/_xlfn.XLOOKUP(I$4,Years,WholeFoods_TotalEquity),"n/a") -> n/a | ... K39: =IFERROR(_xlfn.XLOOKUP(K$4,Years,WholeFoods_TotalDebt)/_xlfn.XLOOKUP(K$4,Years,WholeFoods_TotalEquity),"n/a") -> n/a | L39: =IFERROR(K39-B39,"n/a") -> n/a | M39: =IFERROR(I39-E39,"n/a") -> n/a | N39: =IFERROR(_xludf.XLOOKUP(K$4,Years,WholeFoods_TotalDebt)/_xludf.XLOOKUP(K$4,Years,WholeFoods_TotalEquity),"n/a") -> n/a
A41: Debt-to-equity incl. operating leases (supplementary) — (Total debt + Operating lease liability) / Total equity – lease-adjusted view from FY2019
A42: Walmart | B42: =IFERROR((_xlfn.XLOOKUP(B$4,Years,Walmart_TotalDebt)+_xlfn.XLOOKUP(B$4,Years,Walmart_OperatingLease))/_xlfn.XLOOKUP(B$4,Years,Walmart_TotalEquity),"n/a") -> n/a | C42: =IFERROR((_xlfn.XLOOKUP(C$4,Years,Walmart_TotalDebt)+_xlfn.XLOOKUP(C$4,Years,Walmart_OperatingLease))/_xlfn.XLOOKUP(C$4,Years,Walmart_TotalEquity),"n/a") -> n/a | D42: =IFERROR((_xlfn.XLOOKUP(D$4,Years,Walmart_TotalDebt)+_xlfn.XLOOKUP(D$4,Years,Walmart_OperatingLease))/_xlfn.XLOOKUP(D$4,Years,Walmart_TotalEquity),"n/a") -> n/a | E42: =IFERROR((_xlfn.XLOOKUP(E$4,Years,Walmart_TotalDebt)+_xlfn.XLOOKUP(E$4,Years,Walmart_OperatingLease))/_xlfn.XLOOKUP(E$4,Years,Walmart_TotalEquity),"n/a") -> 0.88818177 | F42: =IFERROR((_xlfn.XLOOKUP(F$4,Years,Walmart_TotalDebt)+_xlfn.XLOOKUP(F$4,Years,Walmart_OperatingLease))/_xlfn.XLOOKUP(F$4,Years,Walmart_TotalEquity),"n/a") -> 0.72255544 | G42: =IFERROR((_xlfn.XLOOKUP(G$4,Years,Walmart_TotalDebt)+_xlfn.XLOOKUP(G$4,Years,Walmart_OperatingLease))/_xlfn.XLOOKUP(G$4,Years,Walmart_TotalEquity),"n/a") -> 0.62381517 | H42: =IFERROR((_xlfn.XLOOKUP(H$4,Years,Walmart_TotalDebt)+_xlfn.XLOOKUP(H$4,Years,Walmart_OperatingLease))/_xlfn.XLOOKUP(H$4,Years,Walmart_TotalEquity),"n/a") -> 0.70352461 | I42: =IFERROR((_xlfn.XLOOKUP(I$4,Years,Walmart_TotalDebt)+_xlfn.XLOOKUP(I$4,Years,Walmart_OperatingLease))/_xlfn.XLOOKUP(I$4,Years,Walmart_TotalEquity),"n/a") -> 0.67871255 | ... K42: =IFERROR((_xlfn.XLOOKUP(K$4,Years,Walmart_TotalDebt)+_xlfn.XLOOKUP(K$4,Years,Walmart_OperatingLease))/_xlfn.XLOOKUP(K$4,Years,Walmart_TotalEquity),"n/a") -> 0.63364719 | L42: =IFERROR(K42-B42,"n/a") -> n/a | M42: =IFERROR(I42-E42,"n/a") -> -0.20946923 | N42: =IFERROR((_xludf.XLOOKUP(K$4,Years,Walmart_TotalDebt)+_xludf.XLOOKUP(K$4,Years,Walmart_OperatingLease))/_xludf.XLOOKUP(K$4,Years,Walmart_TotalEquity),"n/a") -> n/a
A43: Costco | B43: =IFERROR((_xlfn.XLOOKUP(B$4,Years,Costco_TotalDebt)+_xlfn.XLOOKUP(B$4,Years,Costco_OperatingLease))/_xlfn.XLOOKUP(B$4,Years,Costco_TotalEquity),"n/a") -> n/a | C43: =IFERROR((_xlfn.XLOOKUP(C$4,Years,Costco_TotalDebt)+_xlfn.XLOOKUP(C$4,Years,Costco_OperatingLease))/_xlfn.XLOOKUP(C$4,Years,Costco_TotalEquity),"n/a") -> n/a | D43: =IFERROR((_xlfn.XLOOKUP(D$4,Years,Costco_TotalDebt)+_xlfn.XLOOKUP(D$4,Years,Costco_OperatingLease))/_xlfn.XLOOKUP(D$4,Years,Costco_TotalEquity),"n/a") -> n/a | E43: =IFERROR((_xlfn.XLOOKUP(E$4,Years,Costco_TotalDebt)+_xlfn.XLOOKUP(E$4,Years,Costco_OperatingLease))/_xlfn.XLOOKUP(E$4,Years,Costco_TotalEquity),"n/a") -> n/a | F43: =IFERROR((_xlfn.XLOOKUP(F$4,Years,Costco_TotalDebt)+_xlfn.XLOOKUP(F$4,Years,Costco_OperatingLease))/_xlfn.XLOOKUP(F$4,Years,Costco_TotalEquity),"n/a") -> 0.59267576 | G43: =IFERROR((_xlfn.XLOOKUP(G$4,Years,Costco_TotalDebt)+_xlfn.XLOOKUP(G$4,Years,Costco_OperatingLease))/_xlfn.XLOOKUP(G$4,Years,Costco_TotalEquity),"n/a") -> 0.63098794 | H43: =IFERROR((_xlfn.XLOOKUP(H$4,Years,Costco_TotalDebt)+_xlfn.XLOOKUP(H$4,Years,Costco_OperatingLease))/_xlfn.XLOOKUP(H$4,Years,Costco_TotalEquity),"n/a") -> 0.52821233 | I43: =IFERROR((_xlfn.XLOOKUP(I$4,Years,Costco_TotalDebt)+_xlfn.XLOOKUP(I$4,Years,Costco_OperatingLease))/_xlfn.XLOOKUP(I$4,Years,Costco_TotalEquity),"n/a") -> 0.42046452 | ... K43: =IFERROR((_xlfn.XLOOKUP(K$4,Years,Costco_TotalDebt)+_xlfn.XLOOKUP(K$4,Years,Costco_OperatingLease))/_xlfn.XLOOKUP(K$4,Years,Costco_TotalEquity),"n/a") -> 0.34065972 | L43: =IFERROR(K43-B43,"n/a") -> n/a | M43: =IFERROR(I43-E43,"n/a") -> n/a | N43: =IFERROR((_xludf.XLOOKUP(K$4,Years,Costco_TotalDebt)+_xludf.XLOOKUP(K$4,Years,Costco_OperatingLease))/_xludf.XLOOKUP(K$4,Years,Costco_TotalEquity),"n/a") -> n/a
A44: Kroger | B44: =IFERROR((_xlfn.XLOOKUP(B$4,Years,Kroger_TotalDebt)+_xlfn.XLOOKUP(B$4,Years,Kroger_OperatingLease))/_xlfn.XLOOKUP(B$4,Years,Kroger_TotalEquity),"n/a") -> n/a | C44: =IFERROR((_xlfn.XLOOKUP(C$4,Years,Kroger_TotalDebt)+_xlfn.XLOOKUP(C$4,Years,Kroger_OperatingLease))/_xlfn.XLOOKUP(C$4,Years,Kroger_TotalEquity),"n/a") -> n/a | D44: =IFERROR((_xlfn.XLOOKUP(D$4,Years,Kroger_TotalDebt)+_xlfn.XLOOKUP(D$4,Years,Kroger_OperatingLease))/_xlfn.XLOOKUP(D$4,Years,Kroger_TotalEquity),"n/a") -> n/a | E44: =IFERROR((_xlfn.XLOOKUP(E$4,Years,Kroger_TotalDebt)+_xlfn.XLOOKUP(E$4,Years,Kroger_OperatingLease))/_xlfn.XLOOKUP(E$4,Years,Kroger_TotalEquity),"n/a") -> 2.4703138 | F44: =IFERROR((_xlfn.XLOOKUP(F$4,Years,Kroger_TotalDebt)+_xlfn.XLOOKUP(F$4,Years,Kroger_OperatingLease))/_xlfn.XLOOKUP(F$4,Years,Kroger_TotalEquity),"n/a") -> 2.1557068 | G44: =IFERROR((_xlfn.XLOOKUP(G$4,Years,Kroger_TotalDebt)+_xlfn.XLOOKUP(G$4,Years,Kroger_OperatingLease))/_xlfn.XLOOKUP(G$4,Years,Kroger_TotalEquity),"n/a") -> 2.1677803 | H44: =IFERROR((_xlfn.XLOOKUP(H$4,Years,Kroger_TotalDebt)+_xlfn.XLOOKUP(H$4,Years,Kroger_OperatingLease))/_xlfn.XLOOKUP(H$4,Years,Kroger_TotalEquity),"n/a") -> 2.0383463 | I44: =IFERROR((_xlfn.XLOOKUP(I$4,Years,Kroger_TotalDebt)+_xlfn.XLOOKUP(I$4,Years,Kroger_OperatingLease))/_xlfn.XLOOKUP(I$4,Years,Kroger_TotalEquity),"n/a") -> 1.6590811 | ... K44: =IFERROR((_xlfn.XLOOKUP(K$4,Years,Kroger_TotalDebt)+_xlfn.XLOOKUP(K$4,Years,Kroger_OperatingLease))/_xlfn.XLOOKUP(K$4,Years,Kroger_TotalEquity),"n/a") -> 4.1597035 | L44: =IFERROR(K44-B44,"n/a") -> n/a | M44: =IFERROR(I44-E44,"n/a") -> -0.81123266 | N44: =IFERROR((_xludf.XLOOKUP(K$4,Years,Kroger_TotalDebt)+_xludf.XLOOKUP(K$4,Years,Kroger_OperatingLease))/_xludf.XLOOKUP(K$4,Years,Kroger_TotalEquity),"n/a") -> n/a
A45: Sam's Club | B45: =IFERROR((_xlfn.XLOOKUP(B$4,Years,SamsClub_TotalDebt)+_xlfn.XLOOKUP(B$4,Years,SamsClub_OperatingLease))/_xlfn.XLOOKUP(B$4,Years,SamsClub_TotalEquity),"n/a") -> n/a | C45: =IFERROR((_xlfn.XLOOKUP(C$4,Years,SamsClub_TotalDebt)+_xlfn.XLOOKUP(C$4,Years,SamsClub_OperatingLease))/_xlfn.XLOOKUP(C$4,Years,SamsClub_TotalEquity),"n/a") -> n/a | D45: =IFERROR((_xlfn.XLOOKUP(D$4,Years,SamsClub_TotalDebt)+_xlfn.XLOOKUP(D$4,Years,SamsClub_OperatingLease))/_xlfn.XLOOKUP(D$4,Years,SamsClub_TotalEquity),"n/a") -> n/a | E45: =IFERROR((_xlfn.XLOOKUP(E$4,Years,SamsClub_TotalDebt)+_xlfn.XLOOKUP(E$4,Years,SamsClub_OperatingLease))/_xlfn.XLOOKUP(E$4,Years,SamsClub_TotalEquity),"n/a") -> n/a | F45: =IFERROR((_xlfn.XLOOKUP(F$4,Years,SamsClub_TotalDebt)+_xlfn.XLOOKUP(F$4,Years,SamsClub_OperatingLease))/_xlfn.XLOOKUP(F$4,Years,SamsClub_TotalEquity),"n/a") -> n/a | G45: =IFERROR((_xlfn.XLOOKUP(G$4,Years,SamsClub_TotalDebt)+_xlfn.XLOOKUP(G$4,Years,SamsClub_OperatingLease))/_xlfn.XLOOKUP(G$4,Years,SamsClub_TotalEquity),"n/a") -> n/a | H45: =IFERROR((_xlfn.XLOOKUP(H$4,Years,SamsClub_TotalDebt)+_xlfn.XLOOKUP(H$4,Years,SamsClub_OperatingLease))/_xlfn.XLOOKUP(H$4,Years,SamsClub_TotalEquity),"n/a") -> n/a | I45: =IFERROR((_xlfn.XLOOKUP(I$4,Years,SamsClub_TotalDebt)+_xlfn.XLOOKUP(I$4,Years,SamsClub_OperatingLease))/_xlfn.XLOOKUP(I$4,Years,SamsClub_TotalEquity),"n/a") -> n/a | ... K45: =IFERROR((_xlfn.XLOOKUP(K$4,Years,SamsClub_TotalDebt)+_xlfn.XLOOKUP(K$4,Years,SamsClub_OperatingLease))/_xlfn.XLOOKUP(K$4,Years,SamsClub_TotalEquity),"n/a") -> n/a | L45: =IFERROR(K45-B45,"n/a") -> n/a | M45: =IFERROR(I45-E45,"n/a") -> n/a | N45: =IFERROR((_xludf.XLOOKUP(K$4,Years,SamsClub_TotalDebt)+_xludf.XLOOKUP(K$4,Years,SamsClub_OperatingLease))/_xludf.XLOOKUP(K$4,Years,SamsClub_TotalEquity),"n/a") -> n/a
A46: Whole Foods | B46: =IFERROR((_xlfn.XLOOKUP(B$4,Years,WholeFoods_TotalDebt)+_xlfn.XLOOKUP(B$4,Years,WholeFoods_OperatingLease))/_xlfn.XLOOKUP(B$4,Years,WholeFoods_TotalEquity),"n/a") -> n/a | C46: =IFERROR((_xlfn.XLOOKUP(C$4,Years,WholeFoods_TotalDebt)+_xlfn.XLOOKUP(C$4,Years,WholeFoods_OperatingLease))/_xlfn.XLOOKUP(C$4,Years,WholeFoods_TotalEquity),"n/a") -> n/a | D46: =IFERROR((_xlfn.XLOOKUP(D$4,Years,WholeFoods_TotalDebt)+_xlfn.XLOOKUP(D$4,Years,WholeFoods_OperatingLease))/_xlfn.XLOOKUP(D$4,Years,WholeFoods_TotalEquity),"n/a") -> n/a | E46: =IFERROR((_xlfn.XLOOKUP(E$4,Years,WholeFoods_TotalDebt)+_xlfn.XLOOKUP(E$4,Years,WholeFoods_OperatingLease))/_xlfn.XLOOKUP(E$4,Years,WholeFoods_TotalEquity),"n/a") -> n/a | F46: =IFERROR((_xlfn.XLOOKUP(F$4,Years,WholeFoods_TotalDebt)+_xlfn.XLOOKUP(F$4,Years,WholeFoods_OperatingLease))/_xlfn.XLOOKUP(F$4,Years,WholeFoods_TotalEquity),"n/a") -> n/a | G46: =IFERROR((_xlfn.XLOOKUP(G$4,Years,WholeFoods_TotalDebt)+_xlfn.XLOOKUP(G$4,Years,WholeFoods_OperatingLease))/_xlfn.XLOOKUP(G$4,Years,WholeFoods_TotalEquity),"n/a") -> n/a | H46: =IFERROR((_xlfn.XLOOKUP(H$4,Years,WholeFoods_TotalDebt)+_xlfn.XLOOKUP(H$4,Years,WholeFoods_OperatingLease))/_xlfn.XLOOKUP(H$4,Years,WholeFoods_TotalEquity),"n/a") -> n/a | I46: =IFERROR((_xlfn.XLOOKUP(I$4,Years,WholeFoods_TotalDebt)+_xlfn.XLOOKUP(I$4,Years,WholeFoods_OperatingLease))/_xlfn.XLOOKUP(I$4,Years,WholeFoods_TotalEquity),"n/a") -> n/a | ... K46: =IFERROR((_xlfn.XLOOKUP(K$4,Years,WholeFoods_TotalDebt)+_xlfn.XLOOKUP(K$4,Years,WholeFoods_OperatingLease))/_xlfn.XLOOKUP(K$4,Years,WholeFoods_TotalEquity),"n/a") -> n/a | L46: =IFERROR(K46-B46,"n/a") -> n/a | M46: =IFERROR(I46-E46,"n/a") -> n/a | N46: =IFERROR((_xludf.XLOOKUP(K$4,Years,WholeFoods_TotalDebt)+_xludf.XLOOKUP(K$4,Years,WholeFoods_OperatingLease))/_xludf.XLOOKUP(K$4,Years,WholeFoods_TotalEquity),"n/a") -> n/a
A48: Revenue growth YoY — Revenue / prior-year revenue − 1 (FY2015 base year on Raw Data)
A49: Walmart | B49: =IFERROR(_xlfn.XLOOKUP(B$4,Years,Walmart_Revenue)/_xlfn.XLOOKUP(B$4-1,Years,Walmart_Revenue)-1,"n/a") -> 0.0056475573 | C49: =IFERROR(_xlfn.XLOOKUP(C$4,Years,Walmart_Revenue)/_xlfn.XLOOKUP(C$4-1,Years,Walmart_Revenue)-1,"n/a") -> 0.030009329 | D49: =IFERROR(_xlfn.XLOOKUP(D$4,Years,Walmart_Revenue)/_xlfn.XLOOKUP(D$4-1,Years,Walmart_Revenue)-1,"n/a") -> 0.029385127 | E49: =IFERROR(_xlfn.XLOOKUP(E$4,Years,Walmart_Revenue)/_xlfn.XLOOKUP(E$4-1,Years,Walmart_Revenue)-1,"n/a") -> 0.018805516 | F49: =IFERROR(_xlfn.XLOOKUP(F$4,Years,Walmart_Revenue)/_xlfn.XLOOKUP(F$4-1,Years,Walmart_Revenue)-1,"n/a") -> 0.067907741 | G49: =IFERROR(_xlfn.XLOOKUP(G$4,Years,Walmart_Revenue)/_xlfn.XLOOKUP(G$4-1,Years,Walmart_Revenue)-1,"n/a") -> 0.022565301 | H49: =IFERROR(_xlfn.XLOOKUP(H$4,Years,Walmart_Revenue)/_xlfn.XLOOKUP(H$4-1,Years,Walmart_Revenue)-1,"n/a") -> 0.067139048 | I49: =IFERROR(_xlfn.XLOOKUP(I$4,Years,Walmart_Revenue)/_xlfn.XLOOKUP(I$4-1,Years,Walmart_Revenue)-1,"n/a") -> 0.060665378 | ... K49: =IFERROR(_xlfn.XLOOKUP(K$4,Years,Walmart_Revenue)/_xlfn.XLOOKUP(K$4-1,Years,Walmart_Revenue)-1,"n/a") -> 0.047254565 | L49: =IFERROR(K49-B49,"n/a") -> 0.041607008 | M49: =IFERROR(I49-E49,"n/a") -> 0.041859863 | N49: =IFERROR(_xludf.XLOOKUP(K$4,Years,Walmart_Revenue)/_xludf.XLOOKUP(K$4-1,Years,Walmart_Revenue)-1,"n/a") -> n/a
A50: Costco | B50: =IFERROR(_xlfn.XLOOKUP(B$4,Years,Costco_Revenue)/_xlfn.XLOOKUP(B$4-1,Years,Costco_Revenue)-1,"n/a") -> 0.021176077 | C50: =IFERROR(_xlfn.XLOOKUP(C$4,Years,Costco_Revenue)/_xlfn.XLOOKUP(C$4-1,Years,Costco_Revenue)-1,"n/a") -> 0.087005591 | D50: =IFERROR(_xlfn.XLOOKUP(D$4,Years,Costco_Revenue)/_xlfn.XLOOKUP(D$4-1,Years,Costco_Revenue)-1,"n/a") -> 0.097184795 | E50: =IFERROR(_xlfn.XLOOKUP(E$4,Years,Costco_Revenue)/_xlfn.XLOOKUP(E$4-1,Years,Costco_Revenue)-1,"n/a") -> 0.078860685 | F50: =IFERROR(_xlfn.XLOOKUP(F$4,Years,Costco_Revenue)/_xlfn.XLOOKUP(F$4-1,Years,Costco_Revenue)-1,"n/a") -> 0.092861782 | G50: =IFERROR(_xlfn.XLOOKUP(G$4,Years,Costco_Revenue)/_xlfn.XLOOKUP(G$4-1,Years,Costco_Revenue)-1,"n/a") -> 0.17664502 | H50: =IFERROR(_xlfn.XLOOKUP(H$4,Years,Costco_Revenue)/_xlfn.XLOOKUP(H$4-1,Years,Costco_Revenue)-1,"n/a") -> 0.15973799 | I50: =IFERROR(_xlfn.XLOOKUP(I$4,Years,Costco_Revenue)/_xlfn.XLOOKUP(I$4-1,Years,Costco_Revenue)-1,"n/a") -> 0.067256319 | ... K50: =IFERROR(_xlfn.XLOOKUP(K$4,Years,Costco_Revenue)/_xlfn.XLOOKUP(K$4-1,Years,Costco_Revenue)-1,"n/a") -> 0.081269905 | L50: =IFERROR(K50-B50,"n/a") -> 0.060093828 | M50: =IFERROR(I50-E50,"n/a") -> -0.011604365 | N50: =IFERROR(_xludf.XLOOKUP(K$4,Years,Costco_Revenue)/_xludf.XLOOKUP(K$4-1,Years,Costco_Revenue)-1,"n/a") -> n/a
A51: Kroger | B51: =IFERROR(_xlfn.XLOOKUP(B$4,Years,Kroger_Revenue)/_xlfn.XLOOKUP(B$4-1,Years,Kroger_Revenue)-1,"n/a") -> 0.050141127 | C51: =IFERROR(_xlfn.XLOOKUP(C$4,Years,Kroger_Revenue)/_xlfn.XLOOKUP(C$4-1,Years,Kroger_Revenue)-1,"n/a") -> 0.068867753 | D51: =IFERROR(_xlfn.XLOOKUP(D$4,Years,Kroger_Revenue)/_xlfn.XLOOKUP(D$4-1,Years,Kroger_Revenue)-1,"n/a") -> -0.011583387 | E51: =IFERROR(_xlfn.XLOOKUP(E$4,Years,Kroger_Revenue)/_xlfn.XLOOKUP(E$4-1,Years,Kroger_Revenue)-1,"n/a") -> 0.0035616978 | F51: =IFERROR(_xlfn.XLOOKUP(F$4,Years,Kroger_Revenue)/_xlfn.XLOOKUP(F$4-1,Years,Kroger_Revenue)-1,"n/a") -> 0.083509151 | G51: =IFERROR(_xlfn.XLOOKUP(G$4,Years,Kroger_Revenue)/_xlfn.XLOOKUP(G$4-1,Years,Kroger_Revenue)-1,"n/a") -> 0.040679859 | H51: =IFERROR(_xlfn.XLOOKUP(H$4,Years,Kroger_Revenue)/_xlfn.XLOOKUP(H$4-1,Years,Kroger_Revenue)-1,"n/a") -> 0.075205964 | I51: =IFERROR(_xlfn.XLOOKUP(I$4,Years,Kroger_Revenue)/_xlfn.XLOOKUP(I$4-1,Years,Kroger_Revenue)-1,"n/a") -> 0.012012842 | ... K51: =IFERROR(_xlfn.XLOOKUP(K$4,Years,Kroger_Revenue)/_xlfn.XLOOKUP(K$4-1,Years,Kroger_Revenue)-1,"n/a") -> 0.0035276605 | L51: =IFERROR(K51-B51,"n/a") -> -0.046613467 | M51: =IFERROR(I51-E51,"n/a") -> 0.0084511447 | N51: =IFERROR(_xludf.XLOOKUP(K$4,Years,Kroger_Revenue)/_xludf.XLOOKUP(K$4-1,Years,Kroger_Revenue)-1,"n/a") -> n/a
A52: Sam's Club | B52: =IFERROR(_xlfn.XLOOKUP(B$4,Years,SamsClub_Revenue)/_xlfn.XLOOKUP(B$4-1,Years,SamsClub_Revenue)-1,"n/a") -> 0.0094495671 | C52: =IFERROR(_xlfn.XLOOKUP(C$4,Years,SamsClub_Revenue)/_xlfn.XLOOKUP(C$4-1,Years,SamsClub_Revenue)-1,"n/a") -> 0.032267062 | D52: =IFERROR(_xlfn.XLOOKUP(D$4,Years,SamsClub_Revenue)/_xlfn.XLOOKUP(D$4-1,Years,SamsClub_Revenue)-1,"n/a") -> -0.02325385 | E52: =IFERROR(_xlfn.XLOOKUP(E$4,Years,SamsClub_Revenue)/_xlfn.XLOOKUP(E$4-1,Years,SamsClub_Revenue)-1,"n/a") -> 0.016476772 | F52: =IFERROR(_xlfn.XLOOKUP(F$4,Years,SamsClub_Revenue)/_xlfn.XLOOKUP(F$4-1,Years,SamsClub_Revenue)-1,"n/a") -> 0.08705266 | G52: =IFERROR(_xlfn.XLOOKUP(G$4,Years,SamsClub_Revenue)/_xlfn.XLOOKUP(G$4-1,Years,SamsClub_Revenue)-1,"n/a") -> 0.150931 | H52: =IFERROR(_xlfn.XLOOKUP(H$4,Years,SamsClub_Revenue)/_xlfn.XLOOKUP(H$4-1,Years,SamsClub_Revenue)-1,"n/a") -> 0.14667736 | I52: =IFERROR(_xlfn.XLOOKUP(I$4,Years,SamsClub_Revenue)/_xlfn.XLOOKUP(I$4-1,Years,SamsClub_Revenue)-1,"n/a") -> 0.021744028 | ... K52: =IFERROR(_xlfn.XLOOKUP(K$4,Years,SamsClub_Revenue)/_xlfn.XLOOKUP(K$4-1,Years,SamsClub_Revenue)-1,"n/a") -> 0.030774175 | L52: =IFERROR(K52-B52,"n/a") -> 0.021324608 | M52: =IFERROR(I52-E52,"n/a") -> 0.0052672558 | N52: =IFERROR(_xludf.XLOOKUP(K$4,Years,SamsClub_Revenue)/_xludf.XLOOKUP(K$4-1,Years,SamsClub_Revenue)-1,"n/a") -> n/a
A53: Whole Foods | B53: =IFERROR(_xlfn.XLOOKUP(B$4,Years,WholeFoods_Revenue)/_xlfn.XLOOKUP(B$4-1,Years,WholeFoods_Revenue)-1,"n/a") -> 0.021768796 | C53: =IFERROR(_xlfn.XLOOKUP(C$4,Years,WholeFoods_Revenue)/_xlfn.XLOOKUP(C$4-1,Years,WholeFoods_Revenue)-1,"n/a") -> 0.019460697 | D53: =IFERROR(_xlfn.XLOOKUP(D$4,Years,WholeFoods_Revenue)/_xlfn.XLOOKUP(D$4-1,Years,WholeFoods_Revenue)-1,"n/a") -> n/a | E53: =IFERROR(_xlfn.XLOOKUP(E$4,Years,WholeFoods_Revenue)/_xlfn.XLOOKUP(E$4-1,Years,WholeFoods_Revenue)-1,"n/a") -> n/a | F53: =IFERROR(_xlfn.XLOOKUP(F$4,Years,WholeFoods_Revenue)/_xlfn.XLOOKUP(F$4-1,Years,WholeFoods_Revenue)-1,"n/a") -> n/a | G53: =IFERROR(_xlfn.XLOOKUP(G$4,Years,WholeFoods_Revenue)/_xlfn.XLOOKUP(G$4-1,Years,WholeFoods_Revenue)-1,"n/a") -> n/a | H53: =IFERROR(_xlfn.XLOOKUP(H$4,Years,WholeFoods_Revenue)/_xlfn.XLOOKUP(H$4-1,Years,WholeFoods_Revenue)-1,"n/a") -> n/a | I53: =IFERROR(_xlfn.XLOOKUP(I$4,Years,WholeFoods_Revenue)/_xlfn.XLOOKUP(I$4-1,Years,WholeFoods_Revenue)-1,"n/a") -> n/a | ... K53: =IFERROR(_xlfn.XLOOKUP(K$4,Years,WholeFoods_Revenue)/_xlfn.XLOOKUP(K$4-1,Years,WholeFoods_Revenue)-1,"n/a") -> n/a | L53: =IFERROR(K53-B53,"n/a") -> n/a | M53: =IFERROR(I53-E53,"n/a") -> n/a | N53: =IFERROR(_xludf.XLOOKUP(K$4,Years,WholeFoods_Revenue)/_xludf.XLOOKUP(K$4-1,Years,WholeFoods_Revenue)-1,"n/a") -> n/a
A54: Whole Foods (Amazon 'Physical stores', successor) | B54: =IFERROR(_xlfn.XLOOKUP(B$4,Years,WholeFoods_SuccessorRevenue)/_xlfn.XLOOKUP(B$4-1,Years,WholeFoods_SuccessorRevenue)-1,"n/a") -> n/a | C54: =IFERROR(_xlfn.XLOOKUP(C$4,Years,WholeFoods_SuccessorRevenue)/_xlfn.XLOOKUP(C$4-1,Years,WholeFoods_SuccessorRevenue)-1,"n/a") -> n/a | D54: =IFERROR(_xlfn.XLOOKUP(D$4,Years,WholeFoods_SuccessorRevenue)/_xlfn.XLOOKUP(D$4-1,Years,WholeFoods_SuccessorRevenue)-1,"n/a") -> n/a | E54: =IFERROR(_xlfn.XLOOKUP(E$4,Years,WholeFoods_SuccessorRevenue)/_xlfn.XLOOKUP(E$4-1,Years,WholeFoods_SuccessorRevenue)-1,"n/a") -> -0.0018578727 | F54: =IFERROR(_xlfn.XLOOKUP(F$4,Years,WholeFoods_SuccessorRevenue)/_xlfn.XLOOKUP(F$4-1,Years,WholeFoods_SuccessorRevenue)-1,"n/a") -> -0.056130758 | G54: =IFERROR(_xlfn.XLOOKUP(G$4,Years,WholeFoods_SuccessorRevenue)/_xlfn.XLOOKUP(G$4-1,Years,WholeFoods_SuccessorRevenue)-1,"n/a") -> 0.052258581 | H54: =IFERROR(_xlfn.XLOOKUP(H$4,Years,WholeFoods_SuccessorRevenue)/_xlfn.XLOOKUP(H$4-1,Years,WholeFoods_SuccessorRevenue)-1,"n/a") -> 0.11057101 | I54: =IFERROR(_xlfn.XLOOKUP(I$4,Years,WholeFoods_SuccessorRevenue)/_xlfn.XLOOKUP(I$4-1,Years,WholeFoods_SuccessorRevenue)-1,"n/a") -> 0.056267468 | ... K54: =IFERROR(_xlfn.XLOOKUP(K$4,Years,WholeFoods_SuccessorRevenue)/_xlfn.XLOOKUP(K$4-1,Years,WholeFoods_SuccessorRevenue)-1,"n/a") -> 0.063445675 | L54: =IFERROR(K54-B54,"n/a") -> n/a | M54: =IFERROR(I54-E54,"n/a") -> 0.058125341 | N54: =IFERROR(_xludf.XLOOKUP(K$4,Years,WholeFoods_SuccessorRevenue)/_xludf.XLOOKUP(K$4-1,Years,WholeFoods_SuccessorRevenue)-1,"n/a") -> n/a
A56: Sam's Club: no balance sheet or net income at segment level, so current ratio, debt-to-equity and net margin are n/a by construction. Whole Foods: standalone data ends FY2017; the successor growth row uses Amazon's 'Physical stores' line (mostly, not only, Whole Foods).

Sheet Scorecard
A1: 05 — SCORECARD | J1: COMPETITOR SCORECARD · FY2016–FY2025 · SEC 10-K DATA
A2: Scorecard | J2: Direction-aware ranks and colour scales (green = strongest) · change the year to re-rank
A3: Scorecard year (input) | B3: 2025 | C3: ← any year FY2016–FY2025
A5: Metric | B5: Better is | C5: Walmart | D5: Costco | E5: Kroger | F5: Sam's Club | G5: Whole Foods | H5: Leader | I5: Laggard | J5: Takeaway
A6: Gross profit margin | B6: Higher | C6: =IFERROR(_xlfn.XLOOKUP(ScorecardYear,RatioYears,GM_Walmart),"n/a") -> 0.24209351 | D6: =IFERROR(_xlfn.XLOOKUP(ScorecardYear,RatioYears,GM_Costco),"n/a") -> 0.11124366 | E6: =IFERROR(_xlfn.XLOOKUP(ScorecardYear,RatioYears,GM_Kroger),"n/a") -> 0.23300958 | F6: =IFERROR(_xlfn.XLOOKUP(ScorecardYear,RatioYears,GM_SamsClub),"n/a") -> 0.11348707 | G6: =IFERROR(_xlfn.XLOOKUP(ScorecardYear,RatioYears,GM_WholeFoods),"n/a") -> n/a | H6: =IFERROR(INDEX($C$5:$G$5,MATCH(MAX(C6:G6),C6:G6,0)),"n/a") -> Walmart | I6: =IFERROR(INDEX($C$5:$G$5,MATCH(MIN(C6:G6),C6:G6,0)),"n/a") -> Costco | J6: ="FY"&ScorecardYear&": "&H6&" leads at "&TEXT(MAX(C6:G6),"0.0%")&", "&I6&" trails at "&TEXT(MIN(C6:G6),"0.0%")&". Level reflects business model, not execution: warehouse clubs (Costco, Sam's Club) run 10–12% on net sales, supercenters and supermarkets 22–25%. Compare each company's trend on the Trend tab, not levels across models." -> FY2025: Walmart leads at 24.2%, Costco trails at 11.1%. Level reflects business model, not execution: warehouse clubs (Costco, Sam's Club) run 10–12% on net sales, supercenters and supermarkets 22–25%. Compare each company's trend on the Trend tab, not levels across models.
A7: rank (of companies with data) | C7: =IFERROR("#"&_xlfn.RANK.EQ(C6,C6:G6,0)&" of "&COUNT(C6:G6),"–") -> #1 of 4 | D7: =IFERROR("#"&_xlfn.RANK.EQ(D6,C6:G6,0)&" of "&COUNT(C6:G6),"–") -> #4 of 4 | E7: =IFERROR("#"&_xlfn.RANK.EQ(E6,C6:G6,0)&" of "&COUNT(C6:G6),"–") -> #2 of 4 | F7: =IFERROR("#"&_xlfn.RANK.EQ(F6,C6:G6,0)&" of "&COUNT(C6:G6),"–") -> #3 of 4 | G7: =IFERROR("#"&_xlfn.RANK.EQ(G6,C6:G6,0)&" of "&COUNT(C6:G6),"–") -> –
A8: Operating margin | B8: Higher | C8: =IFERROR(_xlfn.XLOOKUP(ScorecardYear,RatioYears,OM_Walmart),"n/a") -> 0.042220344 | D8: =IFERROR(_xlfn.XLOOKUP(ScorecardYear,RatioYears,OM_Costco),"n/a") -> 0.038468093 | E8: =IFERROR(_xlfn.XLOOKUP(ScorecardYear,RatioYears,OM_Kroger),"n/a") -> 0.012801235 | F8: =IFERROR(_xlfn.XLOOKUP(ScorecardYear,RatioYears,OM_SamsClub),"n/a") -> 0.02625383 | G8: =IFERROR(_xlfn.XLOOKUP(ScorecardYear,RatioYears,OM_WholeFoods),"n/a") -> n/a | H8: =IFERROR(INDEX($C$5:$G$5,MATCH(MAX(C8:G8),C8:G8,0)),"n/a") -> Walmart | I8: =IFERROR(INDEX($C$5:$G$5,MATCH(MIN(C8:G8),C8:G8,0)),"n/a") -> Kroger | J8: ="FY"&ScorecardYear&": "&H8&" leads at "&TEXT(MAX(C8:G8),"0.0%")&", "&I8&" trails at "&TEXT(MIN(C8:G8),"0.0%")&". Operating margin isolates cost discipline below gross profit. Costco's has risen steadily; Kroger's FY2025 figure carries $2.7B of restructuring and impairment charges." -> FY2025: Walmart leads at 4.2%, Kroger trails at 1.3%. Operating margin isolates cost discipline below gross profit. Costco's has risen steadily; Kroger's FY2025 figure carries $2.7B of restructuring and impairment charges.
A9: rank (of companies with data) | C9: =IFERROR("#"&_xlfn.RANK.EQ(C8,C8:G8,0)&" of "&COUNT(C8:G8),"–") -> #1 of 4 | D9: =IFERROR("#"&_xlfn.RANK.EQ(D8,C8:G8,0)&" of "&COUNT(C8:G8),"–") -> #2 of 4 | E9: =IFERROR("#"&_xlfn.RANK.EQ(E8,C8:G8,0)&" of "&COUNT(C8:G8),"–") -> #4 of 4 | F9: =IFERROR("#"&_xlfn.RANK.EQ(F8,C8:G8,0)&" of "&COUNT(C8:G8),"–") -> #3 of 4 | G9: =IFERROR("#"&_xlfn.RANK.EQ(G8,C8:G8,0)&" of "&COUNT(C8:G8),"–") -> –
A10: Net profit margin | B10: Higher | C10: =IFERROR(_xlfn.XLOOKUP(ScorecardYear,RatioYears,NM_Walmart),"n/a") -> 0.030991785 | D10: =IFERROR(_xlfn.XLOOKUP(ScorecardYear,RatioYears,NM_Costco),"n/a") -> 0.030006076 | E10: =IFERROR(_xlfn.XLOOKUP(ScorecardYear,RatioYears,NM_Kroger),"n/a") -> 0.0068815107 | F10: =IFERROR(_xlfn.XLOOKUP(ScorecardYear,RatioYears,NM_SamsClub),"n/a") -> n/a | G10: =IFERROR(_xlfn.XLOOKUP(ScorecardYear,RatioYears,NM_WholeFoods),"n/a") -> n/a | H10: =IFERROR(INDEX($C$5:$G$5,MATCH(MAX(C10:G10),C10:G10,0)),"n/a") -> Walmart | I10: =IFERROR(INDEX($C$5:$G$5,MATCH(MIN(C10:G10),C10:G10,0)),"n/a") -> Kroger | J10: ="FY"&ScorecardYear&": "&H10&" leads at "&TEXT(MAX(C10:G10),"0.0%")&", "&I10&" trails at "&TEXT(MIN(C10:G10),"0.0%")&". The cleanest cross-model comparison. Costco converts the thinnest gross margin into the highest net margin through membership fees and SG&A control." -> FY2025: Walmart leads at 3.1%, Kroger trails at 0.7%. The cleanest cross-model comparison. Costco converts the thinnest gross margin into the highest net margin through membership fees and SG&A control.
A11: rank (of companies with data) | C11: =IFERROR("#"&_xlfn.RANK.EQ(C10,C10:G10,0)&" of "&COUNT(C10:G10),"–") -> #1 of 3 | D11: =IFERROR("#"&_xlfn.RANK.EQ(D10,C10:G10,0)&" of "&COUNT(C10:G10),"–") -> #2 of 3 | E11: =IFERROR("#"&_xlfn.RANK.EQ(E10,C10:G10,0)&" of "&COUNT(C10:G10),"–") -> #3 of 3 | F11: =IFERROR("#"&_xlfn.RANK.EQ(F10,C10:G10,0)&" of "&COUNT(C10:G10),"–") -> – | G11: =IFERROR("#"&_xlfn.RANK.EQ(G10,C10:G10,0)&" of "&COUNT(C10:G10),"–") -> –
A12: Current ratio | B12: Higher | C12: =IFERROR(_xlfn.XLOOKUP(ScorecardYear,RatioYears,CR_Walmart),"n/a") -> 0.78975332 | D12: =IFERROR(_xlfn.XLOOKUP(ScorecardYear,RatioYears,CR_Costco),"n/a") -> 1.0342783 | E12: =IFERROR(_xlfn.XLOOKUP(ScorecardYear,RatioYears,CR_Kroger),"n/a") -> 0.80102717 | F12: =IFERROR(_xlfn.XLOOKUP(ScorecardYear,RatioYears,CR_SamsClub),"n/a") -> n/a | G12: =IFERROR(_xlfn.XLOOKUP(ScorecardYear,RatioYears,CR_WholeFoods),"n/a") -> n/a | H12: =IFERROR(INDEX($C$5:$G$5,MATCH(MAX(C12:G12),C12:G12,0)),"n/a") -> Costco | I12: =IFERROR(INDEX($C$5:$G$5,MATCH(MIN(C12:G12),C12:G12,0)),"n/a") -> Walmart | J12: ="FY"&ScorecardYear&": "&H12&" leads at "&TEXT(MAX(C12:G12),"0.00")&"x"&", "&I12&" trails at "&TEXT(MIN(C12:G12),"0.00")&"x"&". Grocers and clubs run near or below 1.0x by design – inventory turns faster than suppliers are paid. A ratio above 1.0x is rare in this set and is Costco's alone." -> FY2025: Costco leads at 1.03x, Walmart trails at 0.79x. Grocers and clubs run near or below 1.0x by design – inventory turns faster than suppliers are paid. A ratio above 1.0x is rare in this set and is Costco's alone.
A13: rank (of companies with data) | C13: =IFERROR("#"&_xlfn.RANK.EQ(C12,C12:G12,0)&" of "&COUNT(C12:G12),"–") -> #3 of 3 | D13: =IFERROR("#"&_xlfn.RANK.EQ(D12,C12:G12,0)&" of "&COUNT(C12:G12),"–") -> #1 of 3 | E13: =IFERROR("#"&_xlfn.RANK.EQ(E12,C12:G12,0)&" of "&COUNT(C12:G12),"–") -> #2 of 3 | F13: =IFERROR("#"&_xlfn.RANK.EQ(F12,C12:G12,0)&" of "&COUNT(C12:G12),"–") -> – | G13: =IFERROR("#"&_xlfn.RANK.EQ(G12,C12:G12,0)&" of "&COUNT(C12:G12),"–") -> –
A14: Debt-to-equity | B14: Lower | C14: =IFERROR(_xlfn.XLOOKUP(ScorecardYear,RatioYears,DE_Walmart),"n/a") -> 0.48658476 | D14: =IFERROR(_xlfn.XLOOKUP(ScorecardYear,RatioYears,DE_Costco),"n/a") -> 0.24917707 | E14: =IFERROR(_xlfn.XLOOKUP(ScorecardYear,RatioYears,DE_Kroger),"n/a") -> 2.9592318 | F14: =IFERROR(_xlfn.XLOOKUP(ScorecardYear,RatioYears,DE_SamsClub),"n/a") -> n/a | G14: =IFERROR(_xlfn.XLOOKUP(ScorecardYear,RatioYears,DE_WholeFoods),"n/a") -> n/a | H14: =IFERROR(INDEX($C$5:$G$5,MATCH(MIN(C14:G14),C14:G14,0)),"n/a") -> Costco | I14: =IFERROR(INDEX($C$5:$G$5,MATCH(MAX(C14:G14),C14:G14,0)),"n/a") -> Kroger | J14: ="FY"&ScorecardYear&": "&H14&" leads at "&TEXT(MIN(C14:G14),"0.00")&"x"&", "&I14&" trails at "&TEXT(MAX(C14:G14),"0.00")&"x"&". Kroger's debt-to-equity is a multiple of its peers' after the FY2024 $10.5B debt issue and $6.9B of FY2024–25 buybacks; Costco has de-levered every year since FY2021." -> FY2025: Costco leads at 0.25x, Kroger trails at 2.96x. Kroger's debt-to-equity is a multiple of its peers' after the FY2024 $10.5B debt issue and $6.9B of FY2024–25 buybacks; Costco has de-levered every year since FY2021.
A15: rank (of companies with data) | C15: =IFERROR("#"&_xlfn.RANK.EQ(C14,C14:G14,1)&" of "&COUNT(C14:G14),"–") -> #2 of 3 | D15: =IFERROR("#"&_xlfn.RANK.EQ(D14,C14:G14,1)&" of "&COUNT(C14:G14),"–") -> #1 of 3 | E15: =IFERROR("#"&_xlfn.RANK.EQ(E14,C14:G14,1)&" of "&COUNT(C14:G14),"–") -> #3 of 3 | F15: =IFERROR("#"&_xlfn.RANK.EQ(F14,C14:G14,1)&" of "&COUNT(C14:G14),"–") -> – | G15: =IFERROR("#"&_xlfn.RANK.EQ(G14,C14:G14,1)&" of "&COUNT(C14:G14),"–") -> –
A16: Revenue growth YoY | B16: Higher | C16: =IFERROR(_xlfn.XLOOKUP(ScorecardYear,RatioYears,GR_Walmart),"n/a") -> 0.047254565 | D16: =IFERROR(_xlfn.XLOOKUP(ScorecardYear,RatioYears,GR_Costco),"n/a") -> 0.081269905 | E16: =IFERROR(_xlfn.XLOOKUP(ScorecardYear,RatioYears,GR_Kroger),"n/a") -> 0.0035276605 | F16: =IFERROR(_xlfn.XLOOKUP(ScorecardYear,RatioYears,GR_SamsClub),"n/a") -> 0.030774175 | G16: =IFERROR(_xlfn.XLOOKUP(ScorecardYear,RatioYears,GR_WholeFoods),"n/a") -> n/a | H16: =IFERROR(INDEX($C$5:$G$5,MATCH(MAX(C16:G16),C16:G16,0)),"n/a") -> Costco | I16: =IFERROR(INDEX($C$5:$G$5,MATCH(MIN(C16:G16),C16:G16,0)),"n/a") -> Kroger | J16: ="FY"&ScorecardYear&": "&H16&" leads at "&TEXT(MAX(C16:G16),"0.0%")&", "&I16&" trails at "&TEXT(MIN(C16:G16),"0.0%")&". Costco has led growth in nearly every year of the window; Kroger's revenue has been flat to down since FY2022." -> FY2025: Costco leads at 8.1%, Kroger trails at 0.4%. Costco has led growth in nearly every year of the window; Kroger's revenue has been flat to down since FY2022.
A17: rank (of companies with data) | C17: =IFERROR("#"&_xlfn.RANK.EQ(C16,C16:G16,0)&" of "&COUNT(C16:G16),"–") -> #2 of 4 | D17: =IFERROR("#"&_xlfn.RANK.EQ(D16,C16:G16,0)&" of "&COUNT(C16:G16),"–") -> #1 of 4 | E17: =IFERROR("#"&_xlfn.RANK.EQ(E16,C16:G16,0)&" of "&COUNT(C16:G16),"–") -> #4 of 4 | F17: =IFERROR("#"&_xlfn.RANK.EQ(F16,C16:G16,0)&" of "&COUNT(C16:G16),"–") -> #3 of 4 | G17: =IFERROR("#"&_xlfn.RANK.EQ(G16,C16:G16,0)&" of "&COUNT(C16:G16),"–") -> –
A19: Composite rank (average of five core ranks) | B19: Lower | C19: =IFERROR(AVERAGE(IFERROR(_xlfn.RANK.EQ(C6,C6:G6,0),""),IFERROR(_xlfn.RANK.EQ(C10,C10:G10,0),""),IFERROR(_xlfn.RANK.EQ(C12,C12:G12,0),""),IFERROR(_xlfn.RANK.EQ(C14,C14:G14,1),""),IFERROR(_xlfn.RANK.EQ(C16,C16:G16,0),"")),"n/a") -> 1.8 | D19: =IFERROR(AVERAGE(IFERROR(_xlfn.RANK.EQ(D6,C6:G6,0),""),IFERROR(_xlfn.RANK.EQ(D10,C10:G10,0),""),IFERROR(_xlfn.RANK.EQ(D12,C12:G12,0),""),IFERROR(_xlfn.RANK.EQ(D14,C14:G14,1),""),IFERROR(_xlfn.RANK.EQ(D16,C16:G16,0),"")),"n/a") -> 1.8 | E19: =IFERROR(AVERAGE(IFERROR(_xlfn.RANK.EQ(E6,C6:G6,0),""),IFERROR(_xlfn.RANK.EQ(E10,C10:G10,0),""),IFERROR(_xlfn.RANK.EQ(E12,C12:G12,0),""),IFERROR(_xlfn.RANK.EQ(E14,C14:G14,1),""),IFERROR(_xlfn.RANK.EQ(E16,C16:G16,0),"")),"n/a") -> 2.8 | F19: =IFERROR(AVERAGE(IFERROR(_xlfn.RANK.EQ(F6,C6:G6,0),""),IFERROR(_xlfn.RANK.EQ(F10,C10:G10,0),""),IFERROR(_xlfn.RANK.EQ(F12,C12:G12,0),""),IFERROR(_xlfn.RANK.EQ(F14,C14:G14,1),""),IFERROR(_xlfn.RANK.EQ(F16,C16:G16,0),"")),"n/a") -> n/a | G19: =IFERROR(AVERAGE(IFERROR(_xlfn.RANK.EQ(G6,C6:G6,0),""),IFERROR(_xlfn.RANK.EQ(G10,C10:G10,0),""),IFERROR(_xlfn.RANK.EQ(G12,C12:G12,0),""),IFERROR(_xlfn.RANK.EQ(G14,C14:G14,1),""),IFERROR(_xlfn.RANK.EQ(G16,C16:G16,0),"")),"n/a") -> n/a | H19: =IFERROR(INDEX($C$5:$G$5,MATCH(MIN(C19:G19),C19:G19,0)),"n/a") -> Walmart | I19: =IFERROR(INDEX($C$5:$G$5,MATCH(MAX(C19:G19),C19:G19,0)),"n/a") -> Kroger | J19: Computed only for the three full filers, which have all five core metrics. Sam's Club and Whole Foods lack the balance-sheet metrics and are not ranked.
A21: Sam's Club: net margin, current ratio and debt-to-equity are n/a (segment reporting). Whole Foods: n/a after FY2017 (acquired). Operating margin is supplementary and excluded from the composite.

Sheet Trend
A1: 06 — TREND | T1: COMPETITOR SCORECARD · FY2016–FY2025 · SEC 10-K DATA
A2: Trend
A3: FY2016–FY2025. Shaded band = FY2020–FY2023 (COVID-19 and the inflation spike). Gaps = data not available (Sam's Club balance sheet, Whole Foods after FY2017); charts read the helper block via NA() so missing years are skipped, never plotted as zero.
A69: Chart helper block (formulas; do not edit): =IF(ISNUMBER(ratio), ratio, NA()) — one row per series, plus the shaded-window series
A70: Series | B70: FY2016 | C70: FY2017 | D70: FY2018 | E70: FY2019 | F70: FY2020 | G70: FY2021 | H70: FY2022 | I70: FY2023 | J70: FY2024 | K70: FY2025
A71: Walmart | B71: =IF(ISNUMBER('Ratio Calculations'!B7),'Ratio Calculations'!B7,NA()) -> 0.24944267 | C71: =IF(ISNUMBER('Ratio Calculations'!C7),'Ratio Calculations'!C7,NA()) -> 0.24682256 | D71: =IF(ISNUMBER('Ratio Calculations'!D7),'Ratio Calculations'!D7,NA()) -> 0.2449949 | E71: =IF(ISNUMBER('Ratio Calculations'!E7),'Ratio Calculations'!E7,NA()) -> 0.24103622 | F71: =IF(ISNUMBER('Ratio Calculations'!F7),'Ratio Calculations'!F7,NA()) -> 0.24299348 | G71: =IF(ISNUMBER('Ratio Calculations'!G7),'Ratio Calculations'!G7,NA()) -> 0.2444017 | H71: =IF(ISNUMBER('Ratio Calculations'!H7),'Ratio Calculations'!H7,NA()) -> 0.23463353 | I71: =IF(ISNUMBER('Ratio Calculations'!I7),'Ratio Calculations'!I7,NA()) -> 0.23729571 | ... K71: =IF(ISNUMBER('Ratio Calculations'!K7),'Ratio Calculations'!K7,NA()) -> 0.24209351
A72: Costco | B72: =IF(ISNUMBER('Ratio Calculations'!B8),'Ratio Calculations'!B8,NA()) -> 0.11348031 | C72: =IF(ISNUMBER('Ratio Calculations'!C8),'Ratio Calculations'!C8,NA()) -> 0.11325809 | D72: =IF(ISNUMBER('Ratio Calculations'!D8),'Ratio Calculations'!D8,NA()) -> 0.11039196 | E72: =IF(ISNUMBER('Ratio Calculations'!E8),'Ratio Calculations'!E8,NA()) -> 0.11024365 | F72: =IF(ISNUMBER('Ratio Calculations'!F8),'Ratio Calculations'!F8,NA()) -> 0.11200221 | G72: =IF(ISNUMBER('Ratio Calculations'!G8),'Ratio Calculations'!G8,NA()) -> 0.11126153 | H72: =IF(ISNUMBER('Ratio Calculations'!H8),'Ratio Calculations'!H8,NA()) -> 0.10482647 | I72: =IF(ISNUMBER('Ratio Calculations'!I8),'Ratio Calculations'!I8,NA()) -> 0.10569181 | ... K72: =IF(ISNUMBER('Ratio Calculations'!K8),'Ratio Calculations'!K8,NA()) -> 0.11124366
A73: Kroger | B73: =IF(ISNUMBER('Ratio Calculations'!B9),'Ratio Calculations'!B9,NA()) -> 0.22399577 | C73: =IF(ISNUMBER('Ratio Calculations'!C9),'Ratio Calculations'!C9,NA()) -> 0.22281798 | D73: =IF(ISNUMBER('Ratio Calculations'!D9),'Ratio Calculations'!D9,NA()) -> 0.2195204 | E73: =IF(ISNUMBER('Ratio Calculations'!E9),'Ratio Calculations'!E9,NA()) -> 0.22072846 | F73: =IF(ISNUMBER('Ratio Calculations'!F9),'Ratio Calculations'!F9,NA()) -> 0.23321861 | G73: =IF(ISNUMBER('Ratio Calculations'!G9),'Ratio Calculations'!G9,NA()) -> 0.22009892 | H73: =IF(ISNUMBER('Ratio Calculations'!H9),'Ratio Calculations'!H9,NA()) -> 0.21434256 | I73: =IF(ISNUMBER('Ratio Calculations'!I9),'Ratio Calculations'!I9,NA()) -> 0.22236885 | ... K73: =IF(ISNUMBER('Ratio Calculations'!K9),'Ratio Calculations'!K9,NA()) -> 0.23300958
A74: Sam's Club | B74: =IF(ISNUMBER('Ratio Calculations'!B10),'Ratio Calculations'!B10,NA()) -> #N/A | C74: =IF(ISNUMBER('Ratio Calculations'!C10),'Ratio Calculations'!C10,NA()) -> #N/A | D74: =IF(ISNUMBER('Ratio Calculations'!D10),'Ratio Calculations'!D10,NA()) -> #N/A | E74: =IF(ISNUMBER('Ratio Calculations'!E10),'Ratio Calculations'!E10,NA()) -> #N/A | F74: =IF(ISNUMBER('Ratio Calculations'!F10),'Ratio Calculations'!F10,NA()) -> #N/A | G74: =IF(ISNUMBER('Ratio Calculations'!G10),'Ratio Calculations'!G10,NA()) -> #N/A | H74: =IF(ISNUMBER('Ratio Calculations'!H10),'Ratio Calculations'!H10,NA()) -> 0.10387101 | I74: =IF(ISNUMBER('Ratio Calculations'!I10),'Ratio Calculations'!I10,NA()) -> 0.10943501 | ... K74: =IF(ISNUMBER('Ratio Calculations'!K10),'Ratio Calculations'!K10,NA()) -> 0.11348707
A75: Whole Foods | B75: =IF(ISNUMBER('Ratio Calculations'!B11),'Ratio Calculations'!B11,NA()) -> 0.34412363 | C75: =IF(ISNUMBER('Ratio Calculations'!C11),'Ratio Calculations'!C11,NA()) -> 0.33668122 | D75: =IF(ISNUMBER('Ratio Calculations'!D11),'Ratio Calculations'!D11,NA()) -> #N/A | E75: =IF(ISNUMBER('Ratio Calculations'!E11),'Ratio Calculations'!E11,NA()) -> #N/A | F75: =IF(ISNUMBER('Ratio Calculations'!F11),'Ratio Calculations'!F11,NA()) -> #N/A | G75: =IF(ISNUMBER('Ratio Calculations'!G11),'Ratio Calculations'!G11,NA()) -> #N/A | H75: =IF(ISNUMBER('Ratio Calculations'!H11),'Ratio Calculations'!H11,NA()) -> #N/A | I75: =IF(ISNUMBER('Ratio Calculations'!I11),'Ratio Calculations'!I11,NA()) -> #N/A | ... K75: =IF(ISNUMBER('Ratio Calculations'!K11),'Ratio Calculations'!K11,NA()) -> #N/A
A76: FY2020–23 window | B76: =IF(AND(B$70>="FY2020",B$70<="FY2023"),1,NA()) -> #N/A | C76: =IF(AND(C$70>="FY2020",C$70<="FY2023"),1,NA()) -> #N/A | D76: =IF(AND(D$70>="FY2020",D$70<="FY2023"),1,NA()) -> #N/A | E76: =IF(AND(E$70>="FY2020",E$70<="FY2023"),1,NA()) -> #N/A | F76: =IF(AND(F$70>="FY2020",F$70<="FY2023"),1,NA()) -> 1 | G76: =IF(AND(G$70>="FY2020",G$70<="FY2023"),1,NA()) -> 1 | H76: =IF(AND(H$70>="FY2020",H$70<="FY2023"),1,NA()) -> 1 | I76: =IF(AND(I$70>="FY2020",I$70<="FY2023"),1,NA()) -> 1 | ... K76: =IF(AND(K$70>="FY2020",K$70<="FY2023"),1,NA()) -> #N/A
A78: Walmart | B78: =IF(ISNUMBER('Ratio Calculations'!B21),'Ratio Calculations'!B21,NA()) -> 0.028345145 | C78: =IF(ISNUMBER('Ratio Calculations'!C21),'Ratio Calculations'!C21,NA()) -> 0.01989265 | D78: =IF(ISNUMBER('Ratio Calculations'!D21),'Ratio Calculations'!D21,NA()) -> 0.01307 | E78: =IF(ISNUMBER('Ratio Calculations'!E21),'Ratio Calculations'!E21,NA()) -> 0.028621381 | F78: =IF(ISNUMBER('Ratio Calculations'!F21),'Ratio Calculations'!F21,NA()) -> 0.024332127 | G78: =IF(ISNUMBER('Ratio Calculations'!G21),'Ratio Calculations'!G21,NA()) -> 0.024082274 | H78: =IF(ISNUMBER('Ratio Calculations'!H21),'Ratio Calculations'!H21,NA()) -> 0.019277713 | I78: =IF(ISNUMBER('Ratio Calculations'!I21),'Ratio Calculations'!I21,NA()) -> 0.024136488 | ... K78: =IF(ISNUMBER('Ratio Calculations'!K21),'Ratio Calculations'!K21,NA()) -> 0.030991785
A79: Costco | B79: =IF(ISNUMBER('Ratio Calculations'!B22),'Ratio Calculations'!B22,NA()) -> 0.02024588 | C79: =IF(ISNUMBER('Ratio Calculations'!C22),'Ratio Calculations'!C22,NA()) -> 0.02123292 | D79: =IF(ISNUMBER('Ratio Calculations'!D22),'Ratio Calculations'!D22,NA()) -> 0.022638947 | E79: =IF(ISNUMBER('Ratio Calculations'!E22),'Ratio Calculations'!E22,NA()) -> 0.024499334 | F79: =IF(ISNUMBER('Ratio Calculations'!F22),'Ratio Calculations'!F22,NA()) -> 0.024519054 | G79: =IF(ISNUMBER('Ratio Calculations'!G22),'Ratio Calculations'!G22,NA()) -> 0.026071064 | H79: =IF(ISNUMBER('Ratio Calculations'!H22),'Ratio Calculations'!H22,NA()) -> 0.026238046 | I79: =IF(ISNUMBER('Ratio Calculations'!I22),'Ratio Calculations'!I22,NA()) -> 0.026469227 | ... K79: =IF(ISNUMBER('Ratio Calculations'!K22),'Ratio Calculations'!K22,NA()) -> 0.030006076
A80: Kroger | B80: =IF(ISNUMBER('Ratio Calculations'!B23),'Ratio Calculations'!B23,NA()) -> 0.017123733 | C80: =IF(ISNUMBER('Ratio Calculations'!C23),'Ratio Calculations'!C23,NA()) -> 0.015468851 | D80: =IF(ISNUMBER('Ratio Calculations'!D23),'Ratio Calculations'!D23,NA()) -> 0.025522765 | E80: =IF(ISNUMBER('Ratio Calculations'!E23),'Ratio Calculations'!E23,NA()) -> 0.013566557 | F80: =IF(ISNUMBER('Ratio Calculations'!F23),'Ratio Calculations'!F23,NA()) -> 0.019509728 | G80: =IF(ISNUMBER('Ratio Calculations'!G23),'Ratio Calculations'!G23,NA()) -> 0.012002495 | H80: =IF(ISNUMBER('Ratio Calculations'!H23),'Ratio Calculations'!H23,NA()) -> 0.015135777 | I80: =IF(ISNUMBER('Ratio Calculations'!I23),'Ratio Calculations'!I23,NA()) -> 0.014422917 | ... K80: =IF(ISNUMBER('Ratio Calculations'!K23),'Ratio Calculations'!K23,NA()) -> 0.0068815107
A81: Whole Foods | B81: =IF(ISNUMBER('Ratio Calculations'!B25),'Ratio Calculations'!B25,NA()) -> 0.032243704 | C81: =IF(ISNUMBER('Ratio Calculations'!C25),'Ratio Calculations'!C25,NA()) -> 0.015283843 | D81: =IF(ISNUMBER('Ratio Calculations'!D25),'Ratio Calculations'!D25,NA()) -> #N/A | E81: =IF(ISNUMBER('Ratio Calculations'!E25),'Ratio Calculations'!E25,NA()) -> #N/A | F81: =IF(ISNUMBER('Ratio Calculations'!F25),'Ratio Calculations'!F25,NA()) -> #N/A | G81: =IF(ISNUMBER('Ratio Calculations'!G25),'Ratio Calculations'!G25,NA()) -> #N/A | H81: =IF(ISNUMBER('Ratio Calculations'!H25),'Ratio Calculations'!H25,NA()) -> #N/A | I81: =IF(ISNUMBER('Ratio Calculations'!I25),'Ratio Calculations'!I25,NA()) -> #N/A | ... K81: =IF(ISNUMBER('Ratio Calculations'!K25),'Ratio Calculations'!K25,NA()) -> #N/A
A82: FY2020–23 window | B82: =IF(AND(B$70>="FY2020",B$70<="FY2023"),1,NA()) -> #N/A | C82: =IF(AND(C$70>="FY2020",C$70<="FY2023"),1,NA()) -> #N/A | D82: =IF(AND(D$70>="FY2020",D$70<="FY2023"),1,NA()) -> #N/A | E82: =IF(AND(E$70>="FY2020",E$70<="FY2023"),1,NA()) -> #N/A | F82: =IF(AND(F$70>="FY2020",F$70<="FY2023"),1,NA()) -> 1 | G82: =IF(AND(G$70>="FY2020",G$70<="FY2023"),1,NA()) -> 1 | H82: =IF(AND(H$70>="FY2020",H$70<="FY2023"),1,NA()) -> 1 | I82: =IF(AND(I$70>="FY2020",I$70<="FY2023"),1,NA()) -> 1 | ... K82: =IF(AND(K$70>="FY2020",K$70<="FY2023"),1,NA()) -> #N/A
A84: Walmart | B84: =IF(ISNUMBER('Ratio Calculations'!B14),'Ratio Calculations'!B14,NA()) -> 0.047295234 | C84: =IF(ISNUMBER('Ratio Calculations'!C14),'Ratio Calculations'!C14,NA()) -> 0.041223493 | D84: =IF(ISNUMBER('Ratio Calculations'!D14),'Ratio Calculations'!D14,NA()) -> 0.043025186 | E84: =IF(ISNUMBER('Ratio Calculations'!E14),'Ratio Calculations'!E14,NA()) -> 0.039559476 | F84: =IF(ISNUMBER('Ratio Calculations'!F14),'Ratio Calculations'!F14,NA()) -> 0.040609978 | G84: =IF(ISNUMBER('Ratio Calculations'!G14),'Ratio Calculations'!G14,NA()) -> 0.045691681 | H84: =IF(ISNUMBER('Ratio Calculations'!H14),'Ratio Calculations'!H14,NA()) -> 0.033716192 | I84: =IF(ISNUMBER('Ratio Calculations'!I14),'Ratio Calculations'!I14,NA()) -> 0.042033061 | ... K84: =IF(ISNUMBER('Ratio Calculations'!K14),'Ratio Calculations'!K14,NA()) -> 0.042220344
A85: Costco | B85: =IF(ISNUMBER('Ratio Calculations'!B15),'Ratio Calculations'!B15,NA()) -> 0.031635264 | C85: =IF(ISNUMBER('Ratio Calculations'!C15),'Ratio Calculations'!C15,NA()) -> 0.032582506 | D85: =IF(ISNUMBER('Ratio Calculations'!D15),'Ratio Calculations'!D15,NA()) -> 0.032361992 | E85: =IF(ISNUMBER('Ratio Calculations'!E15),'Ratio Calculations'!E15,NA()) -> 0.03171723 | F85: =IF(ISNUMBER('Ratio Calculations'!F15),'Ratio Calculations'!F15,NA()) -> 0.033298615 | G85: =IF(ISNUMBER('Ratio Calculations'!G15),'Ratio Calculations'!G15,NA()) -> 0.03492804 | H85: =IF(ISNUMBER('Ratio Calculations'!H15),'Ratio Calculations'!H15,NA()) -> 0.034988551 | I85: =IF(ISNUMBER('Ratio Calculations'!I15),'Ratio Calculations'!I15,NA()) -> 0.034134029 | ... K85: =IF(ISNUMBER('Ratio Calculations'!K15),'Ratio Calculations'!K15,NA()) -> 0.038468093
A86: Kroger | B86: =IF(ISNUMBER('Ratio Calculations'!B16),'Ratio Calculations'!B16,NA()) -> 0.029929684 | C86: =IF(ISNUMBER('Ratio Calculations'!C16),'Ratio Calculations'!C16,NA()) -> 0.021187541 | D86: =IF(ISNUMBER('Ratio Calculations'!D16),'Ratio Calculations'!D16,NA()) -> 0.021452254 | E86: =IF(ISNUMBER('Ratio Calculations'!E16),'Ratio Calculations'!E16,NA()) -> 0.018407667 | F86: =IF(ISNUMBER('Ratio Calculations'!F16),'Ratio Calculations'!F16,NA()) -> 0.020981449 | G86: =IF(ISNUMBER('Ratio Calculations'!G16),'Ratio Calculations'!G16,NA()) -> 0.025216117 | H86: =IF(ISNUMBER('Ratio Calculations'!H16),'Ratio Calculations'!H16,NA()) -> 0.027829864 | I86: =IF(ISNUMBER('Ratio Calculations'!I16),'Ratio Calculations'!I16,NA()) -> 0.020634635 | ... K86: =IF(ISNUMBER('Ratio Calculations'!K16),'Ratio Calculations'!K16,NA()) -> 0.012801235
A87: Sam's Club | B87: =IF(ISNUMBER('Ratio Calculations'!B17),'Ratio Calculations'!B17,NA()) -> 0.028379674 | C87: =IF(ISNUMBER('Ratio Calculations'!C17),'Ratio Calculations'!C17,NA()) -> 0.015451905 | D87: =IF(ISNUMBER('Ratio Calculations'!D17),'Ratio Calculations'!D17,NA()) -> 0.026279846 | E87: =IF(ISNUMBER('Ratio Calculations'!E17),'Ratio Calculations'!E17,NA()) -> 0.02792897 | F87: =IF(ISNUMBER('Ratio Calculations'!F17),'Ratio Calculations'!F17,NA()) -> 0.029823189 | G87: =IF(ISNUMBER('Ratio Calculations'!G17),'Ratio Calculations'!G17,NA()) -> 0.030711295 | H87: =IF(ISNUMBER('Ratio Calculations'!H17),'Ratio Calculations'!H17,NA()) -> 0.023285316 | I87: =IF(ISNUMBER('Ratio Calculations'!I17),'Ratio Calculations'!I17,NA()) -> 0.025435431 | ... K87: =IF(ISNUMBER('Ratio Calculations'!K17),'Ratio Calculations'!K17,NA()) -> 0.02625383
A88: Whole Foods | B88: =IF(ISNUMBER('Ratio Calculations'!B18),'Ratio Calculations'!B18,NA()) -> 0.054502671 | C88: =IF(ISNUMBER('Ratio Calculations'!C18),'Ratio Calculations'!C18,NA()) -> 0.028633812 | D88: =IF(ISNUMBER('Ratio Calculations'!D18),'Ratio Calculations'!D18,NA()) -> #N/A | E88: =IF(ISNUMBER('Ratio Calculations'!E18),'Ratio Calculations'!E18,NA()) -> #N/A | F88: =IF(ISNUMBER('Ratio Calculations'!F18),'Ratio Calculations'!F18,NA()) -> #N/A | G88: =IF(ISNUMBER('Ratio Calculations'!G18),'Ratio Calculations'!G18,NA()) -> #N/A | H88: =IF(ISNUMBER('Ratio Calculations'!H18),'Ratio Calculations'!H18,NA()) -> #N/A | I88: =IF(ISNUMBER('Ratio Calculations'!I18),'Ratio Calculations'!I18,NA()) -> #N/A | ... K88: =IF(ISNUMBER('Ratio Calculations'!K18),'Ratio Calculations'!K18,NA()) -> #N/A
A89: FY2020–23 window | B89: =IF(AND(B$70>="FY2020",B$70<="FY2023"),1,NA()) -> #N/A | C89: =IF(AND(C$70>="FY2020",C$70<="FY2023"),1,NA()) -> #N/A | D89: =IF(AND(D$70>="FY2020",D$70<="FY2023"),1,NA()) -> #N/A | E89: =IF(AND(E$70>="FY2020",E$70<="FY2023"),1,NA()) -> #N/A | F89: =IF(AND(F$70>="FY2020",F$70<="FY2023"),1,NA()) -> 1 | G89: =IF(AND(G$70>="FY2020",G$70<="FY2023"),1,NA()) -> 1 | H89: =IF(AND(H$70>="FY2020",H$70<="FY2023"),1,NA()) -> 1 | I89: =IF(AND(I$70>="FY2020",I$70<="FY2023"),1,NA()) -> 1 | ... K89: =IF(AND(K$70>="FY2020",K$70<="FY2023"),1,NA()) -> #N/A
A91: Walmart | B91: =IF(ISNUMBER('Ratio Calculations'!B28),'Ratio Calculations'!B28,NA()) -> 0.86195613 | C91: =IF(ISNUMBER('Ratio Calculations'!C28),'Ratio Calculations'!C28,NA()) -> 0.75984768 | D91: =IF(ISNUMBER('Ratio Calculations'!D28),'Ratio Calculations'!D28,NA()) -> 0.79890806 | E91: =IF(ISNUMBER('Ratio Calculations'!E28),'Ratio Calculations'!E28,NA()) -> 0.79452372 | F91: =IF(ISNUMBER('Ratio Calculations'!F28),'Ratio Calculations'!F28,NA()) -> 0.97217335 | G91: =IF(ISNUMBER('Ratio Calculations'!G28),'Ratio Calculations'!G28,NA()) -> 0.9277973 | H91: =IF(ISNUMBER('Ratio Calculations'!H28),'Ratio Calculations'!H28,NA()) -> 0.82057095 | I91: =IF(ISNUMBER('Ratio Calculations'!I28),'Ratio Calculations'!I28,NA()) -> 0.83186712 | ... K91: =IF(ISNUMBER('Ratio Calculations'!K28),'Ratio Calculations'!K28,NA()) -> 0.78975332
A92: Costco | B92: =IF(ISNUMBER('Ratio Calculations'!B29),'Ratio Calculations'!B29,NA()) -> 0.97707865 | C92: =IF(ISNUMBER('Ratio Calculations'!C29),'Ratio Calculations'!C29,NA()) -> 0.98982566 | D92: =IF(ISNUMBER('Ratio Calculations'!D29),'Ratio Calculations'!D29,NA()) -> 1.0182174 | E92: =IF(ISNUMBER('Ratio Calculations'!E29),'Ratio Calculations'!E29,NA()) -> 1.0106726 | F92: =IF(ISNUMBER('Ratio Calculations'!F29),'Ratio Calculations'!F29,NA()) -> 1.1318628 | G92: =IF(ISNUMBER('Ratio Calculations'!G29),'Ratio Calculations'!G29,NA()) -> 1.0021738 | H92: =IF(ISNUMBER('Ratio Calculations'!H29),'Ratio Calculations'!H29,NA()) -> 1.0218139 | I92: =IF(ISNUMBER('Ratio Calculations'!I29),'Ratio Calculations'!I29,NA()) -> 1.0683679 | ... K92: =IF(ISNUMBER('Ratio Calculations'!K29),'Ratio Calculations'!K29,NA()) -> 1.0342783
A93: Kroger | B93: =IF(ISNUMBER('Ratio Calculations'!B30),'Ratio Calculations'!B30,NA()) -> 0.80404355 | C93: =IF(ISNUMBER('Ratio Calculations'!C30),'Ratio Calculations'!C30,NA()) -> 0.78305276 | D93: =IF(ISNUMBER('Ratio Calculations'!D30),'Ratio Calculations'!D30,NA()) -> 0.7568306 | E93: =IF(ISNUMBER('Ratio Calculations'!E30),'Ratio Calculations'!E30,NA()) -> 0.76458611 | F93: =IF(ISNUMBER('Ratio Calculations'!F30),'Ratio Calculations'!F30,NA()) -> 0.81367955 | G93: =IF(ISNUMBER('Ratio Calculations'!G30),'Ratio Calculations'!G30,NA()) -> 0.74581878 | H93: =IF(ISNUMBER('Ratio Calculations'!H30),'Ratio Calculations'!H30,NA()) -> 0.73500406 | I93: =IF(ISNUMBER('Ratio Calculations'!I30),'Ratio Calculations'!I30,NA()) -> 0.80632706 | ... K93: =IF(ISNUMBER('Ratio Calculations'!K30),'Ratio Calculations'!K30,NA()) -> 0.80102717
A94: Whole Foods | B94: =IF(ISNUMBER('Ratio Calculations'!B32),'Ratio Calculations'!B32,NA()) -> 1.4727815 | C94: =IF(ISNUMBER('Ratio Calculations'!C32),'Ratio Calculations'!C32,NA()) -> 1.5830258 | D94: =IF(ISNUMBER('Ratio Calculations'!D32),'Ratio Calculations'!D32,NA()) -> #N/A | E94: =IF(ISNUMBER('Ratio Calculations'!E32),'Ratio Calculations'!E32,NA()) -> #N/A | F94: =IF(ISNUMBER('Ratio Calculations'!F32),'Ratio Calculations'!F32,NA()) -> #N/A | G94: =IF(ISNUMBER('Ratio Calculations'!G32),'Ratio Calculations'!G32,NA()) -> #N/A | H94: =IF(ISNUMBER('Ratio Calculations'!H32),'Ratio Calculations'!H32,NA()) -> #N/A | I94: =IF(ISNUMBER('Ratio Calculations'!I32),'Ratio Calculations'!I32,NA()) -> #N/A | ... K94: =IF(ISNUMBER('Ratio Calculations'!K32),'Ratio Calculations'!K32,NA()) -> #N/A
A95: FY2020–23 window | B95: =IF(AND(B$70>="FY2020",B$70<="FY2023"),1,NA()) -> #N/A | C95: =IF(AND(C$70>="FY2020",C$70<="FY2023"),1,NA()) -> #N/A | D95: =IF(AND(D$70>="FY2020",D$70<="FY2023"),1,NA()) -> #N/A | E95: =IF(AND(E$70>="FY2020",E$70<="FY2023"),1,NA()) -> #N/A | F95: =IF(AND(F$70>="FY2020",F$70<="FY2023"),1,NA()) -> 1 | G95: =IF(AND(G$70>="FY2020",G$70<="FY2023"),1,NA()) -> 1 | H95: =IF(AND(H$70>="FY2020",H$70<="FY2023"),1,NA()) -> 1 | I95: =IF(AND(I$70>="FY2020",I$70<="FY2023"),1,NA()) -> 1 | ... K95: =IF(AND(K$70>="FY2020",K$70<="FY2023"),1,NA()) -> #N/A
A97: Walmart | B97: =IF(ISNUMBER('Ratio Calculations'!B35),'Ratio Calculations'!B35,NA()) -> 0.57041038 | C97: =IF(ISNUMBER('Ratio Calculations'!C35),'Ratio Calculations'!C35,NA()) -> 0.57517755 | D97: =IF(ISNUMBER('Ratio Calculations'!D35),'Ratio Calculations'!D35,NA()) -> 0.72874652 | E97: =IF(ISNUMBER('Ratio Calculations'!E35),'Ratio Calculations'!E35,NA()) -> 0.66790514 | F97: =IF(ISNUMBER('Ratio Calculations'!F35),'Ratio Calculations'!F35,NA()) -> 0.55832791 | G97: =IF(ISNUMBER('Ratio Calculations'!G35),'Ratio Calculations'!G35,NA()) -> 0.46610658 | H97: =IF(ISNUMBER('Ratio Calculations'!H35),'Ratio Calculations'!H35,NA()) -> 0.53277455 | I97: =IF(ISNUMBER('Ratio Calculations'!I35),'Ratio Calculations'!I35,NA()) -> 0.51899855 | ... K97: =IF(ISNUMBER('Ratio Calculations'!K35),'Ratio Calculations'!K35,NA()) -> 0.48658476
A98: Costco | B98: =IF(ISNUMBER('Ratio Calculations'!B36),'Ratio Calculations'!B36,NA()) -> 0.44883231 | C98: =IF(ISNUMBER('Ratio Calculations'!C36),'Ratio Calculations'!C36,NA()) -> 0.63534615 | D98: =IF(ISNUMBER('Ratio Calculations'!D36),'Ratio Calculations'!D36,NA()) -> 0.53224452 | E98: =IF(ISNUMBER('Ratio Calculations'!E36),'Ratio Calculations'!E36,NA()) -> 0.46483573 | F98: =IF(ISNUMBER('Ratio Calculations'!F36),'Ratio Calculations'!F36,NA()) -> 0.44357124 | G98: =IF(ISNUMBER('Ratio Calculations'!G36),'Ratio Calculations'!G36,NA()) -> 0.47256334 | H98: =IF(ISNUMBER('Ratio Calculations'!H36),'Ratio Calculations'!H36,NA()) -> 0.39642563 | I98: =IF(ISNUMBER('Ratio Calculations'!I36),'Ratio Calculations'!I36,NA()) -> 0.3148695 | ... K98: =IF(ISNUMBER('Ratio Calculations'!K36),'Ratio Calculations'!K36,NA()) -> 0.24917707
A99: Kroger | B99: =IF(ISNUMBER('Ratio Calculations'!B37),'Ratio Calculations'!B37,NA()) -> 2.0979136 | C99: =IF(ISNUMBER('Ratio Calculations'!C37),'Ratio Calculations'!C37,NA()) -> 2.2576394 | D99: =IF(ISNUMBER('Ratio Calculations'!D37),'Ratio Calculations'!D37,NA()) -> 1.9437141 | E99: =IF(ISNUMBER('Ratio Calculations'!E37),'Ratio Calculations'!E37,NA()) -> 1.641899 | F99: =IF(ISNUMBER('Ratio Calculations'!F37),'Ratio Calculations'!F37,NA()) -> 1.4045026 | G99: =IF(ISNUMBER('Ratio Calculations'!G37),'Ratio Calculations'!G37,NA()) -> 1.4173295 | H99: =IF(ISNUMBER('Ratio Calculations'!H37),'Ratio Calculations'!H37,NA()) -> 1.3359297 | I99: =IF(ISNUMBER('Ratio Calculations'!I37),'Ratio Calculations'!I37,NA()) -> 1.0538747 | ... K99: =IF(ISNUMBER('Ratio Calculations'!K37),'Ratio Calculations'!K37,NA()) -> 2.9592318
A100: Whole Foods | B100: =IF(ISNUMBER('Ratio Calculations'!B39),'Ratio Calculations'!B39,NA()) -> 0.32599256 | C100: =IF(ISNUMBER('Ratio Calculations'!C39),'Ratio Calculations'!C39,NA()) -> 0.31574344 | D100: =IF(ISNUMBER('Ratio Calculations'!D39),'Ratio Calculations'!D39,NA()) -> #N/A | E100: =IF(ISNUMBER('Ratio Calculations'!E39),'Ratio Calculations'!E39,NA()) -> #N/A | F100: =IF(ISNUMBER('Ratio Calculations'!F39),'Ratio Calculations'!F39,NA()) -> #N/A | G100: =IF(ISNUMBER('Ratio Calculations'!G39),'Ratio Calculations'!G39,NA()) -> #N/A | H100: =IF(ISNUMBER('Ratio Calculations'!H39),'Ratio Calculations'!H39,NA()) -> #N/A | I100: =IF(ISNUMBER('Ratio Calculations'!I39),'Ratio Calculations'!I39,NA()) -> #N/A | ... K100: =IF(ISNUMBER('Ratio Calculations'!K39),'Ratio Calculations'!K39,NA()) -> #N/A
A101: FY2020–23 window | B101: =IF(AND(B$70>="FY2020",B$70<="FY2023"),1,NA()) -> #N/A | C101: =IF(AND(C$70>="FY2020",C$70<="FY2023"),1,NA()) -> #N/A | D101: =IF(AND(D$70>="FY2020",D$70<="FY2023"),1,NA()) -> #N/A | E101: =IF(AND(E$70>="FY2020",E$70<="FY2023"),1,NA()) -> #N/A | F101: =IF(AND(F$70>="FY2020",F$70<="FY2023"),1,NA()) -> 1 | G101: =IF(AND(G$70>="FY2020",G$70<="FY2023"),1,NA()) -> 1 | H101: =IF(AND(H$70>="FY2020",H$70<="FY2023"),1,NA()) -> 1 | I101: =IF(AND(I$70>="FY2020",I$70<="FY2023"),1,NA()) -> 1 | ... K101: =IF(AND(K$70>="FY2020",K$70<="FY2023"),1,NA()) -> #N/A
A103: Walmart | B103: =IF(ISNUMBER('Ratio Calculations'!B49),'Ratio Calculations'!B49,NA()) -> 0.0056475573 | C103: =IF(ISNUMBER('Ratio Calculations'!C49),'Ratio Calculations'!C49,NA()) -> 0.030009329 | D103: =IF(ISNUMBER('Ratio Calculations'!D49),'Ratio Calculations'!D49,NA()) -> 0.029385127 | E103: =IF(ISNUMBER('Ratio Calculations'!E49),'Ratio Calculations'!E49,NA()) -> 0.018805516 | F103: =IF(ISNUMBER('Ratio Calculations'!F49),'Ratio Calculations'!F49,NA()) -> 0.067907741 | G103: =IF(ISNUMBER('Ratio Calculations'!G49),'Ratio Calculations'!G49,NA()) -> 0.022565301 | H103: =IF(ISNUMBER('Ratio Calculations'!H49),'Ratio Calculations'!H49,NA()) -> 0.067139048 | I103: =IF(ISNUMBER('Ratio Calculations'!I49),'Ratio Calculations'!I49,NA()) -> 0.060665378 | ... K103: =IF(ISNUMBER('Ratio Calculations'!K49),'Ratio Calculations'!K49,NA()) -> 0.047254565
A104: Costco | B104: =IF(ISNUMBER('Ratio Calculations'!B50),'Ratio Calculations'!B50,NA()) -> 0.021176077 | C104: =IF(ISNUMBER('Ratio Calculations'!C50),'Ratio Calculations'!C50,NA()) -> 0.087005591 | D104: =IF(ISNUMBER('Ratio Calculations'!D50),'Ratio Calculations'!D50,NA()) -> 0.097184795 | E104: =IF(ISNUMBER('Ratio Calculations'!E50),'Ratio Calculations'!E50,NA()) -> 0.078860685 | F104: =IF(ISNUMBER('Ratio Calculations'!F50),'Ratio Calculations'!F50,NA()) -> 0.092861782 | G104: =IF(ISNUMBER('Ratio Calculations'!G50),'Ratio Calculations'!G50,NA()) -> 0.17664502 | H104: =IF(ISNUMBER('Ratio Calculations'!H50),'Ratio Calculations'!H50,NA()) -> 0.15973799 | I104: =IF(ISNUMBER('Ratio Calculations'!I50),'Ratio Calculations'!I50,NA()) -> 0.067256319 | ... K104: =IF(ISNUMBER('Ratio Calculations'!K50),'Ratio Calculations'!K50,NA()) -> 0.081269905
A105: Kroger | B105: =IF(ISNUMBER('Ratio Calculations'!B51),'Ratio Calculations'!B51,NA()) -> 0.050141127 | C105: =IF(ISNUMBER('Ratio Calculations'!C51),'Ratio Calculations'!C51,NA()) -> 0.068867753 | D105: =IF(ISNUMBER('Ratio Calculations'!D51),'Ratio Calculations'!D51,NA()) -> -0.011583387 | E105: =IF(ISNUMBER('Ratio Calculations'!E51),'Ratio Calculations'!E51,NA()) -> 0.0035616978 | F105: =IF(ISNUMBER('Ratio Calculations'!F51),'Ratio Calculations'!F51,NA()) -> 0.083509151 | G105: =IF(ISNUMBER('Ratio Calculations'!G51),'Ratio Calculations'!G51,NA()) -> 0.040679859 | H105: =IF(ISNUMBER('Ratio Calculations'!H51),'Ratio Calculations'!H51,NA()) -> 0.075205964 | I105: =IF(ISNUMBER('Ratio Calculations'!I51),'Ratio Calculations'!I51,NA()) -> 0.012012842 | ... K105: =IF(ISNUMBER('Ratio Calculations'!K51),'Ratio Calculations'!K51,NA()) -> 0.0035276605
A106: Sam's Club | B106: =IF(ISNUMBER('Ratio Calculations'!B52),'Ratio Calculations'!B52,NA()) -> 0.0094495671 | C106: =IF(ISNUMBER('Ratio Calculations'!C52),'Ratio Calculations'!C52,NA()) -> 0.032267062 | D106: =IF(ISNUMBER('Ratio Calculations'!D52),'Ratio Calculations'!D52,NA()) -> -0.02325385 | E106: =IF(ISNUMBER('Ratio Calculations'!E52),'Ratio Calculations'!E52,NA()) -> 0.016476772 | F106: =IF(ISNUMBER('Ratio Calculations'!F52),'Ratio Calculations'!F52,NA()) -> 0.08705266 | G106: =IF(ISNUMBER('Ratio Calculations'!G52),'Ratio Calculations'!G52,NA()) -> 0.150931 | H106: =IF(ISNUMBER('Ratio Calculations'!H52),'Ratio Calculations'!H52,NA()) -> 0.14667736 | I106: =IF(ISNUMBER('Ratio Calculations'!I52),'Ratio Calculations'!I52,NA()) -> 0.021744028 | ... K106: =IF(ISNUMBER('Ratio Calculations'!K52),'Ratio Calculations'!K52,NA()) -> 0.030774175
A107: Whole Foods | B107: =IF(ISNUMBER('Ratio Calculations'!B53),'Ratio Calculations'!B53,NA()) -> 0.021768796 | C107: =IF(ISNUMBER('Ratio Calculations'!C53),'Ratio Calculations'!C53,NA()) -> 0.019460697 | D107: =IF(ISNUMBER('Ratio Calculations'!D53),'Ratio Calculations'!D53,NA()) -> #N/A | E107: =IF(ISNUMBER('Ratio Calculations'!E53),'Ratio Calculations'!E53,NA()) -> #N/A | F107: =IF(ISNUMBER('Ratio Calculations'!F53),'Ratio Calculations'!F53,NA()) -> #N/A | G107: =IF(ISNUMBER('Ratio Calculations'!G53),'Ratio Calculations'!G53,NA()) -> #N/A | H107: =IF(ISNUMBER('Ratio Calculations'!H53),'Ratio Calculations'!H53,NA()) -> #N/A | I107: =IF(ISNUMBER('Ratio Calculations'!I53),'Ratio Calculations'!I53,NA()) -> #N/A | ... K107: =IF(ISNUMBER('Ratio Calculations'!K53),'Ratio Calculations'!K53,NA()) -> #N/A
A108: FY2020–23 window | B108: =IF(AND(B$70>="FY2020",B$70<="FY2023"),1,NA()) -> #N/A | C108: =IF(AND(C$70>="FY2020",C$70<="FY2023"),1,NA()) -> #N/A | D108: =IF(AND(D$70>="FY2020",D$70<="FY2023"),1,NA()) -> #N/A | E108: =IF(AND(E$70>="FY2020",E$70<="FY2023"),1,NA()) -> #N/A | F108: =IF(AND(F$70>="FY2020",F$70<="FY2023"),1,NA()) -> 1 | G108: =IF(AND(G$70>="FY2020",G$70<="FY2023"),1,NA()) -> 1 | H108: =IF(AND(H$70>="FY2020",H$70<="FY2023"),1,NA()) -> 1 | I108: =IF(AND(I$70>="FY2020",I$70<="FY2023"),1,NA()) -> 1 | ... K108: =IF(AND(K$70>="FY2020",K$70<="FY2023"),1,NA()) -> #N/A

Sheet Methodology & Tools
A1: 07 — METHODOLOGY & TOOLS | B1: COMPETITOR SCORECARD · FY2016–FY2025 · SEC 10-K DATA
A2: Methodology & Tools
A3: How the workbook was built, what was assumed, and where accounting policy limits comparability.
A4: DATA SOURCES
A5: SEC EDGAR | B5: Primary source for every number. Three endpoints: (1) the XBRL companyfacts API (data.sec.gov/api/xbrl/companyfacts) for undimensioned 10-K facts; (2) the filing index and XBRL instance documents under sec.gov/Archives for dimensional facts (segments, product lines) and for values the API omits; (3) the submissions API for the 10-K filing list. Access follows the SEC fair-use rules: declared User-Agent, ≤5 requests/second, every download cached and logged to data/raw/manifest.csv.
A6: Companies / CIKs | B6: Walmart Inc. 104169 · Costco Wholesale Corp. 909832 · The Kroger Co. 56873 · Whole Foods Market, Inc. 865436 (through FY2017) · Amazon.com, Inc. 1018724 (successor, 'Physical stores' revenue only) · Sam's Club = Walmart segment (no CIK).
A7: Value selection | B7: Fiscal-year label follows the SEC frame convention (the calendar year containing most of the period). Flow items use 10-K facts spanning 340–380 days (53-week years qualify); balance-sheet items match the period-end date. Where a period is re-tagged in later filings as a comparative, the latest-filed (restated) value is used and the first-filed value is retained on Data Lineage with a restatement flag. Values the API could not supply (7 of 900+) were read from the filing's XBRL instance or derived from two tagged facts, each with its own citation, and are shaded yellow on Raw Data. No value is estimated.
A8: EXCEL TECHNIQUES
A9: Named ranges | B9: 103 defined names (e.g. Walmart_Revenue, Kroger_TotalDebt, GM_Costco, ScorecardYear, Years, RatioYears). Every cross-tab formula reads as a sentence and survives row insertions.
A10: XLOOKUP + IFERROR | B10: All ratio cells: =IFERROR((XLOOKUP(year,Years,Company_Revenue)-XLOOKUP(year,Years,Company_COGS))/XLOOKUP(year,Years,Company_Revenue),"n/a"). Missing data returns the text n/a rather than #DIV/0! or #VALUE!, and is styled grey-italic by conditional formatting.
A11: Formula-built totals | B11: Total debt is a formula over the extracted components under a written policy (below), not a typed number; the Scorecard leader/laggard and takeaway text are built with INDEX/MATCH, RANK.EQ and TEXT so they re-write when the year input changes.
A12: Scorecard year input | B12: Data-validated list (FY2016–FY2025) driving XLOOKUPs on the Scorecard and the at-a-glance figures; ranks and colour scales recompute.
A13: Conditional formatting | B13: Three-colour scales per metric row (direction-aware: low debt-to-equity is green), text-detection rules for n/a, and a reversed scale on the composite rank.
A14: Native combo charts | B14: Each Trend chart is an Excel column+line combination: a zero-gap column series on a hidden secondary axis shades FY2020–FY2023; ratio lines sit on top. The helper block converts n/a to NA() so Excel draws gaps rather than zeros.
A15: Model conventions | B15: Blue font = hard-coded SEC input; black = formula; yellow shading = instance/derived value; grey band = debt components; freeze panes, print titles, fit-to-width and footers on every tab; document properties set.
A16: Verification | B16: 948 formulas written; the workbook is recalculated in Excel via COM after the build and scanned for error values (#REF!, #DIV/0!, #NAME?, #VALUE!) – the only #N/A values are the intentional NA() chart gaps. Extraction is covered by 12 pytest checks (coverage, accounting identities, derivation tie-outs, segment sanity).
A17: ACCOUNTING POLICY & COMPARABILITY
A18: Revenue (ASC 606) | B18: Revenue = net sales per the income statement. Tag names changed at ASC 606 adoption (SalesRevenueNet / SalesRevenueGoodsNet → RevenueFromContractWithCustomerExcludingAssessedTax), so tags are tried in a per-company priority list held in config/companies.yaml. Costco reports 'Total revenue' = net sales + membership fees; this workbook uses NET SALES (the ProductMember disaggregated-revenue fact, SalesRevenueNet before 2018) so Costco's basis matches Walmart's and Sam's Club's net sales, which also exclude membership income. Membership fees ($5.3B FY2025) are a memo row: they carry no cost of sales, so on a total-revenue basis Costco's gross margin would read about two points higher.
A19: Leases (ASC 842) | B19: Adopted FY2019 (Costco FY2020). Operating lease liabilities are EXCLUDED from Total debt – including them would create a step-up in FY2019 with no financing event – and shown as a memo line and in the supplementary lease-inclusive debt-to-equity. Finance/capital leases are INCLUDED throughout because they were liabilities under ASC 840 too. Policy per company in config/debt_policy.yaml.
A20: Segments (ASC 280 / ASU 2023-07) | B20: Sam's Club figures are Walmart's reportable-segment disclosures (StatementBusinessSegmentsAxis = SamsClubUSMember, renamed from SamsClubMember in the FY2024 10-K). ASU 2023-07 required significant segment expenses from FY2024, which is why cost of revenue – and so gross margin – exists for FY2022–FY2025 only. Amazon's 'Physical stores' line is a disaggregated-revenue disclosure, not a segment, and includes more than Whole Foods.
A21: Inventory (LIFO vs FIFO) | B21: Walmart U.S. (retail method, LIFO), Sam's Club (weighted-average, LIFO), Costco U.S. (LIFO), Kroger (~91% LIFO, link-chain dollar-value) and Whole Foods (LIFO) all report cost of sales after a LIFO charge in inflationary years; Costco Canada and Walmart International are FIFO. In 2021–2023 LIFO raised reported cost of sales and depressed gross margin and inventory for the LIFO filers – Kroger's reserve grew from $1.3B (FY2016) to $2.6B (FY2025) and its LIFO charge was $157M in FY2025; Costco's FY2022 LIFO charge cost 19 bp of gross margin (~$0.4B), FY2023–FY2024 were immaterial, FY2025 7 bp. Effects: (a) gross margins for FY2021–FY2023 are understated relative to a FIFO basis, more so for Kroger; (b) current assets and therefore the current ratio are understated for LIFO filers; (c) only Kroger discloses a reserve balance – Walmart stated that LIFO approximated FIFO through January 2022 (FY2021) and has given only sensitivity language since; Costco discloses the annual charge but no reserve balance. Ratios are presented as reported and trends, rather than levels, are emphasised in the findings.
A22: Equity and net income | B22: Total equity includes noncontrolling interests (Walmart $6.3B FY2025); net income is the amount attributable to the parent. Debt-to-equity on a parent-only equity basis would be marginally higher for Walmart; no other company has material NCI.
A23: Whole Foods cost line | B23: 'Cost of goods sold and occupancy costs' includes store rent, so its gross margin is structurally lower than a pure merchandise margin and is not compared against peers on level – only its own two-year trend is used.
A24: 53-week years | B24: Costco and Kroger FY2023 had 53 weeks; growth in FY2023 is overstated and FY2024 understated by about 2 points. Walmart's January 31 year-end is fixed (no 53-week years).
A25: ASSUMPTIONS & LIMITS
A26: Assumptions | B26: Latest-filed values are the best available (restatements are accepted); segment operating income is comparable to consolidated operating income for margin purposes; Amazon 'Physical stores' is used as a revenue proxy for Whole Foods and labelled as such.
A27: Out of scope | B27: FIFO restatement of LIFO filers; adjustments for 53-week years; currency effects in Walmart International and Costco's non-U.S. operations; pro-forma treatment of Kroger's terminated Albertsons merger.
A28: TOOLS
A29: Pipeline | B29: Python 3 · requests (EDGAR) · lxml (XBRL instance parsing) · pandas (tidy tables) · PyYAML (company register and debt policy) · openpyxl (workbook generation) · pywin32 (Excel recalculation and error scan) · pytest · Git. Re-running src/pull_data.py, src/pull_segments.py and src/build_workbook.py regenerates this file from EDGAR end-to-end.
A30: Author | B30: Ryan Barry – personal portfolio project, September 2026. Public filings only; not an H-E-B work product.

Sheet Data Lineage
A1: 08 — DATA LINEAGE | Q1: COMPETITOR SCORECARD · FY2016–FY2025 · SEC 10-K DATA
A2: Data Lineage
A3: Every input value with its SEC citation – one row per value on Raw Data. 'Restated' = the latest-filed value differs from the first-filed value; both are shown. Links open the filing index on sec.gov.
A4: Company | B4: Line item | C4: Fiscal year | D4: Period start | E4: Period end | F4: Value (USD) | G4: XBRL tag / basis | H4: Dimension | I4: Accession no. | J4: Filed | K4: Status | L4: Restated | M4: First-filed value | N4: First filed | O4: Versions | P4: Note | Q4: EDGAR link
A5: AMZN→WFM | B5: Revenue (net sales) | C5: 2016 | D5: 2016-01-01 | E5: 2016-12-31 | F5: 0 | G5: us-gaap:RevenueFromContractWithCustomerExcludingAssessedTax | H5: srt:ProductOrServiceAxis = amzn:PhysicalStoresMember | I5: 0001018724-19-000004 | J5: 2019-02-01 | K5: ok | M5: 0 | N5: 2019-02-01 | O5: 1 | P5: Dimensional fact parsed from the 10-K XBRL instance (amzn-20181231.xml) | Q5: https://www.sec.gov/Archives/edgar/data/1018724/000101872419000004/
A6: AMZN→WFM | B6: Revenue (net sales) | C6: 2017 | D6: 2017-01-01 | E6: 2017-12-31 | F6: 5798000000 | G6: us-gaap:RevenueFromContractWithCustomerExcludingAssessedTax | H6: srt:ProductOrServiceAxis = amzn:PhysicalStoresMember | I6: 0001018724-20-000004 | J6: 2020-01-31 | K6: ok | M6: 5798000000 | N6: 2019-02-01 | O6: 2 | P6: Dimensional fact parsed from the 10-K XBRL instance (amzn-20191231x10k_htm.xml) | Q6: https://www.sec.gov/Archives/edgar/data/1018724/000101872420000004/
A7: AMZN→WFM | B7: Revenue (net sales) | C7: 2018 | D7: 2018-01-01 | E7: 2018-12-31 | F7: 17224000000 | G7: us-gaap:RevenueFromContractWithCustomerExcludingAssessedTax | H7: srt:ProductOrServiceAxis = amzn:PhysicalStoresMember | I7: 0001018724-21-000004 | J7: 2021-02-03 | K7: ok | M7: 17224000000 | N7: 2019-02-01 | O7: 3 | P7: Dimensional fact parsed from the 10-K XBRL instance (amzn-20201231_htm.xml) | Q7: https://www.sec.gov/Archives/edgar/data/1018724/000101872421000004/
A8: AMZN→WFM | B8: Revenue (net sales) | C8: 2019 | D8: 2019-01-01 | E8: 2019-12-31 | F8: 17192000000 | G8: us-gaap:RevenueFromContractWithCustomerExcludingAssessedTax | H8: srt:ProductOrServiceAxis = amzn:PhysicalStoresMember | I8: 0001018724-22-000005 | J8: 2022-02-04 | K8: ok | M8: 17192000000 | N8: 2020-01-31 | O8: 3 | P8: Dimensional fact parsed from the 10-K XBRL instance (amzn-20211231_htm.xml) | Q8: https://www.sec.gov/Archives/edgar/data/1018724/000101872422000005/
A9: AMZN→WFM | B9: Revenue (net sales) | C9: 2020 | D9: 2020-01-01 | E9: 2020-12-31 | F9: 16227000000 | G9: us-gaap:RevenueFromContractWithCustomerExcludingAssessedTax | H9: srt:ProductOrServiceAxis = amzn:PhysicalStoresMember | I9: 0001018724-23-000004 | J9: 2023-02-03 | K9: ok | M9: 16227000000 | N9: 2021-02-03 | O9: 3 | P9: Dimensional fact parsed from the 10-K XBRL instance (amzn-20221231_htm.xml) | Q9: https://www.sec.gov/Archives/edgar/data/1018724/000101872423000004/
A10: AMZN→WFM | B10: Revenue (net sales) | C10: 2021 | D10: 2021-01-01 | E10: 2021-12-31 | F10: 17075000000 | G10: us-gaap:RevenueFromContractWithCustomerExcludingAssessedTax | H10: srt:ProductOrServiceAxis = amzn:PhysicalStoresMember | I10: 0001018724-24-000008 | J10: 2024-02-02 | K10: ok | M10: 17075000000 | N10: 2022-02-04 | O10: 3 | P10: Dimensional fact parsed from the 10-K XBRL instance (amzn-20231231_htm.xml) | Q10: https://www.sec.gov/Archives/edgar/data/1018724/000101872424000008/
A11: AMZN→WFM | B11: Revenue (net sales) | C11: 2022 | D11: 2022-01-01 | E11: 2022-12-31 | F11: 18963000000 | G11: us-gaap:RevenueFromContractWithCustomerExcludingAssessedTax | H11: srt:ProductOrServiceAxis = amzn:PhysicalStoresMember | I11: 0001018724-25-000004 | J11: 2025-02-07 | K11: ok | M11: 18963000000 | N11: 2023-02-03 | O11: 3 | P11: Dimensional fact parsed from the 10-K XBRL instance (amzn-20241231_htm.xml) | Q11: https://www.sec.gov/Archives/edgar/data/1018724/000101872425000004/
A12: AMZN→WFM | B12: Revenue (net sales) | C12: 2023 | D12: 2023-01-01 | E12: 2023-12-31 | F12: 20030000000 | G12: us-gaap:RevenueFromContractWithCustomerExcludingAssessedTax | H12: srt:ProductOrServiceAxis = amzn:PhysicalStoresMember | I12: 0001018724-26-000004 | J12: 2026-02-06 | K12: ok | M12: 20030000000 | N12: 2024-02-02 | O12: 3 | P12: Dimensional fact parsed from the 10-K XBRL instance (amzn-20251231_htm.xml) | Q12: https://www.sec.gov/Archives/edgar/data/1018724/000101872426000004/
A13: AMZN→WFM | B13: Revenue (net sales) | C13: 2024 | D13: 2024-01-01 | E13: 2024-12-31 | F13: 21215000000 | G13: us-gaap:RevenueFromContractWithCustomerExcludingAssessedTax | H13: srt:ProductOrServiceAxis = amzn:PhysicalStoresMember | I13: 0001018724-26-000004 | J13: 2026-02-06 | K13: ok | M13: 21215000000 | N13: 2025-02-07 | O13: 2 | P13: Dimensional fact parsed from the 10-K XBRL instance (amzn-20251231_htm.xml) | Q13: https://www.sec.gov/Archives/edgar/data/1018724/000101872426000004/
A14: AMZN→WFM | B14: Revenue (net sales) | C14: 2025 | D14: 2025-01-01 | E14: 2025-12-31 | F14: 22561000000 | G14: us-gaap:RevenueFromContractWithCustomerExcludingAssessedTax | H14: srt:ProductOrServiceAxis = amzn:PhysicalStoresMember | I14: 0001018724-26-000004 | J14: 2026-02-06 | K14: ok | M14: 22561000000 | N14: 2026-02-06 | O14: 1 | P14: Dimensional fact parsed from the 10-K XBRL instance (amzn-20251231_htm.xml) | Q14: https://www.sec.gov/Archives/edgar/data/1018724/000101872426000004/
A15: Costco | B15: Cost of sales | C15: 2015 | D15: 2014-09-01 | E15: 2015-08-30 | F15: 101065000000 | G15: CostOfGoodsSold | I15: 0000909832-17-000014 | J15: 2017-10-18 | K15: ok | M15: 101065000000 | N15: 2015-10-14 | O15: 3 | Q15: https://www.sec.gov/Archives/edgar/data/909832/000090983217000014/
A16: Costco | B16: Cost of sales | C16: 2016 | D16: 2015-08-31 | E16: 2016-08-28 | F16: 102901000000 | G16: CostOfGoodsAndServicesSold | I16: 0000909832-18-000013 | J16: 2018-10-26 | K16: ok | M16: 102901000000 | N16: 2018-10-26 | O16: 1 | Q16: https://www.sec.gov/Archives/edgar/data/909832/000090983218000013/
A17: Costco | B17: Cost of sales | C17: 2017 | D17: 2016-08-29 | E17: 2017-09-03 | F17: 111882000000 | G17: CostOfGoodsAndServicesSold | I17: 0000909832-18-000013 | J17: 2018-10-26 | K17: ok | M17: 111882000000 | N17: 2018-10-26 | O17: 1 | Q17: https://www.sec.gov/Archives/edgar/data/909832/000090983218000013/
A18: Costco | B18: Cost of sales | C18: 2018 | D18: 2017-09-04 | E18: 2018-09-02 | F18: 123152000000 | G18: CostOfGoodsAndServicesSold | I18: 0000909832-20-000017 | J18: 2020-10-07 | K18: ok | M18: 123152000000 | N18: 2018-10-26 | O18: 2 | Q18: https://www.sec.gov/Archives/edgar/data/909832/000090983220000017/
A19: Costco | B19: Cost of sales | C19: 2019 | D19: 2018-09-03 | E19: 2019-09-01 | F19: 132886000000 | G19: CostOfGoodsAndServicesSold | I19: 0000909832-21-000014 | J19: 2021-10-06 | K19: ok | M19: 132886000000 | N19: 2020-10-07 | O19: 2 | Q19: https://www.sec.gov/Archives/edgar/data/909832/000090983221000014/
A20: Costco | B20: Cost of sales | C20: 2020 | D20: 2019-09-02 | E20: 2020-08-30 | F20: 144939000000 | G20: CostOfGoodsAndServicesSold | I20: 0000909832-22-000021 | J20: 2022-10-05 | K20: ok | M20: 144939000000 | N20: 2020-10-07 | O20: 3 | Q20: https://www.sec.gov/Archives/edgar/data/909832/000090983222000021/
A21: Costco | B21: Cost of sales | C21: 2021 | D21: 2020-08-31 | E21: 2021-08-29 | F21: 170684000000 | G21: CostOfGoodsAndServicesSold | I21: 0000909832-23-000042 | J21: 2023-10-11 | K21: ok | M21: 170684000000 | N21: 2021-10-06 | O21: 3 | Q21: https://www.sec.gov/Archives/edgar/data/909832/000090983223000042/
A22: Costco | B22: Cost of sales | C22: 2022 | D22: 2021-08-30 | E22: 2022-08-28 | F22: 199382000000 | G22: CostOfGoodsAndServicesSold | I22: 0000909832-24-000049 | J22: 2024-10-09 | K22: ok | M22: 199382000000 | N22: 2022-10-05 | O22: 3 | Q22: https://www.sec.gov/Archives/edgar/data/909832/000090983224000049/
A23: Costco | B23: Cost of sales | C23: 2023 | D23: 2022-08-29 | E23: 2023-09-03 | F23: 212586000000 | G23: CostOfGoodsAndServicesSold | I23: 0000909832-25-000101 | J23: 2025-10-08 | K23: ok | M23: 212586000000 | N23: 2023-10-11 | O23: 3 | Q23: https://www.sec.gov/Archives/edgar/data/909832/000090983225000101/
A24: Costco | B24: Cost of sales | C24: 2024 | D24: 2023-09-04 | E24: 2024-09-01 | F24: 222358000000 | G24: CostOfGoodsAndServicesSold | I24: 0000909832-25-000101 | J24: 2025-10-08 | K24: ok | M24: 222358000000 | N24: 2024-10-09 | O24: 2 | Q24: https://www.sec.gov/Archives/edgar/data/909832/000090983225000101/
A25: Costco | B25: Cost of sales | C25: 2025 | D25: 2024-09-02 | E25: 2025-08-31 | F25: 239886000000 | G25: CostOfGoodsAndServicesSold | I25: 0000909832-25-000101 | J25: 2025-10-08 | K25: ok | M25: 239886000000 | N25: 2025-10-08 | O25: 1 | Q25: https://www.sec.gov/Archives/edgar/data/909832/000090983225000101/
A26: Costco | B26: Current assets | C26: 2015 | E26: 2015-08-30 | F26: 16779000000 | G26: AssetsCurrent | I26: 0000909832-16-000032 | J26: 2016-10-12 | K26: ok | L26: yes | M26: 17299000000 | N26: 2015-10-14 | O26: 2 | Q26: https://www.sec.gov/Archives/edgar/data/909832/000090983216000032/
A27: Costco | B27: Current assets | C27: 2016 | E27: 2016-08-28 | F27: 15218000000 | G27: AssetsCurrent | I27: 0000909832-17-000014 | J27: 2017-10-18 | K27: ok | M27: 15218000000 | N27: 2016-10-12 | O27: 2 | Q27: https://www.sec.gov/Archives/edgar/data/909832/000090983217000014/
A28: Costco | B28: Current assets | C28: 2017 | E28: 2017-09-03 | F28: 17317000000 | G28: AssetsCurrent | I28: 0000909832-18-000013 | J28: 2018-10-26 | K28: ok | M28: 17317000000 | N28: 2017-10-18 | O28: 2 | Q28: https://www.sec.gov/Archives/edgar/data/909832/000090983218000013/
A29: Costco | B29: Current assets | C29: 2018 | E29: 2018-09-02 | F29: 20289000000 | G29: AssetsCurrent | I29: 0000909832-18-000013 | J29: 2018-10-26 | K29: ok | M29: 20289000000 | N29: 2018-10-26 | O29: 1 | Q29: https://www.sec.gov/Archives/edgar/data/909832/000090983218000013/
A30: Costco | B30: Current assets | C30: 2019 | E30: 2019-09-01 | F30: 23485000000 | G30: AssetsCurrent | I30: 0000909832-20-000017 | J30: 2020-10-07 | K30: ok | M30: 23485000000 | N30: 2020-10-07 | O30: 1 | Q30: https://www.sec.gov/Archives/edgar/data/909832/000090983220000017/
A31: Costco | B31: Current assets | C31: 2020 | E31: 2020-08-30 | F31: 28120000000 | G31: AssetsCurrent | I31: 0000909832-21-000014 | J31: 2021-10-06 | K31: ok | M31: 28120000000 | N31: 2020-10-07 | O31: 2 | Q31: https://www.sec.gov/Archives/edgar/data/909832/000090983221000014/
A32: Costco | B32: Current assets | C32: 2021 | E32: 2021-08-29 | F32: 29505000000 | G32: AssetsCurrent | I32: 0000909832-22-000021 | J32: 2022-10-05 | K32: ok | M32: 29505000000 | N32: 2021-10-06 | O32: 2 | Q32: https://www.sec.gov/Archives/edgar/data/909832/000090983222000021/
A33: Costco | B33: Current assets | C33: 2022 | E33: 2022-08-28 | F33: 32696000000 | G33: AssetsCurrent | I33: 0000909832-23-000042 | J33: 2023-10-11 | K33: ok | M33: 32696000000 | N33: 2022-10-05 | O33: 2 | Q33: https://www.sec.gov/Archives/edgar/data/909832/000090983223000042/
A34: Costco | B34: Current assets | C34: 2023 | E34: 2023-09-03 | F34: 35879000000 | G34: AssetsCurrent | I34: 0000909832-24-000049 | J34: 2024-10-09 | K34: ok | M34: 35879000000 | N34: 2023-10-11 | O34: 2 | Q34: https://www.sec.gov/Archives/edgar/data/909832/000090983224000049/
A35: Costco | B35: Current assets | C35: 2024 | E35: 2024-09-01 | F35: 34246000000 | G35: AssetsCurrent | I35: 0000909832-25-000101 | J35: 2025-10-08 | K35: ok | M35: 34246000000 | N35: 2024-10-09 | O35: 2 | Q35: https://www.sec.gov/Archives/edgar/data/909832/000090983225000101/
A36: Costco | B36: Current assets | C36: 2025 | E36: 2025-08-31 | F36: 38380000000 | G36: AssetsCurrent | I36: 0000909832-25-000101 | J36: 2025-10-08 | K36: ok | M36: 38380000000 | N36: 2025-10-08 | O36: 1 | Q36: https://www.sec.gov/Archives/edgar/data/909832/000090983225000101/
A37: Costco | B37: Current liabilities | C37: 2015 | E37: 2015-08-30 | F37: 16539000000 | G37: LiabilitiesCurrent | I37: 0000909832-16-000032 | J37: 2016-10-12 | K37: ok | L37: yes | M37: 16540000000 | N37: 2015-10-14 | O37: 2 | Q37: https://www.sec.gov/Archives/edgar/data/909832/000090983216000032/
A38: Costco | B38: Current liabilities | C38: 2016 | E38: 2016-08-28 | F38: 15575000000 | G38: LiabilitiesCurrent | I38: 0000909832-17-000014 | J38: 2017-10-18 | K38: ok | M38: 15575000000 | N38: 2016-10-12 | O38: 2 | Q38: https://www.sec.gov/Archives/edgar/data/909832/000090983217000014/
A39: Costco | B39: Current liabilities | C39: 2017 | E39: 2017-09-03 | F39: 17495000000 | G39: LiabilitiesCurrent | I39: 0000909832-18-000013 | J39: 2018-10-26 | K39: ok | M39: 17495000000 | N39: 2017-10-18 | O39: 2 | Q39: https://www.sec.gov/Archives/edgar/data/909832/000090983218000013/
A40: Costco | B40: Current liabilities | C40: 2018 | E40: 2018-09-02 | F40: 19926000000 | G40: LiabilitiesCurrent | I40: 0000909832-18-000013 | J40: 2018-10-26 | K40: ok | M40: 19926000000 | N40: 2018-10-26 | O40: 1 | Q40: https://www.sec.gov/Archives/edgar/data/909832/000090983218000013/
A41: Costco | B41: Current liabilities | C41: 2019 | E41: 2019-09-01 | F41: 23237000000 | G41: LiabilitiesCurrent | I41: 0000909832-20-000017 | J41: 2020-10-07 | K41: ok | M41: 23237000000 | N41: 2020-10-07 | O41: 1 | Q41: https://www.sec.gov/Archives/edgar/data/909832/000090983220000017/
A42: Costco | B42: Current liabilities | C42: 2020 | E42: 2020-08-30 | F42: 24844000000 | G42: LiabilitiesCurrent | I42: 0000909832-21-000014 | J42: 2021-10-06 | K42: ok | M42: 24844000000 | N42: 2020-10-07 | O42: 2 | Q42: https://www.sec.gov/Archives/edgar/data/909832/000090983221000014/
A43: Costco | B43: Current liabilities | C43: 2021 | E43: 2021-08-29 | F43: 29441000000 | G43: LiabilitiesCurrent | I43: 0000909832-22-000021 | J43: 2022-10-05 | K43: ok | M43: 29441000000 | N43: 2021-10-06 | O43: 2 | Q43: https://www.sec.gov/Archives/edgar/data/909832/000090983222000021/
A44: Costco | B44: Current liabilities | C44: 2022 | E44: 2022-08-28 | F44: 31998000000 | G44: LiabilitiesCurrent | I44: 0000909832-23-000042 | J44: 2023-10-11 | K44: ok | M44: 31998000000 | N44: 2022-10-05 | O44: 2 | Q44: https://www.sec.gov/Archives/edgar/data/909832/000090983223000042/
A45: Costco | B45: Current liabilities | C45: 2023 | E45: 2023-09-03 | F45: 33583000000 | G45: LiabilitiesCurrent | I45: 0000909832-24-000049 | J45: 2024-10-09 | K45: ok | M45: 33583000000 | N45: 2023-10-11 | O45: 2 | Q45: https://www.sec.gov/Archives/edgar/data/909832/000090983224000049/
A46: Costco | B46: Current liabilities | C46: 2024 | E46: 2024-09-01 | F46: 35464000000 | G46: LiabilitiesCurrent | I46: 0000909832-25-000101 | J46: 2025-10-08 | K46: ok | M46: 35464000000 | N46: 2024-10-09 | O46: 2 | Q46: https://www.sec.gov/Archives/edgar/data/909832/000090983225000101/
A47: Costco | B47: Current liabilities | C47: 2025 | E47: 2025-08-31 | F47: 37108000000 | G47: LiabilitiesCurrent | I47: 0000909832-25-000101 | J47: 2025-10-08 | K47: ok | M47: 37108000000 | N47: 2025-10-08 | O47: 1 | Q47: https://www.sec.gov/Archives/edgar/data/909832/000090983225000101/
A48: Costco | B48: Stockholders' equity – parent only (reference) | C48: 2015 | E48: 2015-08-30 | F48: 10617000000 | G48: StockholdersEquity | I48: 0000909832-16-000032 | J48: 2016-10-12 | K48: ok | M48: 10617000000 | N48: 2015-10-14 | O48: 2 | Q48: https://www.sec.gov/Archives/edgar/data/909832/000090983216000032/
A49: Costco | B49: Stockholders' equity – parent only (reference) | C49: 2016 | E49: 2016-08-28 | F49: 12079000000 | G49: StockholdersEquity | I49: 0000909832-17-000014 | J49: 2017-10-18 | K49: ok | M49: 12079000000 | N49: 2016-10-12 | O49: 2 | Q49: https://www.sec.gov/Archives/edgar/data/909832/000090983217000014/
... A62: Costco | B62: Finance / capital lease liability – current | C62: 2018 | E62: 2018-09-02 | F62: 7000000 | G62: CapitalLeaseObligationsCurrent | I62: 0000909832-18-000013 | J62: 2018-10-26 | K62: ok | M62: 7000000 | N62: 2018-10-26 | O62: 1 | Q62: https://www.sec.gov/Archives/edgar/data/909832/000090983218000013/
A63: Costco | B63: Finance / capital lease liability – current | C63: 2019 | E63: 2019-09-01 | F63: 26000000 | G63: CapitalLeaseObligationsCurrent | I63: 0000909832-19-000019 | J63: 2019-10-11 | K63: instance | L63: yes | P63: Tagged in the FY2019 10-K XBRL instance (cost-20190901.xml, context FI2019Q4) but absent from the companyfacts API; ASC 840 capital lease, pre-842 adoption. | Q63: https://www.sec.gov/Archives/edgar/data/909832/000090983219000019/
A64: Costco | B64: Finance / capital lease liability – current | C64: 2020 | E64: 2020-08-30 | F64: 31000000 | G64: FinanceLeaseLiabilityCurrent | I64: 0000909832-20-000017 | J64: 2020-10-07 | K64: ok | M64: 31000000 | N64: 2020-10-07 | O64: 1 | Q64: https://www.sec.gov/Archives/edgar/data/909832/000090983220000017/
A65: Costco | B65: Finance / capital lease liability – current | C65: 2024 | E65: 2024-09-01 | F65: 147000000 | G65: FinanceLeaseLiabilityCurrent | I65: 0000909832-25-000101 | J65: 2025-10-08 | K65: ok | M65: 147000000 | N65: 2025-10-08 | O65: 1 | Q65: https://www.sec.gov/Archives/edgar/data/909832/000090983225000101/
A66: Costco | B66: Finance / capital lease liability – current | C66: 2025 | E66: 2025-08-31 | F66: 78000000 | G66: FinanceLeaseLiabilityCurrent | I66: 0000909832-25-000101 | J66: 2025-10-08 | K66: ok | M66: 78000000 | N66: 2025-10-08 | O66: 1 | Q66: https://www.sec.gov/Archives/edgar/data/909832/000090983225000101/
A67: Costco | B67: Finance / capital lease liability – non-current | C67: 2015 | E67: 2015-08-30 | F67: 286000000 | G67: CapitalLeaseObligationsNoncurrent | I67: 0000909832-15-000014 | J67: 2015-10-14 | K67: ok | M67: 286000000 | N67: 2015-10-14 | O67: 1 | Q67: https://www.sec.gov/Archives/edgar/data/909832/000090983215000014/
A68: Costco | B68: Finance / capital lease liability – non-current | C68: 2016 | E68: 2016-08-28 | F68: 364000000 | G68: CapitalLeaseObligationsNoncurrent | I68: 0000909832-16-000032 | J68: 2016-10-12 | K68: ok | M68: 364000000 | N68: 2016-10-12 | O68: 1 | Q68: https://www.sec.gov/Archives/edgar/data/909832/000090983216000032/
A69: Costco | B69: Finance / capital lease liability – non-current | C69: 2017 | E69: 2017-09-03 | F69: 373000000 | G69: CapitalLeaseObligationsNoncurrent | I69: 0000909832-17-000014 | J69: 2017-10-18 | K69: ok | M69: 373000000 | N69: 2017-10-18 | O69: 1 | Q69: https://www.sec.gov/Archives/edgar/data/909832/000090983217000014/
A70: Costco | B70: Finance / capital lease liability – non-current | C70: 2018 | E70: 2018-09-02 | F70: 390000000 | G70: CapitalLeaseObligationsNoncurrent | I70: 0000909832-18-000013 | J70: 2018-10-26 | K70: ok | M70: 390000000 | N70: 2018-10-26 | O70: 1 | Q70: https://www.sec.gov/Archives/edgar/data/909832/000090983218000013/
A71: Costco | B71: Finance / capital lease liability – non-current | C71: 2019 | E71: 2019-09-01 | F71: 395000000 | G71: CapitalLeaseObligationsNoncurrent | I71: 0000909832-19-000019 | J71: 2019-10-11 | K71: instance | L71: yes | P71: Tagged in the FY2019 10-K XBRL instance (cost-20190901.xml, context FI2019Q4) but absent from the companyfacts API; ties to CapitalLeasesFutureMinimumPaymentsPresentValueOfNetMinimumPayments 421M. | Q71: https://www.sec.gov/Archives/edgar/data/909832/000090983219000019/
A72: Costco | B72: Finance / capital lease liability – non-current | C72: 2020 | E72: 2020-08-30 | F72: 657000000 | G72: FinanceLeaseLiabilityNoncurrent | I72: 0000909832-20-000017 | J72: 2020-10-07 | K72: ok | M72: 657000000 | N72: 2020-10-07 | O72: 1 | Q72: https://www.sec.gov/Archives/edgar/data/909832/000090983220000017/
A73: Costco | B73: Finance / capital lease liability – non-current | C73: 2024 | E73: 2024-09-01 | F73: 1351000000 | G73: FinanceLeaseLiabilityNoncurrent | I73: 0000909832-25-000101 | J73: 2025-10-08 | K73: ok | M73: 1351000000 | N73: 2025-10-08 | O73: 1 | Q73: https://www.sec.gov/Archives/edgar/data/909832/000090983225000101/
A74: Costco | B74: Finance / capital lease liability – non-current | C74: 2025 | E74: 2025-08-31 | F74: 1401000000 | G74: FinanceLeaseLiabilityNoncurrent | I74: 0000909832-25-000101 | J74: 2025-10-08 | K74: ok | M74: 1401000000 | N74: 2025-10-08 | O74: 1 | Q74: https://www.sec.gov/Archives/edgar/data/909832/000090983225000101/
A75: Costco | B75: Finance lease liability – total (years not split on the balance sheet) | C75: 2020 | E75: 2020-08-30 | F75: 688000000 | G75: FinanceLeaseLiability | I75: 0000909832-20-000017 | J75: 2020-10-07 | K75: ok | M75: 688000000 | N75: 2020-10-07 | O75: 1 | Q75: https://www.sec.gov/Archives/edgar/data/909832/000090983220000017/
A76: Costco | B76: Finance lease liability – total (years not split on the balance sheet) | C76: 2021 | E76: 2021-08-29 | F76: 1052000000 | G76: FinanceLeaseLiability | I76: 0000909832-21-000014 | J76: 2021-10-06 | K76: ok | M76: 1052000000 | N76: 2021-10-06 | O76: 1 | Q76: https://www.sec.gov/Archives/edgar/data/909832/000090983221000014/
A77: Costco | B77: Finance lease liability – total (years not split on the balance sheet) | C77: 2022 | E77: 2022-08-28 | F77: 1628000000 | G77: FinanceLeaseLiabilityPaymentsDue - FinanceLeaseLiabilityUndiscountedExcessAmount | I77: 0000909832-22-000021 | J77: 2022-10-05 | K77: derived | L77: yes | P77: Finance lease liability not tagged as a balance; derived as undiscounted payments less imputed interest (both us-gaap tagged, Leases note). Costco carries finance leases inside other current / other long-term liabilities. | Q77: https://www.sec.gov/Archives/edgar/data/909832/000090983222000021/
A78: Costco | B78: Finance lease liability – total (years not split on the balance sheet) | C78: 2023 | E78: 2023-09-03 | F78: 1432000000 | G78: FinanceLeaseLiabilityPaymentsDue - FinanceLeaseLiabilityUndiscountedExcessAmount | I78: 0000909832-23-000042 | J78: 2023-10-11 | K78: derived | L78: yes | P78: Same derivation as FY2022; ties to cost:OperatingLeaseandFinanceLeaseLiabilities 4078M less OperatingLeaseLiability 2646M = 1432M in the same filing. | Q78: https://www.sec.gov/Archives/edgar/data/909832/000090983223000042/
A79: Costco | B79: Finance lease liability – total (years not split on the balance sheet) | C79: 2025 | E79: 2025-08-31 | F79: 1479000000 | G79: FinanceLeaseLiability | I79: 0000909832-25-000101 | J79: 2025-10-08 | K79: ok | M79: 1479000000 | N79: 2025-10-08 | O79: 1 | Q79: https://www.sec.gov/Archives/edgar/data/909832/000090983225000101/
A80: Costco | B80: Inventory | C80: 2015 | E80: 2015-08-30 | F80: 8908000000 | G80: InventoryNet | I80: 0000909832-16-000032 | J80: 2016-10-12 | K80: ok | M80: 8908000000 | N80: 2015-10-14 | O80: 2 | Q80: https://www.sec.gov/Archives/edgar/data/909832/000090983216000032/
A81: Costco | B81: Inventory | C81: 2016 | E81: 2016-08-28 | F81: 8969000000 | G81: InventoryNet | I81: 0000909832-17-000014 | J81: 2017-10-18 | K81: ok | M81: 8969000000 | N81: 2016-10-12 | O81: 2 | Q81: https://www.sec.gov/Archives/edgar/data/909832/000090983217000014/
A82: Costco | B82: Inventory | C82: 2017 | E82: 2017-09-03 | F82: 9834000000 | G82: InventoryNet | I82: 0000909832-18-000013 | J82: 2018-10-26 | K82: ok | M82: 9834000000 | N82: 2017-10-18 | O82: 2 | Q82: https://www.sec.gov/Archives/edgar/data/909832/000090983218000013/
A83: Costco | B83: Inventory | C83: 2018 | E83: 2018-09-02 | F83: 11040000000 | G83: InventoryNet | I83: 0000909832-18-000013 | J83: 2018-10-26 | K83: ok | M83: 11040000000 | N83: 2018-10-26 | O83: 1 | Q83: https://www.sec.gov/Archives/edgar/data/909832/000090983218000013/
A84: Costco | B84: Inventory | C84: 2019 | E84: 2019-09-01 | F84: 11395000000 | G84: InventoryNet | I84: 0000909832-20-000017 | J84: 2020-10-07 | K84: ok | M84: 11395000000 | N84: 2020-10-07 | O84: 1 | Q84: https://www.sec.gov/Archives/edgar/data/909832/000090983220000017/
A85: Costco | B85: Inventory | C85: 2020 | E85: 2020-08-30 | F85: 12242000000 | G85: InventoryNet | I85: 0000909832-21-000014 | J85: 2021-10-06 | K85: ok | M85: 12242000000 | N85: 2020-10-07 | O85: 2 | Q85: https://www.sec.gov/Archives/edgar/data/909832/000090983221000014/
A86: Costco | B86: Inventory | C86: 2021 | E86: 2021-08-29 | F86: 14215000000 | G86: InventoryNet | I86: 0000909832-22-000021 | J86: 2022-10-05 | K86: ok | M86: 14215000000 | N86: 2021-10-06 | O86: 2 | Q86: https://www.sec.gov/Archives/edgar/data/909832/000090983222000021/
A87: Costco | B87: Inventory | C87: 2022 | E87: 2022-08-28 | F87: 17907000000 | G87: InventoryNet | I87: 0000909832-23-000042 | J87: 2023-10-11 | K87: ok | M87: 17907000000 | N87: 2022-10-05 | O87: 2 | Q87: https://www.sec.gov/Archives/edgar/data/909832/000090983223000042/
A88: Costco | B88: Inventory | C88: 2023 | E88: 2023-09-03 | F88: 16651000000 | G88: InventoryNet | I88: 0000909832-24-000049 | J88: 2024-10-09 | K88: ok | M88: 16651000000 | N88: 2023-10-11 | O88: 2 | Q88: https://www.sec.gov/Archives/edgar/data/909832/000090983224000049/
A89: Costco | B89: Inventory | C89: 2024 | E89: 2024-09-01 | F89: 18647000000 | G89: InventoryNet | I89: 0000909832-25-000101 | J89: 2025-10-08 | K89: ok | M89: 18647000000 | N89: 2024-10-09 | O89: 2 | Q89: https://www.sec.gov/Archives/edgar/data/909832/000090983225000101/
A90: Costco | B90: Inventory | C90: 2025 | E90: 2025-08-31 | F90: 18116000000 | G90: InventoryNet | I90: 0000909832-25-000101 | J90: 2025-10-08 | K90: ok | M90: 18116000000 | N90: 2025-10-08 | O90: 1 | Q90: https://www.sec.gov/Archives/edgar/data/909832/000090983225000101/
... A103: Costco | B103: Long-term debt – due within one year | C103: 2025 | E103: 2025-08-31 | F103: 75000000 | G103: LongTermDebtCurrent | I103: 0000909832-25-000101 | J103: 2025-10-08 | K103: ok | M103: 75000000 | N103: 2025-10-08 | O103: 1 | Q103: https://www.sec.gov/Archives/edgar/data/909832/000090983225000101/
A104: Costco | B104: Long-term debt – non-current | C104: 2015 | E104: 2015-08-30 | F104: 4852000000 | G104: LongTermDebtNoncurrent | I104: 0000909832-16-000032 | J104: 2016-10-12 | K104: ok | L104: yes | M104: 4864000000 | N104: 2015-10-14 | O104: 2 | Q104: https://www.sec.gov/Archives/edgar/data/909832/000090983216000032/
A105: Costco | B105: Long-term debt – non-current | C105: 2016 | E105: 2016-08-28 | F105: 4061000000 | G105: LongTermDebtNoncurrent | I105: 0000909832-17-000014 | J105: 2017-10-18 | K105: ok | M105: 4061000000 | N105: 2016-10-12 | O105: 2 | Q105: https://www.sec.gov/Archives/edgar/data/909832/000090983217000014/
A106: Costco | B106: Long-term debt – non-current | C106: 2017 | E106: 2017-09-03 | F106: 6573000000 | G106: LongTermDebtNoncurrent | I106: 0000909832-18-000013 | J106: 2018-10-26 | K106: ok | M106: 6573000000 | N106: 2017-10-18 | O106: 2 | Q106: https://www.sec.gov/Archives/edgar/data/909832/000090983218000013/
A107: Costco | B107: Long-term debt – non-current | C107: 2018 | E107: 2018-09-02 | F107: 6487000000 | G107: LongTermDebtNoncurrent | I107: 0000909832-18-000013 | J107: 2018-10-26 | K107: ok | M107: 6487000000 | N107: 2018-10-26 | O107: 1 | Q107: https://www.sec.gov/Archives/edgar/data/909832/000090983218000013/
A108: Costco | B108: Long-term debt – non-current | C108: 2019 | E108: 2019-09-01 | F108: 5124000000 | G108: LongTermDebtNoncurrent | I108: 0000909832-20-000017 | J108: 2020-10-07 | K108: ok | M108: 5124000000 | N108: 2020-10-07 | O108: 1 | Q108: https://www.sec.gov/Archives/edgar/data/909832/000090983220000017/
A109: Costco | B109: Long-term debt – non-current | C109: 2020 | E109: 2020-08-30 | F109: 7514000000 | G109: LongTermDebtNoncurrent | I109: 0000909832-21-000014 | J109: 2021-10-06 | K109: ok | M109: 7514000000 | N109: 2020-10-07 | O109: 2 | Q109: https://www.sec.gov/Archives/edgar/data/909832/000090983221000014/
A110: Costco | B110: Long-term debt – non-current | C110: 2021 | E110: 2021-08-29 | F110: 6692000000 | G110: LongTermDebtNoncurrent | I110: 0000909832-22-000021 | J110: 2022-10-05 | K110: ok | M110: 6692000000 | N110: 2021-10-06 | O110: 2 | Q110: https://www.sec.gov/Archives/edgar/data/909832/000090983222000021/
A111: Costco | B111: Long-term debt – non-current | C111: 2022 | E111: 2022-08-28 | F111: 6484000000 | G111: LongTermDebtNoncurrent | I111: 0000909832-23-000042 | J111: 2023-10-11 | K111: ok | M111: 6484000000 | N111: 2022-10-05 | O111: 2 | Q111: https://www.sec.gov/Archives/edgar/data/909832/000090983223000042/
A112: Costco | B112: Long-term debt – non-current | C112: 2023 | E112: 2023-09-03 | F112: 5377000000 | G112: LongTermDebtNoncurrent | I112: 0000909832-24-000049 | J112: 2024-10-09 | K112: ok | M112: 5377000000 | N112: 2023-10-11 | O112: 2 | Q112: https://www.sec.gov/Archives/edgar/data/909832/000090983224000049/
A113: Costco | B113: Long-term debt – non-current | C113: 2024 | E113: 2024-09-01 | F113: 5794000000 | G113: LongTermDebtNoncurrent | I113: 0000909832-25-000101 | J113: 2025-10-08 | K113: ok | M113: 5794000000 | N113: 2024-10-09 | O113: 2 | Q113: https://www.sec.gov/Archives/edgar/data/909832/000090983225000101/
A114: Costco | B114: Long-term debt – non-current | C114: 2025 | E114: 2025-08-31 | F114: 5713000000 | G114: LongTermDebtNoncurrent | I114: 0000909832-25-000101 | J114: 2025-10-08 | K114: ok | M114: 5713000000 | N114: 2025-10-08 | O114: 1 | Q114: https://www.sec.gov/Archives/edgar/data/909832/000090983225000101/
A115: Costco | B115: Net income | C115: 2015 | D115: 2014-09-01 | E115: 2015-08-30 | F115: 2377000000 | G115: NetIncomeLoss | I115: 0000909832-17-000014 | J115: 2017-10-18 | K115: ok | M115: 2377000000 | N115: 2015-10-14 | O115: 3 | Q115: https://www.sec.gov/Archives/edgar/data/909832/000090983217000014/
A116: Costco | B116: Net income | C116: 2016 | D116: 2015-08-31 | E116: 2016-08-28 | F116: 2350000000 | G116: NetIncomeLoss | I116: 0000909832-18-000013 | J116: 2018-10-26 | K116: ok | M116: 2350000000 | N116: 2016-10-12 | O116: 3 | Q116: https://www.sec.gov/Archives/edgar/data/909832/000090983218000013/
A117: Costco | B117: Net income | C117: 2017 | D117: 2016-08-29 | E117: 2017-09-03 | F117: 2679000000 | G117: NetIncomeLoss | I117: 0000909832-18-000013 | J117: 2018-10-26 | K117: ok | M117: 2679000000 | N117: 2017-10-18 | O117: 2 | Q117: https://www.sec.gov/Archives/edgar/data/909832/000090983218000013/
A118: Costco | B118: Net income | C118: 2018 | D118: 2017-09-04 | E118: 2018-09-02 | F118: 3134000000 | G118: NetIncomeLoss | I118: 0000909832-20-000017 | J118: 2020-10-07 | K118: ok | M118: 3134000000 | N118: 2018-10-26 | O118: 2 | Q118: https://www.sec.gov/Archives/edgar/data/909832/000090983220000017/
A119: Costco | B119: Net income | C119: 2019 | D119: 2018-09-03 | E119: 2019-09-01 | F119: 3659000000 | G119: NetIncomeLoss | I119: 0000909832-21-000014 | J119: 2021-10-06 | K119: ok | M119: 3659000000 | N119: 2020-10-07 | O119: 2 | Q119: https://www.sec.gov/Archives/edgar/data/909832/000090983221000014/
A120: Costco | B120: Net income | C120: 2020 | D120: 2019-09-02 | E120: 2020-08-30 | F120: 4002000000 | G120: NetIncomeLoss | I120: 0000909832-22-000021 | J120: 2022-10-05 | K120: ok | M120: 4002000000 | N120: 2020-10-07 | O120: 3 | Q120: https://www.sec.gov/Archives/edgar/data/909832/000090983222000021/
A121: Costco | B121: Net income | C121: 2021 | D121: 2020-08-31 | E121: 2021-08-29 | F121: 5007000000 | G121: NetIncomeLoss | I121: 0000909832-23-000042 | J121: 2023-10-11 | K121: ok | M121: 5007000000 | N121: 2021-10-06 | O121: 3 | Q121: https://www.sec.gov/Archives/edgar/data/909832/000090983223000042/
A122: Costco | B122: Net income | C122: 2022 | D122: 2021-08-30 | E122: 2022-08-28 | F122: 5844000000 | G122: NetIncomeLoss | I122: 0000909832-24-000049 | J122: 2024-10-09 | K122: ok | M122: 5844000000 | N122: 2022-10-05 | O122: 3 | Q122: https://www.sec.gov/Archives/edgar/data/909832/000090983224000049/
A123: Costco | B123: Net income | C123: 2023 | D123: 2022-08-29 | E123: 2023-09-03 | F123: 6292000000 | G123: NetIncomeLoss | I123: 0000909832-25-000101 | J123: 2025-10-08 | K123: ok | M123: 6292000000 | N123: 2023-10-11 | O123: 3 | Q123: https://www.sec.gov/Archives/edgar/data/909832/000090983225000101/
A124: Costco | B124: Net income | C124: 2024 | D124: 2023-09-04 | E124: 2024-09-01 | F124: 7367000000 | G124: NetIncomeLoss | I124: 0000909832-25-000101 | J124: 2025-10-08 | K124: ok | M124: 7367000000 | N124: 2024-10-09 | O124: 2 | Q124: https://www.sec.gov/Archives/edgar/data/909832/000090983225000101/
...
